Workbook

Sheet Dashboard
B1: CartNest: payment gateway reconciliation, September 2026
B2: All figures in INR, read live from the bridge, batch_recon, orders and mdr_check sheets (same numbers as Part A).
B4: SALES PER ORDERS | E4: CASH RECEIVED IN BANK | H4: TOTAL GAP | K4: UNEXPLAINED
B5: =bridge!B4 -> 19894293 | E5: =bridge!B19 -> 16984049 | H5: =bridge!B26 -> 2910244.4 | K5: =bridge!B27 -> 0
B6: Paid + Refunded orders | E6: 27 gateway settlements, 1-30 Sep | H6: Sales less cash in bank | K6: =IF(bridge!B27=0,"Gap fully explained by the bridge","CHECK THE BRIDGE") -> Gap fully explained by the bridge
B8: TIMING: DUE IN OCTOBER | E8: STILL OWED BY GATEWAY | H8: EXCESS FEES TO RECOVER | K8: REFUNDS PAID TO CUSTOMERS
B9: =-bridge!B16 -> 1265526.9 | E9: =-(bridge!B17+bridge!B18) -> 552324.03 | H9: =-bridge!B14 -> 1185.2 | K9: =-bridge!B11 -> 893888
B10: Batches STL-20261001 and -02 | E10: 1 missing batch + 1 short-paid batch | H10: MDR + GST charged above rate card | K10: 243 refunds, not a loss
B12: 1. Bridge: sales per orders to cash in bank
B32: Blue = totals, green = adds to cash, red = takes away from cash. Fee overcharge (₹1,185) and short-paid (₹1,250) are too small to see; see the tables below.
B34: 2. Where the gap comes from (largest first)
B35: Item | E35: Amount (INR) | F35: % of gap | G35: Nature
B36: Due in October (timing) | E36: =-bridge!B16 -> 1265526.9 | F36: =E36/$E$47 -> 0.43485244 | G36: Timing: arrives 1-2 Oct
B37: Refunds paid to customers | E37: =-bridge!B11 -> 893888 | F37: =E37/$E$47 -> 0.30715221 | G37: Expected: money returned
B38: Missing settlement STL-20260912 | E38: =-bridge!B17 -> 551074.03 | F38: =E38/$E$47 -> 0.18935661 | G38: Genuine: chase gateway
B39: Gateway fees at correct rate | E39: =-(bridge!B12+bridge!B13) -> 205776.31 | F39: =E39/$E$47 -> 0.070707569 | G39: Expected: cost of payments
B40: Paid orders with no payment | E40: =-bridge!B5 -> 67617 | F40: =E40/$E$47 -> 0.023234131 | G40: Genuine: investigate orders
B41: Amount differences | E41: =-bridge!B6 -> 3145 | F41: =E41/$E$47 -> 0.0010806652 | G41: Genuine: gateway collected less
B42: Short-paid batch STL-20260911 | E42: =-bridge!B18 -> 1250 | F42: =E42/$E$47 -> 0.00042951719 | G42: Genuine: chase gateway
B43: Excess MDR + GST charged | E43: =-bridge!B14 -> 1185.2 | F43: =E43/$E$47 -> 0.00040725101 | G43: Genuine: recover from gateway
B44: Payments with no order | E44: =-bridge!B8 -> -24992 | F44: =E44/$E$47 -> -0.0085875948 | G44: Offsets gap: identify payer
B45: Duplicate charges | E45: =-bridge!B7 -> -25539 | F45: =E45/$E$47 -> -0.0087755515 | G45: Offsets gap: refund customers
B46: Payments on Failed/Cancelled orders | E46: =-bridge!B9 -> -28687 | F46: =E46/$E$47 -> -0.0098572476 | G46: Offsets gap: refund customers
B47: Total gap | E47: =SUM(E36:E46) -> 2910244.4 | F47: =SUM(F36:F46) -> 1 | G47: =IF(ROUND(E47-bridge!B26,2)=0,"Agrees with bridge","DOES NOT AGREE") -> Agrees with bridge
B50: 3. Exceptions by type (count and rupee value)
B51: Exception | E51: Count | F51: Value (INR) | G51: Nature
B52: Due in October (batches) | E52: =COUNTIF(batch_recon!F:F,"Due in October") -> 2 | F52: =-bridge!B16 -> 1265526.9 | G52: Timing
B53: Missing settlement (batches) | E53: =COUNTIF(batch_recon!F:F,"Missing") -> 1 | F53: =-bridge!B17 -> 551074.03 | G53: Genuine: chase gateway
B54: Paid orders with no payment | E54: =COUNTIF(orders!N:N,"Paid, no payment") -> 20 | F54: =SUMIF(orders!N:N,"Paid, no payment",orders!O:O) -> 67617 | G54: Genuine: investigate
B55: Refunded orders with no refund | E55: =COUNTIF(orders!N:N,"Refunded, no refund") -> 6 | F55: =SUMIF(orders!N:N,"Refunded, no refund",orders!O:O) -> 29889 | G55: Customer refund due
B56: Payments on Failed/Cancelled orders | E56: =COUNTIF(orders!N:N,"Payment on failed/cancelled") -> 8 | F56: =SUMIF(orders!N:N,"Payment on failed/cancelled",orders!O:O) -> 28687 | G56: Customer refund due
B57: Duplicate charges (extra amount) | E57: =COUNTIF(orders!N:N,"Duplicate charge") -> 6 | F57: =SUMIF(orders!N:N,"Duplicate charge",orders!O:O) -> 25539 | G57: Customer refund due
B58: Payments with no order | E58: =COUNTIF(pg_transaction_cleaned!Q:Q,"NO ORDER") -> 8 | F58: =SUMIFS(pg_transaction_cleaned!H:H,pg_transaction_cleaned!Q:Q,"NO ORDER") -> 24992 | G58: Identify payer
B59: Refund given, order not Refunded | E59: =COUNTIF(orders!N:N,"Refund, order not Refunded") -> 7 | F59: =SUMIF(orders!N:N,"Refund, order not Refunded",orders!O:O) -> 13886 | G59: Fix order status
B60: Amount differences | E60: =COUNTIF(orders!N:N,"Amount difference") -> 15 | F60: =ABS(SUMIF(orders!N:N,"Amount difference",orders!O:O)) -> 3145 | G60: Genuine: gateway lower
B61: Short-paid settlement (batches) | E61: =COUNTIF(batch_recon!F:F,"Short-paid") -> 1 | F61: =-bridge!B18 -> 1250 | G61: Genuine: chase gateway
B62: MDR + GST overcharge (payments) | E62: =COUNTIF(mdr_check!L:L,">0") -> 55 | F62: =SUM(mdr_check!L:L) -> 1185.2 | G62: Genuine: recover
B63: Refund amount differs from order | E63: =COUNTIF(orders!N:N,"Refund amount differs") -> 0 | F63: =SUMIF(orders!N:N,"Refund amount differs",orders!O:O) -> 0 | G63: None found
B65: Counts are orders or payments, except rows marked batches (settlement batches). Value for duplicates is the extra amount charged.
B67: 4. Daily settlements vs bank receipts
B86: No orange bar = no bank credit: 12 Sep is the missing batch, 1-2 Oct are due in October. 11 Sep is short by ₹1,250 (too small to see here).
B88: 5. Insights
B89: ="1. Fee overcharges sit in two places only. UPI payments of ₹2,000 or less should cost nothing, yet "&D91&" were charged "&TEXT(F91,"0.0%")&"; "&D92&" Wallet payments above ₹2,000 were charged "&TEXT(F92,"0.0%")&" instead of "&TEXT(G92,"0.0%")&". Together ₹"&TEXT(E91+E92,"#,##0.00")&" (MDR + GST) is recoverable from the gateway. Card and NetBanking are charged correctly." -> 1. Fee overcharges sit in two places only. UPI payments of ₹2,000 or less should cost nothing, yet 25 were charged 0.3%; 30 Wallet payments above ₹2,000 were charged 2.4% instead of 1.7%. Together ₹1,185.20 (MDR + GST) is recoverable from the gateway. Card and NetBanking are charged correctly.
B90: Payment method | D90: Payments overcharged | E90: Excess (INR) | F90: Charged rate | G90: Correct rate | H90: Where
B91: UPI | D91: =COUNTIFS(mdr_check!B:B,B91,mdr_check!L:L,">0") -> 25 | E91: =SUMIFS(mdr_check!L:L,mdr_check!B:B,B91) -> 73.9 | F91: =IFERROR(SUMIFS(mdr_check!D:D,mdr_check!B:B,B91,mdr_check!L:L,">0")/SUMIFS(mdr_check!C:C,mdr_check!B:B,B91,mdr_check!L:L,">0"),"-") -> 0.0030022519 | G91: =IFERROR(SUMIFS(mdr_check!H:H,mdr_check!B:B,B91,mdr_check!L:L,">0")/SUMIFS(mdr_check!C:C,mdr_check!B:B,B91,mdr_check!L:L,">0"),"-") -> 0 | H91: Payments of ₹2,000 or less
B92: Wallet | D92: =COUNTIFS(mdr_check!B:B,B92,mdr_check!L:L,">0") -> 30 | E92: =SUMIFS(mdr_check!L:L,mdr_check!B:B,B92) -> 1111.3 | F92: =IFERROR(SUMIFS(mdr_check!D:D,mdr_check!B:B,B92,mdr_check!L:L,">0")/SUMIFS(mdr_check!C:C,mdr_check!B:B,B92,mdr_check!L:L,">0"),"-") -> 0.024000119 | G92: =IFERROR(SUMIFS(mdr_check!H:H,mdr_check!B:B,B92,mdr_check!L:L,">0")/SUMIFS(mdr_check!C:C,mdr_check!B:B,B92,mdr_check!L:L,">0"),"-") -> 0.01700032 | H92: Payments above ₹2,000
B93: Card | D93: =COUNTIFS(mdr_check!B:B,B93,mdr_check!L:L,">0") -> 0 | E93: =SUMIFS(mdr_check!L:L,mdr_check!B:B,B93) -> 0 | F93: =IFERROR(SUMIFS(mdr_check!D:D,mdr_check!B:B,B93,mdr_check!L:L,">0")/SUMIFS(mdr_check!C:C,mdr_check!B:B,B93,mdr_check!L:L,">0"),"-") -> - | G93: =IFERROR(SUMIFS(mdr_check!H:H,mdr_check!B:B,B93,mdr_check!L:L,">0")/SUMIFS(mdr_check!C:C,mdr_check!B:B,B93,mdr_check!L:L,">0"),"-") -> - | H93: None
B94: NetBanking | D94: =COUNTIFS(mdr_check!B:B,B94,mdr_check!L:L,">0") -> 0 | E94: =SUMIFS(mdr_check!L:L,mdr_check!B:B,B94) -> 0 | F94: =IFERROR(SUMIFS(mdr_check!D:D,mdr_check!B:B,B94,mdr_check!L:L,">0")/SUMIFS(mdr_check!C:C,mdr_check!B:B,B94,mdr_check!L:L,">0"),"-") -> - | G94: =IFERROR(SUMIFS(mdr_check!H:H,mdr_check!B:B,B94,mdr_check!L:L,">0")/SUMIFS(mdr_check!C:C,mdr_check!B:B,B94,mdr_check!L:L,">0"),"-") -> - | H94: None
B96: ="2. Problems cluster in Delhi and Mumbai: exception rates of "&TEXT(F98,"0.0%")&" and "&TEXT(F99,"0.0%")&" against "&TEXT(COUNTIF(orders!$N$2:$N$6001,"<>OK")/COUNTA(orders!$A$2:$A$6001),"0.0%")&" across all orders, so "&TEXT((E98+E99)/COUNTIF(orders!$N$2:$N$6001,"<>OK"),"0%")&" of all order exceptions come from "&TEXT((D98+D99)/COUNTA(orders!$A$2:$A$6001),"0%")&" of orders. By payment method NetBanking is highest at "&TEXT(L98,"0.0%")&". Counts are small, so monitor these rather than draw firm conclusions." -> 2. Problems cluster in Delhi and Mumbai: exception rates of 1.8% and 1.7% against 1.0% across all orders, so 34% of all order exceptions come from 20% of orders. By payment method NetBanking is highest at 1.7%. Counts are small, so monitor these rather than draw firm conclusions.
B97: City | D97: Orders | E97: Exceptions | F97: Exception rate | H97: Payment method | J97: Orders | K97: Exceptions | L97: Exception rate
B98: Delhi | D98: =COUNTIF(orders!$I$2:$I$6001,B98) -> 604 | E98: =COUNTIFS(orders!$I$2:$I$6001,B98,orders!$N$2:$N$6001,"<>OK") -> 11 | F98: =E98/D98 -> 0.018211921 | H98: NetBanking | J98: =COUNTIF(orders!$E$2:$E$6001,H98) -> 475 | K98: =COUNTIFS(orders!$E$2:$E$6001,H98,orders!$N$2:$N$6001,"<>OK") -> 8 | L98: =K98/J98 -> 0.016842105
B99: Mumbai | D99: =COUNTIF(orders!$I$2:$I$6001,B99) -> 576 | E99: =COUNTIFS(orders!$I$2:$I$6001,B99,orders!$N$2:$N$6001,"<>OK") -> 10 | F99: =E99/D99 -> 0.017361111 | H99: Card | J99: =COUNTIF(orders!$E$2:$E$6001,H99) -> 1595 | K99: =COUNTIFS(orders!$E$2:$E$6001,H99,orders!$N$2:$N$6001,"<>OK") -> 20 | L99: =K99/J99 -> 0.012539185
B100: Lucknow | D100: =COUNTIF(orders!$I$2:$I$6001,B100) -> 581 | E100: =COUNTIFS(orders!$I$2:$I$6001,B100,orders!$N$2:$N$6001,"<>OK") -> 8 | F100: =E100/D100 -> 0.013769363 | H100: Wallet | J100: =COUNTIF(orders!$E$2:$E$6001,H100) -> 719 | K100: =COUNTIFS(orders!$E$2:$E$6001,H100,orders!$N$2:$N$6001,"<>OK") -> 7 | L100: =K100/J100 -> 0.0097357441
B101: Jaipur | D101: =COUNTIF(orders!$I$2:$I$6001,B101) -> 574 | E101: =COUNTIFS(orders!$I$2:$I$6001,B101,orders!$N$2:$N$6001,"<>OK") -> 6 | F101: =E101/D101 -> 0.010452962 | H101: UPI | J101: =COUNTIF(orders!$E$2:$E$6001,H101) -> 3211 | K101: =COUNTIFS(orders!$E$2:$E$6001,H101,orders!$N$2:$N$6001,"<>OK") -> 27 | L101: =K101/J101 -> 0.0084085955
B102: Ahmedabad | D102: =COUNTIF(orders!$I$2:$I$6001,B102) -> 554 | E102: =COUNTIFS(orders!$I$2:$I$6001,B102,orders!$N$2:$N$6001,"<>OK") -> 5 | F102: =E102/D102 -> 0.0090252708
B103: Pune | D103: =COUNTIF(orders!$I$2:$I$6001,B103) -> 568 | E103: =COUNTIFS(orders!$I$2:$I$6001,B103,orders!$N$2:$N$6001,"<>OK") -> 5 | F103: =E103/D103 -> 0.0088028169
B104: Hyderabad | D104: =COUNTIF(orders!$I$2:$I$6001,B104) -> 606 | E104: =COUNTIFS(orders!$I$2:$I$6001,B104,orders!$N$2:$N$6001,"<>OK") -> 5 | F104: =E104/D104 -> 0.0082508251
B105: Kolkata | D105: =COUNTIF(orders!$I$2:$I$6001,B105) -> 599 | E105: =COUNTIFS(orders!$I$2:$I$6001,B105,orders!$N$2:$N$6001,"<>OK") -> 4 | F105: =E105/D105 -> 0.0066777963
B106: Chennai | D106: =COUNTIF(orders!$I$2:$I$6001,B106) -> 571 | E106: =COUNTIFS(orders!$I$2:$I$6001,B106,orders!$N$2:$N$6001,"<>OK") -> 3 | F106: =E106/D106 -> 0.0052539405
B107: Bengaluru | D107: =COUNTIF(orders!$I$2:$I$6001,B107) -> 587 | E107: =COUNTIFS(orders!$I$2:$I$6001,B107,orders!$N$2:$N$6001,"<>OK") -> 3 | F107: =E107/D107 -> 0.0051107325
B116: ="3. ₹"&TEXT(-(bridge!B17+bridge!B18),"#,##0")&" is still owed by the gateway: batch STL-20260912 never arrived and STL-20260911 was ₹"&TEXT(-bridge!B18,"#,##0")&" short. The other ₹"&TEXT(-bridge!B16,"#,##0")&" is only timing (the 1-2 Oct batches). Matching bank receipts to batches every day would catch a missing batch in days instead of at month end." -> 3. ₹552,324 is still owed by the gateway: batch STL-20260912 never arrived and STL-20260911 was ₹1,250 short. The other ₹1,265,527 is only timing (the 1-2 Oct batches). Matching bank receipts to batches every day would catch a missing batch in days instead of at month end.
B117: Batch | D117: Settlement date | E117: Gateway net | F117: Bank credit | G117: Not received | H117: Status | J117: Days overdue at 30 Sep | K117: Action
B118: STL-20260912 | D118: =INDEX(batch_recon!$B:$B,MATCH($B118,batch_recon!$A:$A,0)) -> 46277 | E118: =INDEX(batch_recon!$C:$C,MATCH($B118,batch_recon!$A:$A,0)) -> 551074.03 | F118: =INDEX(batch_recon!$D:$D,MATCH($B118,batch_recon!$A:$A,0)) -> 0 | G118: =E118-F118 -> 551074.03 | H118: =INDEX(batch_recon!$F:$F,MATCH($B118,batch_recon!$A:$A,0)) -> Missing | J118: =IF(H118="Due in October","not yet due",DATE(2026,9,30)-D118) -> 18 | K118: Chase gateway: batch never paid
B119: STL-20260911 | D119: =INDEX(batch_recon!$B:$B,MATCH($B119,batch_recon!$A:$A,0)) -> 46276 | E119: =INDEX(batch_recon!$C:$C,MATCH($B119,batch_recon!$A:$A,0)) -> 556411.99 | F119: =INDEX(batch_recon!$D:$D,MATCH($B119,batch_recon!$A:$A,0)) -> 555161.99 | G119: =E119-F119 -> 1250 | H119: =INDEX(batch_recon!$F:$F,MATCH($B119,batch_recon!$A:$A,0)) -> Short-paid | J119: =IF(H119="Due in October","not yet due",DATE(2026,9,30)-D119) -> 19 | K119: Claim the ₹1,250 shortfall
B120: STL-20261001 | D120: =INDEX(batch_recon!$B:$B,MATCH($B120,batch_recon!$A:$A,0)) -> 46296 | E120: =INDEX(batch_recon!$C:$C,MATCH($B120,batch_recon!$A:$A,0)) -> 650622.7 | F120: =INDEX(batch_recon!$D:$D,MATCH($B120,batch_recon!$A:$A,0)) -> 0 | G120: =E120-F120 -> 650622.7 | H120: =INDEX(batch_recon!$F:$F,MATCH($B120,batch_recon!$A:$A,0)) -> Due in October | J120: =IF(H120="Due in October","not yet due",DATE(2026,9,30)-D120) -> not yet due | K120: Timing: expect credit in Oct
B121: STL-20261002 | D121: =INDEX(batch_recon!$B:$B,MATCH($B121,batch_recon!$A:$A,0)) -> 46297 | E121: =INDEX(batch_recon!$C:$C,MATCH($B121,batch_recon!$A:$A,0)) -> 614904.2 | F121: =INDEX(batch_recon!$D:$D,MATCH($B121,batch_recon!$A:$A,0)) -> 0 | G121: =E121-F121 -> 614904.2 | H121: =INDEX(batch_recon!$F:$F,MATCH($B121,batch_recon!$A:$A,0)) -> Due in October | J121: =IF(H121="Due in October","not yet due",DATE(2026,9,30)-D121) -> not yet due | K121: Timing: expect credit in Oct
B122: Genuine: still owed by the gateway | E122: =SUMIF($H118:$H121,"Missing",E118:E121)+SUMIF($H118:$H121,"Short-paid",E118:E121) -> 1107486 | F122: =SUMIF($H118:$H121,"Missing",F118:F121)+SUMIF($H118:$H121,"Short-paid",F118:F121) -> 555161.99 | G122: =E122-F122 -> 552324.03 | H122: =IF(ROUND(G122-$E$9,2)=0,"Agrees with the headline above","DOES NOT AGREE") -> Agrees with the headline above
B123: Timing: arrives in October | E123: =SUMIF($H118:$H121,"Due in October",E118:E121) -> 1265526.9 | F123: =SUMIF($H118:$H121,"Due in October",F118:F121) -> 0 | G123: =E123-F123 -> 1265526.9 | H123: =IF(ROUND(G123+bridge!B16,2)=0,"Agrees with the bridge","DOES NOT AGREE") -> Agrees with the bridge
B138: No orange bar = nothing received. STL-20260911 shows an orange bar almost as tall as the blue one because it was only ₹1,250 short.
B140: ="4. Gateway settlements are "&TEXT(E150/E151,"0.0%")&" of all money credited to the bank in September (₹"&TEXT(E150,"#,##0")&" of ₹"&TEXT(E151,"#,##0")&"). The other ₹"&TEXT(E151-E150,"#,##0")&" (COD remittance and marketplace payout) is not gateway money, so it is kept out of the reconciliation. Debits total ₹"&TEXT(F151,"#,##0")&", led by "&INDEX(B142:B149,MATCH(MAX(F142:F149),F142:F149,0))&" (₹"&TEXT(MAX(F142:F149),"#,##0")&"), so the account grew by ₹"&TEXT(G151,"#,##0")&". The ₹"&TEXT($E$9,"#,##0")&" still owed by the gateway equals "&TEXT($E$9/F151,"0%")&" of everything the business paid out in the month." -> 4. Gateway settlements are 98.8% of all money credited to the bank in September (₹16,984,049 of ₹17,191,349). The other ₹207,301 (COD remittance and marketplace payout) is not gateway money, so it is kept out of the reconciliation. Debits total ₹1,182,240, led by Salary (₹640,000), so the account grew by ₹16,009,109. The ₹552,324 still owed by the gateway equals 47% of everything the business paid out in the month.
B141: Bank category | E141: Credits | F141: Debits | G141: Net movement
B142: COD remittance | E142: =SUMIFS(bank_statement_cleaned!$G:$G,bank_statement_cleaned!$J:$J,$B142) -> 132980 | F142: =SUMIFS(bank_statement_cleaned!$F:$F,bank_statement_cleaned!$J:$J,$B142) -> 0 | G142: =E142-F142 -> 132980
B143: Marketplace payout | E143: =SUMIFS(bank_statement_cleaned!$G:$G,bank_statement_cleaned!$J:$J,$B143) -> 74320.55 | F143: =SUMIFS(bank_statement_cleaned!$F:$F,bank_statement_cleaned!$J:$J,$B143) -> 0 | G143: =E143-F143 -> 74320.55
B144: GST payment | E144: =SUMIFS(bank_statement_cleaned!$G:$G,bank_statement_cleaned!$J:$J,$B144) -> 0 | F144: =SUMIFS(bank_statement_cleaned!$F:$F,bank_statement_cleaned!$J:$J,$B144) -> 212450 | G144: =E144-F144 -> -212450
B145: Salary | E145: =SUMIFS(bank_statement_cleaned!$G:$G,bank_statement_cleaned!$J:$J,$B145) -> 0 | F145: =SUMIFS(bank_statement_cleaned!$F:$F,bank_statement_cleaned!$J:$J,$B145) -> 640000 | G145: =E145-F145 -> -640000
B146: Cloud (AWS) | E146: =SUMIFS(bank_statement_cleaned!$G:$G,bank_statement_cleaned!$J:$J,$B146) -> 0 | F146: =SUMIFS(bank_statement_cleaned!$F:$F,bank_statement_cleaned!$J:$J,$B146) -> 48231.2 | G146: =E146-F146 -> -48231.2
B147: Rent | E147: =SUMIFS(bank_statement_cleaned!$G:$G,bank_statement_cleaned!$J:$J,$B147) -> 0 | F147: =SUMIFS(bank_statement_cleaned!$F:$F,bank_statement_cleaned!$J:$J,$B147) -> 185000 | G147: =E147-F147 -> -185000
B148: Packaging vendor | E148: =SUMIFS(bank_statement_cleaned!$G:$G,bank_statement_cleaned!$J:$J,$B148) -> 0 | F148: =SUMIFS(bank_statement_cleaned!$F:$F,bank_statement_cleaned!$J:$J,$B148) -> 96500 | G148: =E148-F148 -> -96500
B149: Bank charges | E149: =SUMIFS(bank_statement_cleaned!$G:$G,bank_statement_cleaned!$J:$J,$B149) -> 0 | F149: =SUMIFS(bank_statement_cleaned!$F:$F,bank_statement_cleaned!$J:$J,$B149) -> 59 | G149: =E149-F149 -> -59
B150: Gateway settlement | E150: =SUMIFS(bank_statement_cleaned!$G:$G,bank_statement_cleaned!$J:$J,$B150) -> 16984049 | F150: =SUMIFS(bank_statement_cleaned!$F:$F,bank_statement_cleaned!$J:$J,$B150) -> 0 | G150: =E150-F150 -> 16984049
B151: Total | E151: =SUM(E142:E150) -> 17191349 | F151: =SUM(F142:F150) -> 1182240.2 | G151: =SUM(G142:G150) -> 16009109
B152: =IF(AND(ROUND(E150-bridge!B19,2)=0,ROUND(E151-SUM(bank_statement_cleaned!G:G),2)=0,ROUND(F151-SUM(bank_statement_cleaned!F:F),2)=0),"Checks pass: credit_cleaned and debit_cleaned totals equal the bank sheet; gateway credits equal bridge cash in bank","DOES NOT AGREE") -> Checks pass: credit_cleaned and debit_cleaned totals equal the bank sheet; gateway credits equal bridge cash in bank
B156: ="5. Gateway fees cost ₹"&TEXT(F162+G162,"#,##0")&" ("&TEXT(I162,"0.00%")&" of the ₹"&TEXT(E162,"#,##0")&" collected): ₹"&TEXT(F162,"#,##0")&" MDR plus ₹"&TEXT(G162,"#,##0")&" GST. "&INDEX(B158:B161,MATCH(MAX(I158:I161),I158:I161,0))&" is the most expensive at "&TEXT(MAX(I158:I161),"0.0%")&" and "&INDEX(B158:B161,MATCH(MIN(I158:I161),I158:I161,0))&" the cheapest at "&TEXT(MIN(I158:I161),"0.0%")&". Card is "&TEXT(E159/E162,"0%")&" of the money collected but "&TEXT((F159+G159)/(F162+G162),"0%")&" of the fees. After fees and refunds, net received is ₹"&TEXT(H164,"#,##0")&", exactly what the gateway owed per the bridge." -> 5. Gateway fees cost ₹206,962 (1.04% of the ₹19,902,749 collected): ₹175,390 MDR plus ₹31,572 GST. Wallet is the most expensive at 2.1% and UPI the cheapest at 0.3%. Card is 27% of the money collected but 49% of the fees. After fees and refunds, net received is ₹18,801,899, exactly what the gateway owed per the bridge.
B157: Payment method | D157: Payments | E157: Gross (INR) | F157: MDR charged | G157: GST charged | H157: Net received | I157: Fee % charged | J157: Fee % at rate card | K157: Overcharge | L157: Share of gross | M157: Share of fees
B158: UPI | D158: =COUNTIFS(pg_transaction_cleaned!$F:$F,"CAPTURE",pg_transaction_cleaned!$G:$G,$B158) -> 2934 | E158: =SUMIFS(pg_transaction_cleaned!$H:$H,pg_transaction_cleaned!$F:$F,"CAPTURE",pg_transaction_cleaned!$G:$G,$B158) -> 10598036 | F158: =SUMIFS(pg_transaction_cleaned!$I:$I,pg_transaction_cleaned!$F:$F,"CAPTURE",pg_transaction_cleaned!$G:$G,$B158) -> 28207.31 | G158: =SUMIFS(pg_transaction_cleaned!$J:$J,pg_transaction_cleaned!$F:$F,"CAPTURE",pg_transaction_cleaned!$G:$G,$B158) -> 5077.46 | H158: =SUMIFS(pg_transaction_cleaned!$K:$K,pg_transaction_cleaned!$F:$F,"CAPTURE",pg_transaction_cleaned!$G:$G,$B158) -> 10564751 | I158: =(F158+G158)/E158 -> 0.0031406546 | J158: =(SUMIFS(mdr_check!$H:$H,mdr_check!$B:$B,$B158)+SUMIFS(mdr_check!$K:$K,mdr_check!$B:$B,$B158))/SUMIFS(mdr_check!$C:$C,mdr_check!$B:$B,$B158) -> 0.0031336816 | K158: =SUMIFS(mdr_check!$L:$L,mdr_check!$B:$B,$B158) -> 73.9 | L158: =E158/E$162 -> 0.53249106 | M158: =(F158+G158)/(F$162+G$162) -> 0.16082589
B159: Card | D159: =COUNTIFS(pg_transaction_cleaned!$F:$F,"CAPTURE",pg_transaction_cleaned!$G:$G,$B159) -> 1462 | E159: =SUMIFS(pg_transaction_cleaned!$H:$H,pg_transaction_cleaned!$F:$F,"CAPTURE",pg_transaction_cleaned!$G:$G,$B159) -> 5288904 | F159: =SUMIFS(pg_transaction_cleaned!$I:$I,pg_transaction_cleaned!$F:$F,"CAPTURE",pg_transaction_cleaned!$G:$G,$B159) -> 85808.87 | G159: =SUMIFS(pg_transaction_cleaned!$J:$J,pg_transaction_cleaned!$F:$F,"CAPTURE",pg_transaction_cleaned!$G:$G,$B159) -> 15446.97 | H159: =SUMIFS(pg_transaction_cleaned!$K:$K,pg_transaction_cleaned!$F:$F,"CAPTURE",pg_transaction_cleaned!$G:$G,$B159) -> 5187648.2 | I159: =(F159+G159)/E159 -> 0.019144957 | J159: =(SUMIFS(mdr_check!$H:$H,mdr_check!$B:$B,$B159)+SUMIFS(mdr_check!$K:$K,mdr_check!$B:$B,$B159))/SUMIFS(mdr_check!$C:$C,mdr_check!$B:$B,$B159) -> 0.019144957 | K159: =SUMIFS(mdr_check!$L:$L,mdr_check!$B:$B,$B159) -> 0 | L159: =E159/E$162 -> 0.26573736 | M159: =(F159+G159)/(F$162+G$162) -> 0.48924962
B160: NetBanking | D160: =COUNTIFS(pg_transaction_cleaned!$F:$F,"CAPTURE",pg_transaction_cleaned!$G:$G,$B160) -> 440 | E160: =SUMIFS(pg_transaction_cleaned!$H:$H,pg_transaction_cleaned!$F:$F,"CAPTURE",pg_transaction_cleaned!$G:$G,$B160) -> 1613736 | F160: =SUMIFS(pg_transaction_cleaned!$I:$I,pg_transaction_cleaned!$F:$F,"CAPTURE",pg_transaction_cleaned!$G:$G,$B160) -> 19044.86 | G160: =SUMIFS(pg_transaction_cleaned!$J:$J,pg_transaction_cleaned!$F:$F,"CAPTURE",pg_transaction_cleaned!$G:$G,$B160) -> 3428.2 | H160: =SUMIFS(pg_transaction_cleaned!$K:$K,pg_transaction_cleaned!$F:$F,"CAPTURE",pg_transaction_cleaned!$G:$G,$B160) -> 1591262.9 | I160: =(F160+G160)/E160 -> 0.013926107 | J160: =(SUMIFS(mdr_check!$H:$H,mdr_check!$B:$B,$B160)+SUMIFS(mdr_check!$K:$K,mdr_check!$B:$B,$B160))/SUMIFS(mdr_check!$C:$C,mdr_check!$B:$B,$B160) -> 0.013926107 | K160: =SUMIFS(mdr_check!$L:$L,mdr_check!$B:$B,$B160) -> 0 | L160: =E160/E$162 -> 0.081081061 | M160: =(F160+G160)/(F$162+G$162) -> 0.1085857
B161: Wallet | D161: =COUNTIFS(pg_transaction_cleaned!$F:$F,"CAPTURE",pg_transaction_cleaned!$G:$G,$B161) -> 663 | E161: =SUMIFS(pg_transaction_cleaned!$H:$H,pg_transaction_cleaned!$F:$F,"CAPTURE",pg_transaction_cleaned!$G:$G,$B161) -> 2402073 | F161: =SUMIFS(pg_transaction_cleaned!$I:$I,pg_transaction_cleaned!$F:$F,"CAPTURE",pg_transaction_cleaned!$G:$G,$B161) -> 42328.49 | G161: =SUMIFS(pg_transaction_cleaned!$J:$J,pg_transaction_cleaned!$F:$F,"CAPTURE",pg_transaction_cleaned!$G:$G,$B161) -> 7619.35 | H161: =SUMIFS(pg_transaction_cleaned!$K:$K,pg_transaction_cleaned!$F:$F,"CAPTURE",pg_transaction_cleaned!$G:$G,$B161) -> 2352125.2 | I161: =(F161+G161)/E161 -> 0.020793639 | J161: =(SUMIFS(mdr_check!$H:$H,mdr_check!$B:$B,$B161)+SUMIFS(mdr_check!$K:$K,mdr_check!$B:$B,$B161))/SUMIFS(mdr_check!$C:$C,mdr_check!$B:$B,$B161) -> 0.020330997 | K161: =SUMIFS(mdr_check!$L:$L,mdr_check!$B:$B,$B161) -> 1111.3 | L161: =E161/E$162 -> 0.12069051 | M161: =(F161+G161)/(F$162+G$162) -> 0.24133879
B162: Total captures | D162: =SUM(D158:D161) -> 5499 | E162: =SUM(E158:E161) -> 19902749 | F162: =SUM(F158:F161) -> 175389.53 | G162: =SUM(G158:G161) -> 31571.98 | H162: =SUM(H158:H161) -> 19695787 | I162: =(F162+G162)/E162 -> 0.010398639 | J162: =(SUM(mdr_check!H:H)+SUM(mdr_check!K:K))/SUM(mdr_check!C:C) -> 0.01033909 | K162: =SUM(K158:K161) -> 1185.2 | L162: =SUM(L158:L161) -> 1 | M162: =SUM(M158:M161) -> 1
B163: Less: refunds (deducted from settlements) | H163: =bridge!B11 -> -893888
B164: Net payable by gateway | H164: =H162+H163 -> 18801899 | I164: =IF(AND(ROUND(H164-bridge!B15,2)=0,ROUND(K162+bridge!B14,2)=0),"Agrees with bridge","DOES NOT AGREE") -> Agrees with bridge
B179: Net received = gross less MDR less GST on captures (before refunds). Fee % charged sits above the rate card only for UPI and Wallet (see insight 1).

Sheet bridge
A1: Bridge: sales per orders to cash in bank (INR)
A3: Line | B3: Amount (INR) | C3: Source
A4: Sales per orders (Paid + Refunded) | B4: =SUMIFS(orders!H:H,orders!G:G,"Paid")+SUMIFS(orders!H:H,orders!G:G,"Refunded") -> 19894293 | C4: orders: order_amount_cleaned by order_status
A5: Paid orders with no payment | B5: =-SUMIFS(orders!O:O,orders!N:N,"Paid, no payment") -> -67617 | C5: orders: exception_type
A6: Amount differences | B6: =SUMIFS(orders!O:O,orders!N:N,"Amount difference") -> -3145 | C6: orders: exception_type (already signed)
A7: Duplicate charges | B7: =SUMIFS(orders!O:O,orders!N:N,"Duplicate charge") -> 25539 | C7: orders: exception_type (extra amount charged)
A8: Payments with no order | B8: =SUMIFS(pg_transaction_cleaned!H:H,pg_transaction_cleaned!Q:Q,"NO ORDER") -> 24992 | C8: pg cleaned: order_found = NO ORDER
A9: Payments on Failed/Cancelled orders | B9: =SUMIFS(orders!O:O,orders!N:N,"Payment on failed/cancelled") -> 28687 | C9: orders: exception_type
A10: Gross captured by gateway | B10: =SUM(B4:B9) -> 19902749 | C10: subtotal
A11: Refunds | B11: =-SUMIFS(pg_transaction_cleaned!H:H,pg_transaction_cleaned!F:F,"REFUND") -> -893888 | C11: pg cleaned: REFUND gross
A12: MDR (at the correct rate) | B12: =-SUM(mdr_check!H:H) -> -174385.11 | C12: mdr_check: expected_mdr
A13: GST on MDR (correct) | B13: =-SUM(mdr_check!K:K) -> -31391.2 | C13: mdr_check: expected_gst
A14: MDR + GST overcharge | B14: =-SUM(mdr_check!L:L) -> -1185.2 | C14: mdr_check: (fee + GST charged) less correct
A15: Net payable by gateway | B15: =B10+SUM(B11:B14) -> 18801899 | C15: subtotal
A16: Due in October | B16: =-SUMIFS(batch_recon!C:C,batch_recon!F:F,"Due in October")+SUMIFS(batch_recon!D:D,batch_recon!F:F,"Due in October") -> -1265526.9 | C16: batch_recon
A17: Missing settlement (STL-20260912) | B17: =SUMIFS(batch_recon!D:D,batch_recon!F:F,"Missing")-SUMIFS(batch_recon!C:C,batch_recon!F:F,"Missing") -> -551074.03 | C17: batch_recon
A18: Short-paid (STL-20260911) | B18: =SUMIFS(batch_recon!D:D,batch_recon!F:F,"Short-paid")-SUMIFS(batch_recon!C:C,batch_recon!F:F,"Short-paid") -> -1250 | C18: batch_recon
A19: Cash in bank | B19: =B15+SUM(B16:B18) -> 16984049 | C19: subtotal
A21: CHECKS
A22: Bank credits on gateway batches (actual) | B22: =SUM(batch_recon!D2:D31) -> 16984049 | C22: batch_recon
A23: Check: bridge cash in bank less bank total (must be 0) | B23: =ROUND(B19-B22,2) -> 0
A24: Check: gross captured less gateway captures (must be 0) | B24: =ROUND(B10-SUMIFS(pg_transaction_cleaned!H:H,pg_transaction_cleaned!F:F,"CAPTURE"),2) -> 0
A25: Check: net payable less sum of gateway net (must be 0) | B25: =ROUND(B15-SUM(pg_transaction_cleaned!K:K),2) -> 0
A26: Total gap (sales less cash in bank) | B26: =B4-B19 -> 2910244.4
A27: Unexplained difference | B27: =ROUND((B19-B4)-(SUM(B5:B9)+B11+B12+B13+B14+SUM(B16:B18)),2) -> 0 | C27: sum of all adjustment lines vs gap

Sheet batch_recon
A1: batch_id | B1: settlement_date | C1: gateway_net | D1: bank_credit | E1: difference | F1: status | H1: Summary by status
A2: STL-20260903 | B2: =DATE(MID(A2,5,4),MID(A2,9,2),RIGHT(A2,2)) -> 46268 | C2: =SUMIFS(pg_transaction_cleaned!$K:$K,pg_transaction_cleaned!$M:$M,A2) -> 463778.55 | D2: =SUMIFS(bank_statement_cleaned!$G:$G,bank_statement_cleaned!$H:$H,A2) -> 463778.55 | E2: =D2-C2 -> 0 | F2: =IF(B2>DATE(2026,9,30),"Due in October",IF(COUNTIF(bank_statement_cleaned!$H:$H,A2)=0,"Missing",IF(ROUND(E2,2)=0,"Matched",IF(E2<0,"Short-paid","Excess")))) -> Matched | H2: Status | I2: Batches | J2: Gateway net | K2: Bank credit | L2: Difference (bank - gateway)
A3: STL-20260904 | B3: =DATE(MID(A3,5,4),MID(A3,9,2),RIGHT(A3,2)) -> 46269 | C3: =SUMIFS(pg_transaction_cleaned!$K:$K,pg_transaction_cleaned!$M:$M,A3) -> 680913.82 | D3: =SUMIFS(bank_statement_cleaned!$G:$G,bank_statement_cleaned!$H:$H,A3) -> 680913.82 | E3: =D3-C3 -> 0 | F3: =IF(B3>DATE(2026,9,30),"Due in October",IF(COUNTIF(bank_statement_cleaned!$H:$H,A3)=0,"Missing",IF(ROUND(E3,2)=0,"Matched",IF(E3<0,"Short-paid","Excess")))) -> Matched | H3: Matched | I3: =COUNTIF($F$2:$F$31,H3) -> 26 | J3: =SUMIF($F$2:$F$31,H3,$C$2:$C$31) -> 16428887 | K3: =SUMIF($F$2:$F$31,H3,$D$2:$D$31) -> 16428887 | L3: =K3-J3 -> 0
A4: STL-20260905 | B4: =DATE(MID(A4,5,4),MID(A4,9,2),RIGHT(A4,2)) -> 46270 | C4: =SUMIFS(pg_transaction_cleaned!$K:$K,pg_transaction_cleaned!$M:$M,A4) -> 578249.99 | D4: =SUMIFS(bank_statement_cleaned!$G:$G,bank_statement_cleaned!$H:$H,A4) -> 578249.99 | E4: =D4-C4 -> 0 | F4: =IF(B4>DATE(2026,9,30),"Due in October",IF(COUNTIF(bank_statement_cleaned!$H:$H,A4)=0,"Missing",IF(ROUND(E4,2)=0,"Matched",IF(E4<0,"Short-paid","Excess")))) -> Matched | H4: Short-paid | I4: =COUNTIF($F$2:$F$31,H4) -> 1 | J4: =SUMIF($F$2:$F$31,H4,$C$2:$C$31) -> 556411.99 | K4: =SUMIF($F$2:$F$31,H4,$D$2:$D$31) -> 555161.99 | L4: =K4-J4 -> -1250
A5: STL-20260906 | B5: =DATE(MID(A5,5,4),MID(A5,9,2),RIGHT(A5,2)) -> 46271 | C5: =SUMIFS(pg_transaction_cleaned!$K:$K,pg_transaction_cleaned!$M:$M,A5) -> 655139.18 | D5: =SUMIFS(bank_statement_cleaned!$G:$G,bank_statement_cleaned!$H:$H,A5) -> 655139.18 | E5: =D5-C5 -> 0 | F5: =IF(B5>DATE(2026,9,30),"Due in October",IF(COUNTIF(bank_statement_cleaned!$H:$H,A5)=0,"Missing",IF(ROUND(E5,2)=0,"Matched",IF(E5<0,"Short-paid","Excess")))) -> Matched | H5: Missing | I5: =COUNTIF($F$2:$F$31,H5) -> 1 | J5: =SUMIF($F$2:$F$31,H5,$C$2:$C$31) -> 551074.03 | K5: =SUMIF($F$2:$F$31,H5,$D$2:$D$31) -> 0 | L5: =K5-J5 -> -551074.03
A6: STL-20260907 | B6: =DATE(MID(A6,5,4),MID(A6,9,2),RIGHT(A6,2)) -> 46272 | C6: =SUMIFS(pg_transaction_cleaned!$K:$K,pg_transaction_cleaned!$M:$M,A6) -> 614451.5 | D6: =SUMIFS(bank_statement_cleaned!$G:$G,bank_statement_cleaned!$H:$H,A6) -> 614451.5 | E6: =D6-C6 -> 0 | F6: =IF(B6>DATE(2026,9,30),"Due in October",IF(COUNTIF(bank_statement_cleaned!$H:$H,A6)=0,"Missing",IF(ROUND(E6,2)=0,"Matched",IF(E6<0,"Short-paid","Excess")))) -> Matched | H6: Due in October | I6: =COUNTIF($F$2:$F$31,H6) -> 2 | J6: =SUMIF($F$2:$F$31,H6,$C$2:$C$31) -> 1265526.9 | K6: =SUMIF($F$2:$F$31,H6,$D$2:$D$31) -> 0 | L6: =K6-J6 -> -1265526.9
A7: STL-20260908 | B7: =DATE(MID(A7,5,4),MID(A7,9,2),RIGHT(A7,2)) -> 46273 | C7: =SUMIFS(pg_transaction_cleaned!$K:$K,pg_transaction_cleaned!$M:$M,A7) -> 704983.27 | D7: =SUMIFS(bank_statement_cleaned!$G:$G,bank_statement_cleaned!$H:$H,A7) -> 704983.27 | E7: =D7-C7 -> 0 | F7: =IF(B7>DATE(2026,9,30),"Due in October",IF(COUNTIF(bank_statement_cleaned!$H:$H,A7)=0,"Missing",IF(ROUND(E7,2)=0,"Matched",IF(E7<0,"Short-paid","Excess")))) -> Matched | H7: Excess | I7: =COUNTIF($F$2:$F$31,H7) -> 0 | J7: =SUMIF($F$2:$F$31,H7,$C$2:$C$31) -> 0 | K7: =SUMIF($F$2:$F$31,H7,$D$2:$D$31) -> 0 | L7: =K7-J7 -> 0
A8: STL-20260909 | B8: =DATE(MID(A8,5,4),MID(A8,9,2),RIGHT(A8,2)) -> 46274 | C8: =SUMIFS(pg_transaction_cleaned!$K:$K,pg_transaction_cleaned!$M:$M,A8) -> 606316.51 | D8: =SUMIFS(bank_statement_cleaned!$G:$G,bank_statement_cleaned!$H:$H,A8) -> 606316.51 | E8: =D8-C8 -> 0 | F8: =IF(B8>DATE(2026,9,30),"Due in October",IF(COUNTIF(bank_statement_cleaned!$H:$H,A8)=0,"Missing",IF(ROUND(E8,2)=0,"Matched",IF(E8<0,"Short-paid","Excess")))) -> Matched | H8: Total | I8: =SUM(I3:I7) -> 30 | J8: =SUM(J3:J7) -> 18801899 | K8: =SUM(K3:K7) -> 16984049 | L8: =SUM(L3:L7) -> -1817850.9
A9: STL-20260910 | B9: =DATE(MID(A9,5,4),MID(A9,9,2),RIGHT(A9,2)) -> 46275 | C9: =SUMIFS(pg_transaction_cleaned!$K:$K,pg_transaction_cleaned!$M:$M,A9) -> 740734.12 | D9: =SUMIFS(bank_statement_cleaned!$G:$G,bank_statement_cleaned!$H:$H,A9) -> 740734.12 | E9: =D9-C9 -> 0 | F9: =IF(B9>DATE(2026,9,30),"Due in October",IF(COUNTIF(bank_statement_cleaned!$H:$H,A9)=0,"Missing",IF(ROUND(E9,2)=0,"Matched",IF(E9<0,"Short-paid","Excess")))) -> Matched
A10: STL-20260911 | B10: =DATE(MID(A10,5,4),MID(A10,9,2),RIGHT(A10,2)) -> 46276 | C10: =SUMIFS(pg_transaction_cleaned!$K:$K,pg_transaction_cleaned!$M:$M,A10) -> 556411.99 | D10: =SUMIFS(bank_statement_cleaned!$G:$G,bank_statement_cleaned!$H:$H,A10) -> 555161.99 | E10: =D10-C10 -> -1250 | F10: =IF(B10>DATE(2026,9,30),"Due in October",IF(COUNTIF(bank_statement_cleaned!$H:$H,A10)=0,"Missing",IF(ROUND(E10,2)=0,"Matched",IF(E10<0,"Short-paid","Excess")))) -> Short-paid
A11: STL-20260912 | B11: =DATE(MID(A11,5,4),MID(A11,9,2),RIGHT(A11,2)) -> 46277 | C11: =SUMIFS(pg_transaction_cleaned!$K:$K,pg_transaction_cleaned!$M:$M,A11) -> 551074.03 | D11: =SUMIFS(bank_statement_cleaned!$G:$G,bank_statement_cleaned!$H:$H,A11) -> 0 | E11: =D11-C11 -> -551074.03 | F11: =IF(B11>DATE(2026,9,30),"Due in October",IF(COUNTIF(bank_statement_cleaned!$H:$H,A11)=0,"Missing",IF(ROUND(E11,2)=0,"Matched",IF(E11<0,"Short-paid","Excess")))) -> Missing | H11: Checks (blue = expected)
A12: STL-20260913 | B12: =DATE(MID(A12,5,4),MID(A12,9,2),RIGHT(A12,2)) -> 46278 | C12: =SUMIFS(pg_transaction_cleaned!$K:$K,pg_transaction_cleaned!$M:$M,A12) -> 654313.3 | D12: =SUMIFS(bank_statement_cleaned!$G:$G,bank_statement_cleaned!$H:$H,A12) -> 654313.3 | E12: =D12-C12 -> 0 | F12: =IF(B12>DATE(2026,9,30),"Due in October",IF(COUNTIF(bank_statement_cleaned!$H:$H,A12)=0,"Missing",IF(ROUND(E12,2)=0,"Matched",IF(E12<0,"Short-paid","Excess")))) -> Matched | H12: Check | I12: Actual | J12: Expected | K12: Status
A13: STL-20260914 | B13: =DATE(MID(A13,5,4),MID(A13,9,2),RIGHT(A13,2)) -> 46279 | C13: =SUMIFS(pg_transaction_cleaned!$K:$K,pg_transaction_cleaned!$M:$M,A13) -> 596289.91 | D13: =SUMIFS(bank_statement_cleaned!$G:$G,bank_statement_cleaned!$H:$H,A13) -> 596289.91 | E13: =D13-C13 -> 0 | F13: =IF(B13>DATE(2026,9,30),"Due in October",IF(COUNTIF(bank_statement_cleaned!$H:$H,A13)=0,"Missing",IF(ROUND(E13,2)=0,"Matched",IF(E13<0,"Short-paid","Excess")))) -> Matched | H13: Batches listed | I13: =COUNTA(A2:A31) -> 30 | J13: 30 | K13: =IF(ROUND(I13-J13,2)=0,"PASS","FAIL") -> PASS
A14: STL-20260915 | B14: =DATE(MID(A14,5,4),MID(A14,9,2),RIGHT(A14,2)) -> 46280 | C14: =SUMIFS(pg_transaction_cleaned!$K:$K,pg_transaction_cleaned!$M:$M,A14) -> 773297.25 | D14: =SUMIFS(bank_statement_cleaned!$G:$G,bank_statement_cleaned!$H:$H,A14) -> 773297.25 | E14: =D14-C14 -> 0 | F14: =IF(B14>DATE(2026,9,30),"Due in October",IF(COUNTIF(bank_statement_cleaned!$H:$H,A14)=0,"Missing",IF(ROUND(E14,2)=0,"Matched",IF(E14<0,"Short-paid","Excess")))) -> Matched | H14: Matched batches | I14: =I3 -> 26 | J14: 26 | K14: =IF(ROUND(I14-J14,2)=0,"PASS","FAIL") -> PASS
A15: STL-20260916 | B15: =DATE(MID(A15,5,4),MID(A15,9,2),RIGHT(A15,2)) -> 46281 | C15: =SUMIFS(pg_transaction_cleaned!$K:$K,pg_transaction_cleaned!$M:$M,A15) -> 614772.68 | D15: =SUMIFS(bank_statement_cleaned!$G:$G,bank_statement_cleaned!$H:$H,A15) -> 614772.68 | E15: =D15-C15 -> 0 | F15: =IF(B15>DATE(2026,9,30),"Due in October",IF(COUNTIF(bank_statement_cleaned!$H:$H,A15)=0,"Missing",IF(ROUND(E15,2)=0,"Matched",IF(E15<0,"Short-paid","Excess")))) -> Matched | H15: Short-paid batches | I15: =I4 -> 1 | J15: 1 | K15: =IF(ROUND(I15-J15,2)=0,"PASS","FAIL") -> PASS
A16: STL-20260917 | B16: =DATE(MID(A16,5,4),MID(A16,9,2),RIGHT(A16,2)) -> 46282 | C16: =SUMIFS(pg_transaction_cleaned!$K:$K,pg_transaction_cleaned!$M:$M,A16) -> 671270.49 | D16: =SUMIFS(bank_statement_cleaned!$G:$G,bank_statement_cleaned!$H:$H,A16) -> 671270.49 | E16: =D16-C16 -> 0 | F16: =IF(B16>DATE(2026,9,30),"Due in October",IF(COUNTIF(bank_statement_cleaned!$H:$H,A16)=0,"Missing",IF(ROUND(E16,2)=0,"Matched",IF(E16<0,"Short-paid","Excess")))) -> Matched | H16: Missing batches | I16: =I5 -> 1 | J16: 1 | K16: =IF(ROUND(I16-J16,2)=0,"PASS","FAIL") -> PASS
A17: STL-20260918 | B17: =DATE(MID(A17,5,4),MID(A17,9,2),RIGHT(A17,2)) -> 46283 | C17: =SUMIFS(pg_transaction_cleaned!$K:$K,pg_transaction_cleaned!$M:$M,A17) -> 589645.35 | D17: =SUMIFS(bank_statement_cleaned!$G:$G,bank_statement_cleaned!$H:$H,A17) -> 589645.35 | E17: =D17-C17 -> 0 | F17: =IF(B17>DATE(2026,9,30),"Due in October",IF(COUNTIF(bank_statement_cleaned!$H:$H,A17)=0,"Missing",IF(ROUND(E17,2)=0,"Matched",IF(E17<0,"Short-paid","Excess")))) -> Matched | H17: Due in October batches | I17: =I6 -> 2 | J17: 2 | K17: =IF(ROUND(I17-J17,2)=0,"PASS","FAIL") -> PASS
A18: STL-20260919 | B18: =DATE(MID(A18,5,4),MID(A18,9,2),RIGHT(A18,2)) -> 46284 | C18: =SUMIFS(pg_transaction_cleaned!$K:$K,pg_transaction_cleaned!$M:$M,A18) -> 610773.29 | D18: =SUMIFS(bank_statement_cleaned!$G:$G,bank_statement_cleaned!$H:$H,A18) -> 610773.29 | E18: =D18-C18 -> 0 | F18: =IF(B18>DATE(2026,9,30),"Due in October",IF(COUNTIF(bank_statement_cleaned!$H:$H,A18)=0,"Missing",IF(ROUND(E18,2)=0,"Matched",IF(E18<0,"Short-paid","Excess")))) -> Matched | H18: Excess batches | I18: =I7 -> 0 | J18: 0 | K18: =IF(ROUND(I18-J18,2)=0,"PASS","FAIL") -> PASS
A19: STL-20260920 | B19: =DATE(MID(A19,5,4),MID(A19,9,2),RIGHT(A19,2)) -> 46285 | C19: =SUMIFS(pg_transaction_cleaned!$K:$K,pg_transaction_cleaned!$M:$M,A19) -> 548940.41 | D19: =SUMIFS(bank_statement_cleaned!$G:$G,bank_statement_cleaned!$H:$H,A19) -> 548940.41 | E19: =D19-C19 -> 0 | F19: =IF(B19>DATE(2026,9,30),"Due in October",IF(COUNTIF(bank_statement_cleaned!$H:$H,A19)=0,"Missing",IF(ROUND(E19,2)=0,"Matched",IF(E19<0,"Short-paid","Excess")))) -> Matched | H19: Short-paid amount (INR) | I19: =ROUND(-L4,2) -> 1250 | J19: 1250 | K19: =IF(ROUND(I19-J19,2)=0,"PASS","FAIL") -> PASS
A20: STL-20260921 | B20: =DATE(MID(A20,5,4),MID(A20,9,2),RIGHT(A20,2)) -> 46286 | C20: =SUMIFS(pg_transaction_cleaned!$K:$K,pg_transaction_cleaned!$M:$M,A20) -> 592258.61 | D20: =SUMIFS(bank_statement_cleaned!$G:$G,bank_statement_cleaned!$H:$H,A20) -> 592258.61 | E20: =D20-C20 -> 0 | F20: =IF(B20>DATE(2026,9,30),"Due in October",IF(COUNTIF(bank_statement_cleaned!$H:$H,A20)=0,"Missing",IF(ROUND(E20,2)=0,"Matched",IF(E20<0,"Short-paid","Excess")))) -> Matched | H20: Missing amount (INR) | I20: =ROUND(J5,2) -> 551074.03 | J20: 551074.03 | K20: =IF(ROUND(I20-J20,2)=0,"PASS","FAIL") -> PASS
A21: STL-20260922 | B21: =DATE(MID(A21,5,4),MID(A21,9,2),RIGHT(A21,2)) -> 46287 | C21: =SUMIFS(pg_transaction_cleaned!$K:$K,pg_transaction_cleaned!$M:$M,A21) -> 584876.78 | D21: =SUMIFS(bank_statement_cleaned!$G:$G,bank_statement_cleaned!$H:$H,A21) -> 584876.78 | E21: =D21-C21 -> 0 | F21: =IF(B21>DATE(2026,9,30),"Due in October",IF(COUNTIF(bank_statement_cleaned!$H:$H,A21)=0,"Missing",IF(ROUND(E21,2)=0,"Matched",IF(E21<0,"Short-paid","Excess")))) -> Matched | H21: Due in October amount (INR) | I21: =ROUND(J6,2) -> 1265526.9 | J21: 1265526.9 | K21: =IF(ROUND(I21-J21,2)=0,"PASS","FAIL") -> PASS
A22: STL-20260923 | B22: =DATE(MID(A22,5,4),MID(A22,9,2),RIGHT(A22,2)) -> 46288 | C22: =SUMIFS(pg_transaction_cleaned!$K:$K,pg_transaction_cleaned!$M:$M,A22) -> 590273.39 | D22: =SUMIFS(bank_statement_cleaned!$G:$G,bank_statement_cleaned!$H:$H,A22) -> 590273.39 | E22: =D22-C22 -> 0 | F22: =IF(B22>DATE(2026,9,30),"Due in October",IF(COUNTIF(bank_statement_cleaned!$H:$H,A22)=0,"Missing",IF(ROUND(E22,2)=0,"Matched",IF(E22<0,"Short-paid","Excess")))) -> Matched | H22: Total gateway net (INR) | I22: =ROUND(C32,2) -> 18801899 | J22: 18801899 | K22: =IF(ROUND(I22-J22,2)=0,"PASS","FAIL") -> PASS
A23: STL-20260924 | B23: =DATE(MID(A23,5,4),MID(A23,9,2),RIGHT(A23,2)) -> 46289 | C23: =SUMIFS(pg_transaction_cleaned!$K:$K,pg_transaction_cleaned!$M:$M,A23) -> 540644.22 | D23: =SUMIFS(bank_statement_cleaned!$G:$G,bank_statement_cleaned!$H:$H,A23) -> 540644.22 | E23: =D23-C23 -> 0 | F23: =IF(B23>DATE(2026,9,30),"Due in October",IF(COUNTIF(bank_statement_cleaned!$H:$H,A23)=0,"Missing",IF(ROUND(E23,2)=0,"Matched",IF(E23<0,"Short-paid","Excess")))) -> Matched | H23: Gateway net ties to pg sheet (diff) | I23: =ROUND(C32-SUM(pg_transaction_cleaned!$K:$K),2) -> 0 | J23: 0 | K23: =IF(ROUND(I23-J23,2)=0,"PASS","FAIL") -> PASS
A24: STL-20260925 | B24: =DATE(MID(A24,5,4),MID(A24,9,2),RIGHT(A24,2)) -> 46290 | C24: =SUMIFS(pg_transaction_cleaned!$K:$K,pg_transaction_cleaned!$M:$M,A24) -> 594966.59 | D24: =SUMIFS(bank_statement_cleaned!$G:$G,bank_statement_cleaned!$H:$H,A24) -> 594966.59 | E24: =D24-C24 -> 0 | F24: =IF(B24>DATE(2026,9,30),"Due in October",IF(COUNTIF(bank_statement_cleaned!$H:$H,A24)=0,"Missing",IF(ROUND(E24,2)=0,"Matched",IF(E24<0,"Short-paid","Excess")))) -> Matched | H24: Total bank credit on batches (INR) | I24: =ROUND(D32,2) -> 16984049 | J24: 16984049 | K24: =IF(ROUND(I24-J24,2)=0,"PASS","FAIL") -> PASS
A25: STL-20260926 | B25: =DATE(MID(A25,5,4),MID(A25,9,2),RIGHT(A25,2)) -> 46291 | C25: =SUMIFS(pg_transaction_cleaned!$K:$K,pg_transaction_cleaned!$M:$M,A25) -> 711251.32 | D25: =SUMIFS(bank_statement_cleaned!$G:$G,bank_statement_cleaned!$H:$H,A25) -> 711251.32 | E25: =D25-C25 -> 0 | F25: =IF(B25>DATE(2026,9,30),"Due in October",IF(COUNTIF(bank_statement_cleaned!$H:$H,A25)=0,"Missing",IF(ROUND(E25,2)=0,"Matched",IF(E25<0,"Short-paid","Excess")))) -> Matched | H25: Bank gateway credits tie (diff) | I25: =ROUND(D32-SUMIF(bank_statement_cleaned!$I:$I,"Gateway",bank_statement_cleaned!$G:$G),2) -> 0 | J25: 0 | K25: =IF(ROUND(I25-J25,2)=0,"PASS","FAIL") -> PASS
A26: STL-20260927 | B26: =DATE(MID(A26,5,4),MID(A26,9,2),RIGHT(A26,2)) -> 46292 | C26: =SUMIFS(pg_transaction_cleaned!$K:$K,pg_transaction_cleaned!$M:$M,A26) -> 805057.1 | D26: =SUMIFS(bank_statement_cleaned!$G:$G,bank_statement_cleaned!$H:$H,A26) -> 805057.1 | E26: =D26-C26 -> 0 | F26: =IF(B26>DATE(2026,9,30),"Due in October",IF(COUNTIF(bank_statement_cleaned!$H:$H,A26)=0,"Missing",IF(ROUND(E26,2)=0,"Matched",IF(E26<0,"Short-paid","Excess")))) -> Matched | H26: Gap = short + missing + October (diff) | I26: =ROUND((C32-D32)-(-L4+J5+J6),2) -> 0 | J26: 0 | K26: =IF(ROUND(I26-J26,2)=0,"PASS","FAIL") -> PASS
A27: STL-20260928 | B27: =DATE(MID(A27,5,4),MID(A27,9,2),RIGHT(A27,2)) -> 46293 | C27: =SUMIFS(pg_transaction_cleaned!$K:$K,pg_transaction_cleaned!$M:$M,A27) -> 569672.43 | D27: =SUMIFS(bank_statement_cleaned!$G:$G,bank_statement_cleaned!$H:$H,A27) -> 569672.43 | E27: =D27-C27 -> 0 | F27: =IF(B27>DATE(2026,9,30),"Due in October",IF(COUNTIF(bank_statement_cleaned!$H:$H,A27)=0,"Missing",IF(ROUND(E27,2)=0,"Matched",IF(E27<0,"Short-paid","Excess")))) -> Matched
A28: STL-20260929 | B28: =DATE(MID(A28,5,4),MID(A28,9,2),RIGHT(A28,2)) -> 46294 | C28: =SUMIFS(pg_transaction_cleaned!$K:$K,pg_transaction_cleaned!$M:$M,A28) -> 641930.73 | D28: =SUMIFS(bank_statement_cleaned!$G:$G,bank_statement_cleaned!$H:$H,A28) -> 641930.73 | E28: =D28-C28 -> 0 | F28: =IF(B28>DATE(2026,9,30),"Due in October",IF(COUNTIF(bank_statement_cleaned!$H:$H,A28)=0,"Missing",IF(ROUND(E28,2)=0,"Matched",IF(E28<0,"Short-paid","Excess")))) -> Matched | H28: Checks passed | I28: =COUNTIF(K13:K26,"PASS")&" of "&COUNTA(K13:K26) -> 14 of 14
A29: STL-20260930 | B29: =DATE(MID(A29,5,4),MID(A29,9,2),RIGHT(A29,2)) -> 46295 | C29: =SUMIFS(pg_transaction_cleaned!$K:$K,pg_transaction_cleaned!$M:$M,A29) -> 694085.78 | D29: =SUMIFS(bank_statement_cleaned!$G:$G,bank_statement_cleaned!$H:$H,A29) -> 694085.78 | E29: =D29-C29 -> 0 | F29: =IF(B29>DATE(2026,9,30),"Due in October",IF(COUNTIF(bank_statement_cleaned!$H:$H,A29)=0,"Missing",IF(ROUND(E29,2)=0,"Matched",IF(E29<0,"Short-paid","Excess")))) -> Matched
A30: STL-20261001 | B30: =DATE(MID(A30,5,4),MID(A30,9,2),RIGHT(A30,2)) -> 46296 | C30: =SUMIFS(pg_transaction_cleaned!$K:$K,pg_transaction_cleaned!$M:$M,A30) -> 650622.7 | D30: =SUMIFS(bank_statement_cleaned!$G:$G,bank_statement_cleaned!$H:$H,A30) -> 0 | E30: =D30-C30 -> -650622.7 | F30: =IF(B30>DATE(2026,9,30),"Due in October",IF(COUNTIF(bank_statement_cleaned!$H:$H,A30)=0,"Missing",IF(ROUND(E30,2)=0,"Matched",IF(E30<0,"Short-paid","Excess")))) -> Due in October
A31: STL-20261002 | B31: =DATE(MID(A31,5,4),MID(A31,9,2),RIGHT(A31,2)) -> 46297 | C31: =SUMIFS(pg_transaction_cleaned!$K:$K,pg_transaction_cleaned!$M:$M,A31) -> 614904.2 | D31: =SUMIFS(bank_statement_cleaned!$G:$G,bank_statement_cleaned!$H:$H,A31) -> 0 | E31: =D31-C31 -> -614904.2 | F31: =IF(B31>DATE(2026,9,30),"Due in October",IF(COUNTIF(bank_statement_cleaned!$H:$H,A31)=0,"Missing",IF(ROUND(E31,2)=0,"Matched",IF(E31<0,"Short-paid","Excess")))) -> Due in October
A32: Total | C32: =SUM(C2:C31) -> 18801899 | D32: =SUM(D2:D31) -> 16984049 | E32: =SUM(E2:E31) -> -1817850.9

Sheet orders
A1: order_id | B1: order_date | C1: customer_id | D1: city | E1: payment_method | F1: order_amount | G1: order_status | H1: order_amount_cleaned | I1: city_clean | J1: capture_count | K1: capture_gross | L1: refund_count | M1: refund_amount | N1: exception_type | O1: exception_value
A2: ORD26000001 | B2: 46286 | C2: CUST28289 | D2: Pune | E2: UPI | F2: 299.0 | G2: Paid | H2: =VALUE(SUBSTITUTE(F2,",","")) -> 299 | I2: =IF(TRIM(D2)="","Unknown",TRIM(D2)) -> Pune | J2: =COUNTIFS(pg_transaction_cleaned!$O:$O,A2,pg_transaction_cleaned!$F:$F,"CAPTURE") -> 1 | K2: =SUMIFS(pg_transaction_cleaned!$H:$H,pg_transaction_cleaned!$O:$O,A2,pg_transaction_cleaned!$F:$F,"CAPTURE") -> 299 | L2: =COUNTIFS(pg_transaction_cleaned!$O:$O,A2,pg_transaction_cleaned!$F:$F,"REFUND") -> 0 | M2: =SUMIFS(pg_transaction_cleaned!$H:$H,pg_transaction_cleaned!$O:$O,A2,pg_transaction_cleaned!$F:$F,"REFUND") -> 0 | N2: =IF(AND(G2="Paid",J2=0),"Paid, no payment",IF(AND(OR(G2="Failed",G2="Cancelled"),J2>0),"Payment on failed/cancelled",IF(J2>1,"Duplicate charge",IF(AND(J2=1,ROUND(K2-H2,2)<>0),"Amount difference",IF(AND(G2="Refunded",L2=0),"Refunded, no refund",IF(AND(G2<>"Refunded",L2>0),"Refund, order not Refunded",IF(AND(L2>0,ROUND(M2-H2,2)<>0),"Refund amount differs","OK"))))))) -> OK | O2: =IF(N2="OK",0,IF(N2="Paid, no payment",H2,IF(N2="Payment on failed/cancelled",K2,IF(OR(N2="Duplicate charge",N2="Amount difference"),K2-H2,IF(N2="Refunded, no refund",H2,M2))))) -> 0
A3: ORD26000002 | B3: 46287 | C3: CUST38657 | D3: Bengaluru | E3: UPI | F3: 4647.0 | G3: Paid | H3: =VALUE(SUBSTITUTE(F3,",","")) -> 4647 | I3: =IF(TRIM(D3)="","Unknown",TRIM(D3)) -> Bengaluru | J3: =COUNTIFS(pg_transaction_cleaned!$O:$O,A3,pg_transaction_cleaned!$F:$F,"CAPTURE") -> 1 | K3: =SUMIFS(pg_transaction_cleaned!$H:$H,pg_transaction_cleaned!$O:$O,A3,pg_transaction_cleaned!$F:$F,"CAPTURE") -> 4647 | L3: =COUNTIFS(pg_transaction_cleaned!$O:$O,A3,pg_transaction_cleaned!$F:$F,"REFUND") -> 0 | M3: =SUMIFS(pg_transaction_cleaned!$H:$H,pg_transaction_cleaned!$O:$O,A3,pg_transaction_cleaned!$F:$F,"REFUND") -> 0 | N3: =IF(AND(G3="Paid",J3=0),"Paid, no payment",IF(AND(OR(G3="Failed",G3="Cancelled"),J3>0),"Payment on failed/cancelled",IF(J3>1,"Duplicate charge",IF(AND(J3=1,ROUND(K3-H3,2)<>0),"Amount difference",IF(AND(G3="Refunded",L3=0),"Refunded, no refund",IF(AND(G3<>"Refunded",L3>0),"Refund, order not Refunded",IF(AND(L3>0,ROUND(M3-H3,2)<>0),"Refund amount differs","OK"))))))) -> OK | O3: =IF(N3="OK",0,IF(N3="Paid, no payment",H3,IF(N3="Payment on failed/cancelled",K3,IF(OR(N3="Duplicate charge",N3="Amount difference"),K3-H3,IF(N3="Refunded, no refund",H3,M3))))) -> 0
A4: ORD26000003 | B4: 46282 | C4: CUST81426 | D4: Kolkata | E4: Card | F4: 2098.0 | G4: Paid | H4: =VALUE(SUBSTITUTE(F4,",","")) -> 2098 | I4: =IF(TRIM(D4)="","Unknown",TRIM(D4)) -> Kolkata | J4: =COUNTIFS(pg_transaction_cleaned!$O:$O,A4,pg_transaction_cleaned!$F:$F,"CAPTURE") -> 1 | K4: =SUMIFS(pg_transaction_cleaned!$H:$H,pg_transaction_cleaned!$O:$O,A4,pg_transaction_cleaned!$F:$F,"CAPTURE") -> 2098 | L4: =COUNTIFS(pg_transaction_cleaned!$O:$O,A4,pg_transaction_cleaned!$F:$F,"REFUND") -> 0 | M4: =SUMIFS(pg_transaction_cleaned!$H:$H,pg_transaction_cleaned!$O:$O,A4,pg_transaction_cleaned!$F:$F,"REFUND") -> 0 | N4: =IF(AND(G4="Paid",J4=0),"Paid, no payment",IF(AND(OR(G4="Failed",G4="Cancelled"),J4>0),"Payment on failed/cancelled",IF(J4>1,"Duplicate charge",IF(AND(J4=1,ROUND(K4-H4,2)<>0),"Amount difference",IF(AND(G4="Refunded",L4=0),"Refunded, no refund",IF(AND(G4<>"Refunded",L4>0),"Refund, order not Refunded",IF(AND(L4>0,ROUND(M4-H4,2)<>0),"Refund amount differs","OK"))))))) -> OK | O4: =IF(N4="OK",0,IF(N4="Paid, no payment",H4,IF(N4="Payment on failed/cancelled",K4,IF(OR(N4="Duplicate charge",N4="Amount difference"),K4-H4,IF(N4="Refunded, no refund",H4,M4))))) -> 0
A5: ORD26000004 | B5: 46273 | C5: CUST30926 | D5: Kolkata | E5: UPI | F5: 3298.0 | G5: Paid | H5: =VALUE(SUBSTITUTE(F5,",","")) -> 3298 | I5: =IF(TRIM(D5)="","Unknown",TRIM(D5)) -> Kolkata | J5: =COUNTIFS(pg_transaction_cleaned!$O:$O,A5,pg_transaction_cleaned!$F:$F,"CAPTURE") -> 1 | K5: =SUMIFS(pg_transaction_cleaned!$H:$H,pg_transaction_cleaned!$O:$O,A5,pg_transaction_cleaned!$F:$F,"CAPTURE") -> 3298 | L5: =COUNTIFS(pg_transaction_cleaned!$O:$O,A5,pg_transaction_cleaned!$F:$F,"REFUND") -> 0 | M5: =SUMIFS(pg_transaction_cleaned!$H:$H,pg_transaction_cleaned!$O:$O,A5,pg_transaction_cleaned!$F:$F,"REFUND") -> 0 | N5: =IF(AND(G5="Paid",J5=0),"Paid, no payment",IF(AND(OR(G5="Failed",G5="Cancelled"),J5>0),"Payment on failed/cancelled",IF(J5>1,"Duplicate charge",IF(AND(J5=1,ROUND(K5-H5,2)<>0),"Amount difference",IF(AND(G5="Refunded",L5=0),"Refunded, no refund",IF(AND(G5<>"Refunded",L5>0),"Refund, order not Refunded",IF(AND(L5>0,ROUND(M5-H5,2)<>0),"Refund amount differs","OK"))))))) -> OK | O5: =IF(N5="OK",0,IF(N5="Paid, no payment",H5,IF(N5="Payment on failed/cancelled",K5,IF(OR(N5="Duplicate charge",N5="Amount difference"),K5-H5,IF(N5="Refunded, no refund",H5,M5))))) -> 0
A6: ORD26000005 | B6: 46276 | C6: CUST23396 | D6: Pune | E6: Card | F6: 499.0 | G6: Paid | H6: =VALUE(SUBSTITUTE(F6,",","")) -> 499 | I6: =IF(TRIM(D6)="","Unknown",TRIM(D6)) -> Pune | J6: =COUNTIFS(pg_transaction_cleaned!$O:$O,A6,pg_transaction_cleaned!$F:$F,"CAPTURE") -> 1 | K6: =SUMIFS(pg_transaction_cleaned!$H:$H,pg_transaction_cleaned!$O:$O,A6,pg_transaction_cleaned!$F:$F,"CAPTURE") -> 499 | L6: =COUNTIFS(pg_transaction_cleaned!$O:$O,A6,pg_transaction_cleaned!$F:$F,"REFUND") -> 0 | M6: =SUMIFS(pg_transaction_cleaned!$H:$H,pg_transaction_cleaned!$O:$O,A6,pg_transaction_cleaned!$F:$F,"REFUND") -> 0 | N6: =IF(AND(G6="Paid",J6=0),"Paid, no payment",IF(AND(OR(G6="Failed",G6="Cancelled"),J6>0),"Payment on failed/cancelled",IF(J6>1,"Duplicate charge",IF(AND(J6=1,ROUND(K6-H6,2)<>0),"Amount difference",IF(AND(G6="Refunded",L6=0),"Refunded, no refund",IF(AND(G6<>"Refunded",L6>0),"Refund, order not Refunded",IF(AND(L6>0,ROUND(M6-H6,2)<>0),"Refund amount differs","OK"))))))) -> OK | O6: =IF(N6="OK",0,IF(N6="Paid, no payment",H6,IF(N6="Payment on failed/cancelled",K6,IF(OR(N6="Duplicate charge",N6="Amount difference"),K6-H6,IF(N6="Refunded, no refund",H6,M6))))) -> 0
A7: ORD26000006 | B7: 46278 | C7: CUST15695 | D7: Ahmedabad | E7: Card | F7: 999.0 | G7: Paid | H7: =VALUE(SUBSTITUTE(F7,",","")) -> 999 | I7: =IF(TRIM(D7)="","Unknown",TRIM(D7)) -> Ahmedabad | J7: =COUNTIFS(pg_transaction_cleaned!$O:$O,A7,pg_transaction_cleaned!$F:$F,"CAPTURE") -> 1 | K7: =SUMIFS(pg_transaction_cleaned!$H:$H,pg_transaction_cleaned!$O:$O,A7,pg_transaction_cleaned!$F:$F,"CAPTURE") -> 999 | L7: =COUNTIFS(pg_transaction_cleaned!$O:$O,A7,pg_transaction_cleaned!$F:$F,"REFUND") -> 0 | M7: =SUMIFS(pg_transaction_cleaned!$H:$H,pg_transaction_cleaned!$O:$O,A7,pg_transaction_cleaned!$F:$F,"REFUND") -> 0 | N7: =IF(AND(G7="Paid",J7=0),"Paid, no payment",IF(AND(OR(G7="Failed",G7="Cancelled"),J7>0),"Payment on failed/cancelled",IF(J7>1,"Duplicate charge",IF(AND(J7=1,ROUND(K7-H7,2)<>0),"Amount difference",IF(AND(G7="Refunded",L7=0),"Refunded, no refund",IF(AND(G7<>"Refunded",L7>0),"Refund, order not Refunded",IF(AND(L7>0,ROUND(M7-H7,2)<>0),"Refund amount differs","OK"))))))) -> OK | O7: =IF(N7="OK",0,IF(N7="Paid, no payment",H7,IF(N7="Payment on failed/cancelled",K7,IF(OR(N7="Duplicate charge",N7="Amount difference"),K7-H7,IF(N7="Refunded, no refund",H7,M7))))) -> 0
A8: ORD26000007 | B8: 46283 | C8: CUST92397 | D8: Lucknow | E8: UPI | F8: 1299.0 | G8: Paid | H8: =VALUE(SUBSTITUTE(F8,",","")) -> 1299 | I8: =IF(TRIM(D8)="","Unknown",TRIM(D8)) -> Lucknow | J8: =COUNTIFS(pg_transaction_cleaned!$O:$O,A8,pg_transaction_cleaned!$F:$F,"CAPTURE") -> 1 | K8: =SUMIFS(pg_transaction_cleaned!$H:$H,pg_transaction_cleaned!$O:$O,A8,pg_transaction_cleaned!$F:$F,"CAPTURE") -> 1299 | L8: =COUNTIFS(pg_transaction_cleaned!$O:$O,A8,pg_transaction_cleaned!$F:$F,"REFUND") -> 0 | M8: =SUMIFS(pg_transaction_cleaned!$H:$H,pg_transaction_cleaned!$O:$O,A8,pg_transaction_cleaned!$F:$F,"REFUND") -> 0 | N8: =IF(AND(G8="Paid",J8=0),"Paid, no payment",IF(AND(OR(G8="Failed",G8="Cancelled"),J8>0),"Payment on failed/cancelled",IF(J8>1,"Duplicate charge",IF(AND(J8=1,ROUND(K8-H8,2)<>0),"Amount difference",IF(AND(G8="Refunded",L8=0),"Refunded, no refund",IF(AND(G8<>"Refunded",L8>0),"Refund, order not Refunded",IF(AND(L8>0,ROUND(M8-H8,2)<>0),"Refund amount differs","OK"))))))) -> OK | O8: =IF(N8="OK",0,IF(N8="Paid, no payment",H8,IF(N8="Payment on failed/cancelled",K8,IF(OR(N8="Duplicate charge",N8="Amount difference"),K8-H8,IF(N8="Refunded, no refund",H8,M8))))) -> 0
A9: ORD26000008 | B9: 46294 | C9: CUST96673 | D9: Bengaluru | E9: UPI | F9: 2499.0 | G9: Paid | H9: =VALUE(SUBSTITUTE(F9,",","")) -> 2499 | I9: =IF(TRIM(D9)="","Unknown",TRIM(D9)) -> Bengaluru | J9: =COUNTIFS(pg_transaction_cleaned!$O:$O,A9,pg_transaction_cleaned!$F:$F,"CAPTURE") -> 1 | K9: =SUMIFS(pg_transaction_cleaned!$H:$H,pg_transaction_cleaned!$O:$O,A9,pg_transaction_cleaned!$F:$F,"CAPTURE") -> 2499 | L9: =COUNTIFS(pg_transaction_cleaned!$O:$O,A9,pg_transaction_cleaned!$F:$F,"REFUND") -> 0 | M9: =SUMIFS(pg_transaction_cleaned!$H:$H,pg_transaction_cleaned!$O:$O,A9,pg_transaction_cleaned!$F:$F,"REFUND") -> 0 | N9: =IF(AND(G9="Paid",J9=0),"Paid, no payment",IF(AND(OR(G9="Failed",G9="Cancelled"),J9>0),"Payment on failed/cancelled",IF(J9>1,"Duplicate charge",IF(AND(J9=1,ROUND(K9-H9,2)<>0),"Amount difference",IF(AND(G9="Refunded",L9=0),"Refunded, no refund",IF(AND(G9<>"Refunded",L9>0),"Refund, order not Refunded",IF(AND(L9>0,ROUND(M9-H9,2)<>0),"Refund amount differs","OK"))))))) -> OK | O9: =IF(N9="OK",0,IF(N9="Paid, no payment",H9,IF(N9="Payment on failed/cancelled",K9,IF(OR(N9="Duplicate charge",N9="Amount difference"),K9-H9,IF(N9="Refunded, no refund",H9,M9))))) -> 0
A10: ORD26000009 | B10: 46290 | C10: CUST59823 | D10: Hyderabad | E10: NetBanking | F10: 349.0 | G10: Paid | H10: =VALUE(SUBSTITUTE(F10,",","")) -> 349 | I10: =IF(TRIM(D10)="","Unknown",TRIM(D10)) -> Hyderabad | J10: =COUNTIFS(pg_transaction_cleaned!$O:$O,A10,pg_transaction_cleaned!$F:$F,"CAPTURE") -> 1 | K10: =SUMIFS(pg_transaction_cleaned!$H:$H,pg_transaction_cleaned!$O:$O,A10,pg_transaction_cleaned!$F:$F,"CAPTURE") -> 349 | L10: =COUNTIFS(pg_transaction_cleaned!$O:$O,A10,pg_transaction_cleaned!$F:$F,"REFUND") -> 0 | M10: =SUMIFS(pg_transaction_cleaned!$H:$H,pg_transaction_cleaned!$O:$O,A10,pg_transaction_cleaned!$F:$F,"REFUND") -> 0 | N10: =IF(AND(G10="Paid",J10=0),"Paid, no payment",IF(AND(OR(G10="Failed",G10="Cancelled"),J10>0),"Payment on failed/cancelled",IF(J10>1,"Duplicate charge",IF(AND(J10=1,ROUND(K10-H10,2)<>0),"Amount difference",IF(AND(G10="Refunded",L10=0),"Refunded, no refund",IF(AND(G10<>"Refunded",L10>0),"Refund, order not Refunded",IF(AND(L10>0,ROUND(M10-H10,2)<>0),"Refund amount differs","OK"))))))) -> OK | O10: =IF(N10="OK",0,IF(N10="Paid, no payment",H10,IF(N10="Payment on failed/cancelled",K10,IF(OR(N10="Duplicate charge",N10="Amount difference"),K10-H10,IF(N10="Refunded, no refund",H10,M10))))) -> 0
A11: ORD26000010 | B11: 46280 | C11: CUST44993 | D11: Pune | E11: UPI | F11: 9497.0 | G11: Paid | H11: =VALUE(SUBSTITUTE(F11,",","")) -> 9497 | I11: =IF(TRIM(D11)="","Unknown",TRIM(D11)) -> Pune | J11: =COUNTIFS(pg_transaction_cleaned!$O:$O,A11,pg_transaction_cleaned!$F:$F,"CAPTURE") -> 1 | K11: =SUMIFS(pg_transaction_cleaned!$H:$H,pg_transaction_cleaned!$O:$O,A11,pg_transaction_cleaned!$F:$F,"CAPTURE") -> 9497 | L11: =COUNTIFS(pg_transaction_cleaned!$O:$O,A11,pg_transaction_cleaned!$F:$F,"REFUND") -> 0 | M11: =SUMIFS(pg_transaction_cleaned!$H:$H,pg_transaction_cleaned!$O:$O,A11,pg_transaction_cleaned!$F:$F,"REFUND") -> 0 | N11: =IF(AND(G11="Paid",J11=0),"Paid, no payment",IF(AND(OR(G11="Failed",G11="Cancelled"),J11>0),"Payment on failed/cancelled",IF(J11>1,"Duplicate charge",IF(AND(J11=1,ROUND(K11-H11,2)<>0),"Amount difference",IF(AND(G11="Refunded",L11=0),"Refunded, no refund",IF(AND(G11<>"Refunded",L11>0),"Refund, order not Refunded",IF(AND(L11>0,ROUND(M11-H11,2)<>0),"Refund amount differs","OK"))))))) -> OK | O11: =IF(N11="OK",0,IF(N11="Paid, no payment",H11,IF(N11="Payment on failed/cancelled",K11,IF(OR(N11="Duplicate charge",N11="Amount difference"),K11-H11,IF(N11="Refunded, no refund",H11,M11))))) -> 0
A12: ORD26000011 | B12: 46285 | C12: CUST45382 | D12: Jaipur | E12: UPI | F12: 5797.0 | G12: Paid | H12: =VALUE(SUBSTITUTE(F12,",","")) -> 5797 | I12: =IF(TRIM(D12)="","Unknown",TRIM(D12)) -> Jaipur | J12: =COUNTIFS(pg_transaction_cleaned!$O:$O,A12,pg_transaction_cleaned!$F:$F,"CAPTURE") -> 1 | K12: =SUMIFS(pg_transaction_cleaned!$H:$H,pg_transaction_cleaned!$O:$O,A12,pg_transaction_cleaned!$F:$F,"CAPTURE") -> 5797 | L12: =COUNTIFS(pg_transaction_cleaned!$O:$O,A12,pg_transaction_cleaned!$F:$F,"REFUND") -> 0 | M12: =SUMIFS(pg_transaction_cleaned!$H:$H,pg_transaction_cleaned!$O:$O,A12,pg_transaction_cleaned!$F:$F,"REFUND") -> 0 | N12: =IF(AND(G12="Paid",J12=0),"Paid, no payment",IF(AND(OR(G12="Failed",G12="Cancelled"),J12>0),"Payment on failed/cancelled",IF(J12>1,"Duplicate charge",IF(AND(J12=1,ROUND(K12-H12,2)<>0),"Amount difference",IF(AND(G12="Refunded",L12=0),"Refunded, no refund",IF(AND(G12<>"Refunded",L12>0),"Refund, order not Refunded",IF(AND(L12>0,ROUND(M12-H12,2)<>0),"Refund amount differs","OK"))))))) -> OK | O12: =IF(N12="OK",0,IF(N12="Paid, no payment",H12,IF(N12="Payment on failed/cancelled",K12,IF(OR(N12="Duplicate charge",N12="Amount difference"),K12-H12,IF(N12="Refunded, no refund",H12,M12))))) -> 0
A13: ORD26000012 | B13: 46273 | C13: CUST14207 | D13: Chennai | E13: UPI | F13: 13997.0 | G13: Paid | H13: =VALUE(SUBSTITUTE(F13,",","")) -> 13997 | I13: =IF(TRIM(D13)="","Unknown",TRIM(D13)) -> Chennai | J13: =COUNTIFS(pg_transaction_cleaned!$O:$O,A13,pg_transaction_cleaned!$F:$F,"CAPTURE") -> 1 | K13: =SUMIFS(pg_transaction_cleaned!$H:$H,pg_transaction_cleaned!$O:$O,A13,pg_transaction_cleaned!$F:$F,"CAPTURE") -> 13997 | L13: =COUNTIFS(pg_transaction_cleaned!$O:$O,A13,pg_transaction_cleaned!$F:$F,"REFUND") -> 0 | M13: =SUMIFS(pg_transaction_cleaned!$H:$H,pg_transaction_cleaned!$O:$O,A13,pg_transaction_cleaned!$F:$F,"REFUND") -> 0 | N13: =IF(AND(G13="Paid",J13=0),"Paid, no payment",IF(AND(OR(G13="Failed",G13="Cancelled"),J13>0),"Payment on failed/cancelled",IF(J13>1,"Duplicate charge",IF(AND(J13=1,ROUND(K13-H13,2)<>0),"Amount difference",IF(AND(G13="Refunded",L13=0),"Refunded, no refund",IF(AND(G13<>"Refunded",L13>0),"Refund, order not Refunded",IF(AND(L13>0,ROUND(M13-H13,2)<>0),"Refund amount differs","OK"))))))) -> OK | O13: =IF(N13="OK",0,IF(N13="Paid, no payment",H13,IF(N13="Payment on failed/cancelled",K13,IF(OR(N13="Duplicate charge",N13="Amount difference"),K13-H13,IF(N13="Refunded, no refund",H13,M13))))) -> 0
... A80: ORD26000079 | B80: 46285 | C80: CUST76162 | D80: Kolkata | E80: Card | F80: 4999.0 | G80: Failed | H80: =VALUE(SUBSTITUTE(F80,",","")) -> 4999 | I80: =IF(TRIM(D80)="","Unknown",TRIM(D80)) -> Kolkata | J80: =COUNTIFS(pg_transaction_cleaned!$O:$O,A80,pg_transaction_cleaned!$F:$F,"CAPTURE") -> 0 | K80: =SUMIFS(pg_transaction_cleaned!$H:$H,pg_transaction_cleaned!$O:$O,A80,pg_transaction_cleaned!$F:$F,"CAPTURE") -> 0 | L80: =COUNTIFS(pg_transaction_cleaned!$O:$O,A80,pg_transaction_cleaned!$F:$F,"REFUND") -> 0 | M80: =SUMIFS(pg_transaction_cleaned!$H:$H,pg_transaction_cleaned!$O:$O,A80,pg_transaction_cleaned!$F:$F,"REFUND") -> 0 | N80: =IF(AND(G80="Paid",J80=0),"Paid, no payment",IF(AND(OR(G80="Failed",G80="Cancelled"),J80>0),"Payment on failed/cancelled",IF(J80>1,"Duplicate charge",IF(AND(J80=1,ROUND(K80-H80,2)<>0),"Amount difference",IF(AND(G80="Refunded",L80=0),"Refunded, no refund",IF(AND(G80<>"Refunded",L80>0),"Refund, order not Refunded",IF(AND(L80>0,ROUND(M80-H80,2)<>0),"Refund amount differs","OK"))))))) -> OK | O80: =IF(N80="OK",0,IF(N80="Paid, no payment",H80,IF(N80="Payment on failed/cancelled",K80,IF(OR(N80="Duplicate charge",N80="Amount difference"),K80-H80,IF(N80="Refunded, no refund",H80,M80))))) -> 0
A81: ORD26000080 | B81: 46292 | C81: CUST43972 | E81: UPI | F81: 1998.0 | G81: Paid | H81: =VALUE(SUBSTITUTE(F81,",","")) -> 1998 | I81: =IF(TRIM(D81)="","Unknown",TRIM(D81)) -> Unknown | J81: =COUNTIFS(pg_transaction_cleaned!$O:$O,A81,pg_transaction_cleaned!$F:$F,"CAPTURE") -> 1 | K81: =SUMIFS(pg_transaction_cleaned!$H:$H,pg_transaction_cleaned!$O:$O,A81,pg_transaction_cleaned!$F:$F,"CAPTURE") -> 1998 | L81: =COUNTIFS(pg_transaction_cleaned!$O:$O,A81,pg_transaction_cleaned!$F:$F,"REFUND") -> 0 | M81: =SUMIFS(pg_transaction_cleaned!$H:$H,pg_transaction_cleaned!$O:$O,A81,pg_transaction_cleaned!$F:$F,"REFUND") -> 0 | N81: =IF(AND(G81="Paid",J81=0),"Paid, no payment",IF(AND(OR(G81="Failed",G81="Cancelled"),J81>0),"Payment on failed/cancelled",IF(J81>1,"Duplicate charge",IF(AND(J81=1,ROUND(K81-H81,2)<>0),"Amount difference",IF(AND(G81="Refunded",L81=0),"Refunded, no refund",IF(AND(G81<>"Refunded",L81>0),"Refund, order not Refunded",IF(AND(L81>0,ROUND(M81-H81,2)<>0),"Refund amount differs","OK"))))))) -> OK | O81: =IF(N81="OK",0,IF(N81="Paid, no payment",H81,IF(N81="Payment on failed/cancelled",K81,IF(OR(N81="Duplicate charge",N81="Amount difference"),K81-H81,IF(N81="Refunded, no refund",H81,M81))))) -> 0
A82: ORD26000081 | B82: 46292 | C82: CUST45992 | D82: Ahmedabad | E82: Card | F82: 10797.0 | G82: Paid | H82: =VALUE(SUBSTITUTE(F82,",","")) -> 10797 | I82: =IF(TRIM(D82)="","Unknown",TRIM(D82)) -> Ahmedabad | J82: =COUNTIFS(pg_transaction_cleaned!$O:$O,A82,pg_transaction_cleaned!$F:$F,"CAPTURE") -> 1 | K82: =SUMIFS(pg_transaction_cleaned!$H:$H,pg_transaction_cleaned!$O:$O,A82,pg_transaction_cleaned!$F:$F,"CAPTURE") -> 10797 | L82: =COUNTIFS(pg_transaction_cleaned!$O:$O,A82,pg_transaction_cleaned!$F:$F,"REFUND") -> 0 | M82: =SUMIFS(pg_transaction_cleaned!$H:$H,pg_transaction_cleaned!$O:$O,A82,pg_transaction_cleaned!$F:$F,"REFUND") -> 0 | N82: =IF(AND(G82="Paid",J82=0),"Paid, no payment",IF(AND(OR(G82="Failed",G82="Cancelled"),J82>0),"Payment on failed/cancelled",IF(J82>1,"Duplicate charge",IF(AND(J82=1,ROUND(K82-H82,2)<>0),"Amount difference",IF(AND(G82="Refunded",L82=0),"Refunded, no refund",IF(AND(G82<>"Refunded",L82>0),"Refund, order not Refunded",IF(AND(L82>0,ROUND(M82-H82,2)<>0),"Refund amount differs","OK"))))))) -> OK | O82: =IF(N82="OK",0,IF(N82="Paid, no payment",H82,IF(N82="Payment on failed/cancelled",K82,IF(OR(N82="Duplicate charge",N82="Amount difference"),K82-H82,IF(N82="Refunded, no refund",H82,M82))))) -> 0
A83: ORD26000082 | B83: 46268 | C83: CUST20561 | D83: Delhi | E83: Wallet | F83: 2197.0 | G83: Paid | H83: =VALUE(SUBSTITUTE(F83,",","")) -> 2197 | I83: =IF(TRIM(D83)="","Unknown",TRIM(D83)) -> Delhi | J83: =COUNTIFS(pg_transaction_cleaned!$O:$O,A83,pg_transaction_cleaned!$F:$F,"CAPTURE") -> 1 | K83: =SUMIFS(pg_transaction_cleaned!$H:$H,pg_transaction_cleaned!$O:$O,A83,pg_transaction_cleaned!$F:$F,"CAPTURE") -> 2197 | L83: =COUNTIFS(pg_transaction_cleaned!$O:$O,A83,pg_transaction_cleaned!$F:$F,"REFUND") -> 0 | M83: =SUMIFS(pg_transaction_cleaned!$H:$H,pg_transaction_cleaned!$O:$O,A83,pg_transaction_cleaned!$F:$F,"REFUND") -> 0 | N83: =IF(AND(G83="Paid",J83=0),"Paid, no payment",IF(AND(OR(G83="Failed",G83="Cancelled"),J83>0),"Payment on failed/cancelled",IF(J83>1,"Duplicate charge",IF(AND(J83=1,ROUND(K83-H83,2)<>0),"Amount difference",IF(AND(G83="Refunded",L83=0),"Refunded, no refund",IF(AND(G83<>"Refunded",L83>0),"Refund, order not Refunded",IF(AND(L83>0,ROUND(M83-H83,2)<>0),"Refund amount differs","OK"))))))) -> OK | O83: =IF(N83="OK",0,IF(N83="Paid, no payment",H83,IF(N83="Payment on failed/cancelled",K83,IF(OR(N83="Duplicate charge",N83="Amount difference"),K83-H83,IF(N83="Refunded, no refund",H83,M83))))) -> 0
A84: ORD26000083 | B84: 46270 | C84: CUST18418 | D84: Kolkata | E84: Card | F84: 1299.0 | G84: Paid | H84: =VALUE(SUBSTITUTE(F84,",","")) -> 1299 | I84: =IF(TRIM(D84)="","Unknown",TRIM(D84)) -> Kolkata | J84: =COUNTIFS(pg_transaction_cleaned!$O:$O,A84,pg_transaction_cleaned!$F:$F,"CAPTURE") -> 1 | K84: =SUMIFS(pg_transaction_cleaned!$H:$H,pg_transaction_cleaned!$O:$O,A84,pg_transaction_cleaned!$F:$F,"CAPTURE") -> 1299 | L84: =COUNTIFS(pg_transaction_cleaned!$O:$O,A84,pg_transaction_cleaned!$F:$F,"REFUND") -> 0 | M84: =SUMIFS(pg_transaction_cleaned!$H:$H,pg_transaction_cleaned!$O:$O,A84,pg_transaction_cleaned!$F:$F,"REFUND") -> 0 | N84: =IF(AND(G84="Paid",J84=0),"Paid, no payment",IF(AND(OR(G84="Failed",G84="Cancelled"),J84>0),"Payment on failed/cancelled",IF(J84>1,"Duplicate charge",IF(AND(J84=1,ROUND(K84-H84,2)<>0),"Amount difference",IF(AND(G84="Refunded",L84=0),"Refunded, no refund",IF(AND(G84<>"Refunded",L84>0),"Refund, order not Refunded",IF(AND(L84>0,ROUND(M84-H84,2)<>0),"Refund amount differs","OK"))))))) -> OK | O84: =IF(N84="OK",0,IF(N84="Paid, no payment",H84,IF(N84="Payment on failed/cancelled",K84,IF(OR(N84="Duplicate charge",N84="Amount difference"),K84-H84,IF(N84="Refunded, no refund",H84,M84))))) -> 0
A85: ORD26000084 | B85: 46279 | C85: CUST65069 | D85: Kolkata | E85: UPI | F85: 1799.0 | G85: Paid | H85: =VALUE(SUBSTITUTE(F85,",","")) -> 1799 | I85: =IF(TRIM(D85)="","Unknown",TRIM(D85)) -> Kolkata | J85: =COUNTIFS(pg_transaction_cleaned!$O:$O,A85,pg_transaction_cleaned!$F:$F,"CAPTURE") -> 1 | K85: =SUMIFS(pg_transaction_cleaned!$H:$H,pg_transaction_cleaned!$O:$O,A85,pg_transaction_cleaned!$F:$F,"CAPTURE") -> 1799 | L85: =COUNTIFS(pg_transaction_cleaned!$O:$O,A85,pg_transaction_cleaned!$F:$F,"REFUND") -> 0 | M85: =SUMIFS(pg_transaction_cleaned!$H:$H,pg_transaction_cleaned!$O:$O,A85,pg_transaction_cleaned!$F:$F,"REFUND") -> 0 | N85: =IF(AND(G85="Paid",J85=0),"Paid, no payment",IF(AND(OR(G85="Failed",G85="Cancelled"),J85>0),"Payment on failed/cancelled",IF(J85>1,"Duplicate charge",IF(AND(J85=1,ROUND(K85-H85,2)<>0),"Amount difference",IF(AND(G85="Refunded",L85=0),"Refunded, no refund",IF(AND(G85<>"Refunded",L85>0),"Refund, order not Refunded",IF(AND(L85>0,ROUND(M85-H85,2)<>0),"Refund amount differs","OK"))))))) -> OK | O85: =IF(N85="OK",0,IF(N85="Paid, no payment",H85,IF(N85="Payment on failed/cancelled",K85,IF(OR(N85="Duplicate charge",N85="Amount difference"),K85-H85,IF(N85="Refunded, no refund",H85,M85))))) -> 0
A86: ORD26000085 | B86: 46294 | C86: CUST59857 | D86: Ahmedabad | E86: Card | F86: 3798.0 | G86: Paid | H86: =VALUE(SUBSTITUTE(F86,",","")) -> 3798 | I86: =IF(TRIM(D86)="","Unknown",TRIM(D86)) -> Ahmedabad | J86: =COUNTIFS(pg_transaction_cleaned!$O:$O,A86,pg_transaction_cleaned!$F:$F,"CAPTURE") -> 1 | K86: =SUMIFS(pg_transaction_cleaned!$H:$H,pg_transaction_cleaned!$O:$O,A86,pg_transaction_cleaned!$F:$F,"CAPTURE") -> 3798 | L86: =COUNTIFS(pg_transaction_cleaned!$O:$O,A86,pg_transaction_cleaned!$F:$F,"REFUND") -> 0 | M86: =SUMIFS(pg_transaction_cleaned!$H:$H,pg_transaction_cleaned!$O:$O,A86,pg_transaction_cleaned!$F:$F,"REFUND") -> 0 | N86: =IF(AND(G86="Paid",J86=0),"Paid, no payment",IF(AND(OR(G86="Failed",G86="Cancelled"),J86>0),"Payment on failed/cancelled",IF(J86>1,"Duplicate charge",IF(AND(J86=1,ROUND(K86-H86,2)<>0),"Amount difference",IF(AND(G86="Refunded",L86=0),"Refunded, no refund",IF(AND(G86<>"Refunded",L86>0),"Refund, order not Refunded",IF(AND(L86>0,ROUND(M86-H86,2)<>0),"Refund amount differs","OK"))))))) -> OK | O86: =IF(N86="OK",0,IF(N86="Paid, no payment",H86,IF(N86="Payment on failed/cancelled",K86,IF(OR(N86="Duplicate charge",N86="Amount difference"),K86-H86,IF(N86="Refunded, no refund",H86,M86))))) -> 0
A87: ORD26000086 | B87: 46266 | C87: CUST64921 | D87: Jaipur | E87: NetBanking | F87: 799.0 | G87: Paid | H87: =VALUE(SUBSTITUTE(F87,",","")) -> 799 | I87: =IF(TRIM(D87)="","Unknown",TRIM(D87)) -> Jaipur | J87: =COUNTIFS(pg_transaction_cleaned!$O:$O,A87,pg_transaction_cleaned!$F:$F,"CAPTURE") -> 1 | K87: =SUMIFS(pg_transaction_cleaned!$H:$H,pg_transaction_cleaned!$O:$O,A87,pg_transaction_cleaned!$F:$F,"CAPTURE") -> 799 | L87: =COUNTIFS(pg_transaction_cleaned!$O:$O,A87,pg_transaction_cleaned!$F:$F,"REFUND") -> 0 | M87: =SUMIFS(pg_transaction_cleaned!$H:$H,pg_transaction_cleaned!$O:$O,A87,pg_transaction_cleaned!$F:$F,"REFUND") -> 0 | N87: =IF(AND(G87="Paid",J87=0),"Paid, no payment",IF(AND(OR(G87="Failed",G87="Cancelled"),J87>0),"Payment on failed/cancelled",IF(J87>1,"Duplicate charge",IF(AND(J87=1,ROUND(K87-H87,2)<>0),"Amount difference",IF(AND(G87="Refunded",L87=0),"Refunded, no refund",IF(AND(G87<>"Refunded",L87>0),"Refund, order not Refunded",IF(AND(L87>0,ROUND(M87-H87,2)<>0),"Refund amount differs","OK"))))))) -> OK | O87: =IF(N87="OK",0,IF(N87="Paid, no payment",H87,IF(N87="Payment on failed/cancelled",K87,IF(OR(N87="Duplicate charge",N87="Amount difference"),K87-H87,IF(N87="Refunded, no refund",H87,M87))))) -> 0
A88: ORD26000087 | B88: 46289 | C88: CUST45774 | D88: Kolkata | E88: UPI | F88: 9297.0 | G88: Failed | H88: =VALUE(SUBSTITUTE(F88,",","")) -> 9297 | I88: =IF(TRIM(D88)="","Unknown",TRIM(D88)) -> Kolkata | J88: =COUNTIFS(pg_transaction_cleaned!$O:$O,A88,pg_transaction_cleaned!$F:$F,"CAPTURE") -> 0 | K88: =SUMIFS(pg_transaction_cleaned!$H:$H,pg_transaction_cleaned!$O:$O,A88,pg_transaction_cleaned!$F:$F,"CAPTURE") -> 0 | L88: =COUNTIFS(pg_transaction_cleaned!$O:$O,A88,pg_transaction_cleaned!$F:$F,"REFUND") -> 0 | M88: =SUMIFS(pg_transaction_cleaned!$H:$H,pg_transaction_cleaned!$O:$O,A88,pg_transaction_cleaned!$F:$F,"REFUND") -> 0 | N88: =IF(AND(G88="Paid",J88=0),"Paid, no payment",IF(AND(OR(G88="Failed",G88="Cancelled"),J88>0),"Payment on failed/cancelled",IF(J88>1,"Duplicate charge",IF(AND(J88=1,ROUND(K88-H88,2)<>0),"Amount difference",IF(AND(G88="Refunded",L88=0),"Refunded, no refund",IF(AND(G88<>"Refunded",L88>0),"Refund, order not Refunded",IF(AND(L88>0,ROUND(M88-H88,2)<>0),"Refund amount differs","OK"))))))) -> OK | O88: =IF(N88="OK",0,IF(N88="Paid, no payment",H88,IF(N88="Payment on failed/cancelled",K88,IF(OR(N88="Duplicate charge",N88="Amount difference"),K88-H88,IF(N88="Refunded, no refund",H88,M88))))) -> 0
A89: ORD26000088 | B89: 46281 | C89: CUST62994 | D89: Delhi | E89: Card | F89: 1299.0 | G89: Paid | H89: =VALUE(SUBSTITUTE(F89,",","")) -> 1299 | I89: =IF(TRIM(D89)="","Unknown",TRIM(D89)) -> Delhi | J89: =COUNTIFS(pg_transaction_cleaned!$O:$O,A89,pg_transaction_cleaned!$F:$F,"CAPTURE") -> 1 | K89: =SUMIFS(pg_transaction_cleaned!$H:$H,pg_transaction_cleaned!$O:$O,A89,pg_transaction_cleaned!$F:$F,"CAPTURE") -> 1299 | L89: =COUNTIFS(pg_transaction_cleaned!$O:$O,A89,pg_transaction_cleaned!$F:$F,"REFUND") -> 0 | M89: =SUMIFS(pg_transaction_cleaned!$H:$H,pg_transaction_cleaned!$O:$O,A89,pg_transaction_cleaned!$F:$F,"REFUND") -> 0 | N89: =IF(AND(G89="Paid",J89=0),"Paid, no payment",IF(AND(OR(G89="Failed",G89="Cancelled"),J89>0),"Payment on failed/cancelled",IF(J89>1,"Duplicate charge",IF(AND(J89=1,ROUND(K89-H89,2)<>0),"Amount difference",IF(AND(G89="Refunded",L89=0),"Refunded, no refund",IF(AND(G89<>"Refunded",L89>0),"Refund, order not Refunded",IF(AND(L89>0,ROUND(M89-H89,2)<>0),"Refund amount differs","OK"))))))) -> OK | O89: =IF(N89="OK",0,IF(N89="Paid, no payment",H89,IF(N89="Payment on failed/cancelled",K89,IF(OR(N89="Duplicate charge",N89="Amount difference"),K89-H89,IF(N89="Refunded, no refund",H89,M89))))) -> 0
A90: ORD26000089 | B90: 46292 | C90: CUST87580 | D90: Lucknow | E90: Wallet | F90: 2998.0 | G90: Paid | H90: =VALUE(SUBSTITUTE(F90,",","")) -> 2998 | I90: =IF(TRIM(D90)="","Unknown",TRIM(D90)) -> Lucknow | J90: =COUNTIFS(pg_transaction_cleaned!$O:$O,A90,pg_transaction_cleaned!$F:$F,"CAPTURE") -> 1 | K90: =SUMIFS(pg_transaction_cleaned!$H:$H,pg_transaction_cleaned!$O:$O,A90,pg_transaction_cleaned!$F:$F,"CAPTURE") -> 2998 | L90: =COUNTIFS(pg_transaction_cleaned!$O:$O,A90,pg_transaction_cleaned!$F:$F,"REFUND") -> 0 | M90: =SUMIFS(pg_transaction_cleaned!$H:$H,pg_transaction_cleaned!$O:$O,A90,pg_transaction_cleaned!$F:$F,"REFUND") -> 0 | N90: =IF(AND(G90="Paid",J90=0),"Paid, no payment",IF(AND(OR(G90="Failed",G90="Cancelled"),J90>0),"Payment on failed/cancelled",IF(J90>1,"Duplicate charge",IF(AND(J90=1,ROUND(K90-H90,2)<>0),"Amount difference",IF(AND(G90="Refunded",L90=0),"Refunded, no refund",IF(AND(G90<>"Refunded",L90>0),"Refund, order not Refunded",IF(AND(L90>0,ROUND(M90-H90,2)<>0),"Refund amount differs","OK"))))))) -> OK | O90: =IF(N90="OK",0,IF(N90="Paid, no payment",H90,IF(N90="Payment on failed/cancelled",K90,IF(OR(N90="Duplicate charge",N90="Amount difference"),K90-H90,IF(N90="Refunded, no refund",H90,M90))))) -> 0
A91: ORD26000090 | B91: 46287 | C91: CUST70515 | D91: Delhi | E91: UPI | F91: 349.0 | G91: Paid | H91: =VALUE(SUBSTITUTE(F91,",","")) -> 349 | I91: =IF(TRIM(D91)="","Unknown",TRIM(D91)) -> Delhi | J91: =COUNTIFS(pg_transaction_cleaned!$O:$O,A91,pg_transaction_cleaned!$F:$F,"CAPTURE") -> 1 | K91: =SUMIFS(pg_transaction_cleaned!$H:$H,pg_transaction_cleaned!$O:$O,A91,pg_transaction_cleaned!$F:$F,"CAPTURE") -> 349 | L91: =COUNTIFS(pg_transaction_cleaned!$O:$O,A91,pg_transaction_cleaned!$F:$F,"REFUND") -> 0 | M91: =SUMIFS(pg_transaction_cleaned!$H:$H,pg_transaction_cleaned!$O:$O,A91,pg_transaction_cleaned!$F:$F,"REFUND") -> 0 | N91: =IF(AND(G91="Paid",J91=0),"Paid, no payment",IF(AND(OR(G91="Failed",G91="Cancelled"),J91>0),"Payment on failed/cancelled",IF(J91>1,"Duplicate charge",IF(AND(J91=1,ROUND(K91-H91,2)<>0),"Amount difference",IF(AND(G91="Refunded",L91=0),"Refunded, no refund",IF(AND(G91<>"Refunded",L91>0),"Refund, order not Refunded",IF(AND(L91>0,ROUND(M91-H91,2)<>0),"Refund amount differs","OK"))))))) -> OK | O91: =IF(N91="OK",0,IF(N91="Paid, no payment",H91,IF(N91="Payment on failed/cancelled",K91,IF(OR(N91="Duplicate charge",N91="Amount difference"),K91-H91,IF(N91="Refunded, no refund",H91,M91))))) -> 0
A92: ORD26000091 | B92: 46267 | C92: CUST54236 | D92: Kolkata | E92: UPI | F92: 1299.0 | G92: Paid | H92: =VALUE(SUBSTITUTE(F92,",","")) -> 1299 | I92: =IF(TRIM(D92)="","Unknown",TRIM(D92)) -> Kolkata | J92: =COUNTIFS(pg_transaction_cleaned!$O:$O,A92,pg_transaction_cleaned!$F:$F,"CAPTURE") -> 1 | K92: =SUMIFS(pg_transaction_cleaned!$H:$H,pg_transaction_cleaned!$O:$O,A92,pg_transaction_cleaned!$F:$F,"CAPTURE") -> 1299 | L92: =COUNTIFS(pg_transaction_cleaned!$O:$O,A92,pg_transaction_cleaned!$F:$F,"REFUND") -> 0 | M92: =SUMIFS(pg_transaction_cleaned!$H:$H,pg_transaction_cleaned!$O:$O,A92,pg_transaction_cleaned!$F:$F,"REFUND") -> 0 | N92: =IF(AND(G92="Paid",J92=0),"Paid, no payment",IF(AND(OR(G92="Failed",G92="Cancelled"),J92>0),"Payment on failed/cancelled",IF(J92>1,"Duplicate charge",IF(AND(J92=1,ROUND(K92-H92,2)<>0),"Amount difference",IF(AND(G92="Refunded",L92=0),"Refunded, no refund",IF(AND(G92<>"Refunded",L92>0),"Refund, order not Refunded",IF(AND(L92>0,ROUND(M92-H92,2)<>0),"Refund amount differs","OK"))))))) -> OK | O92: =IF(N92="OK",0,IF(N92="Paid, no payment",H92,IF(N92="Payment on failed/cancelled",K92,IF(OR(N92="Duplicate charge",N92="Amount difference"),K92-H92,IF(N92="Refunded, no refund",H92,M92))))) -> 0
A93: ORD26000092 | B93: 46274 | C93: CUST80702 | D93: Mumbai | E93: UPI | F93: 8798.0 | G93: Paid | H93: =VALUE(SUBSTITUTE(F93,",","")) -> 8798 | I93: =IF(TRIM(D93)="","Unknown",TRIM(D93)) -> Mumbai | J93: =COUNTIFS(pg_transaction_cleaned!$O:$O,A93,pg_transaction_cleaned!$F:$F,"CAPTURE") -> 1 | K93: =SUMIFS(pg_transaction_cleaned!$H:$H,pg_transaction_cleaned!$O:$O,A93,pg_transaction_cleaned!$F:$F,"CAPTURE") -> 8798 | L93: =COUNTIFS(pg_transaction_cleaned!$O:$O,A93,pg_transaction_cleaned!$F:$F,"REFUND") -> 0 | M93: =SUMIFS(pg_transaction_cleaned!$H:$H,pg_transaction_cleaned!$O:$O,A93,pg_transaction_cleaned!$F:$F,"REFUND") -> 0 | N93: =IF(AND(G93="Paid",J93=0),"Paid, no payment",IF(AND(OR(G93="Failed",G93="Cancelled"),J93>0),"Payment on failed/cancelled",IF(J93>1,"Duplicate charge",IF(AND(J93=1,ROUND(K93-H93,2)<>0),"Amount difference",IF(AND(G93="Refunded",L93=0),"Refunded, no refund",IF(AND(G93<>"Refunded",L93>0),"Refund, order not Refunded",IF(AND(L93>0,ROUND(M93-H93,2)<>0),"Refund amount differs","OK"))))))) -> OK | O93: =IF(N93="OK",0,IF(N93="Paid, no payment",H93,IF(N93="Payment on failed/cancelled",K93,IF(OR(N93="Duplicate charge",N93="Amount difference"),K93-H93,IF(N93="Refunded, no refund",H93,M93))))) -> 0
... A126: ORD26000125 | B126: 46269 | C126: CUST28643 | D126: Pune | E126: UPI | F126: 3598.0 | G126: Paid | H126: =VALUE(SUBSTITUTE(F126,",","")) -> 3598 | I126: =IF(TRIM(D126)="","Unknown",TRIM(D126)) -> Pune | J126: =COUNTIFS(pg_transaction_cleaned!$O:$O,A126,pg_transaction_cleaned!$F:$F,"CAPTURE") -> 1 | K126: =SUMIFS(pg_transaction_cleaned!$H:$H,pg_transaction_cleaned!$O:$O,A126,pg_transaction_cleaned!$F:$F,"CAPTURE") -> 3598 | L126: =COUNTIFS(pg_transaction_cleaned!$O:$O,A126,pg_transaction_cleaned!$F:$F,"REFUND") -> 0 | M126: =SUMIFS(pg_transaction_cleaned!$H:$H,pg_transaction_cleaned!$O:$O,A126,pg_transaction_cleaned!$F:$F,"REFUND") -> 0 | N126: =IF(AND(G126="Paid",J126=0),"Paid, no payment",IF(AND(OR(G126="Failed",G126="Cancelled"),J126>0),"Payment on failed/cancelled",IF(J126>1,"Duplicate charge",IF(AND(J126=1,ROUND(K126-H126,2)<>0),"Amount difference",IF(AND(G126="Refunded",L126=0),"Refunded, no refund",IF(AND(G126<>"Refunded",L126>0),"Refund, order not Refunded",IF(AND(L126>0,ROUND(M126-H126,2)<>0),"Refund amount differs","OK"))))))) -> OK | O126: =IF(N126="OK",0,IF(N126="Paid, no payment",H126,IF(N126="Payment on failed/cancelled",K126,IF(OR(N126="Duplicate charge",N126="Amount difference"),K126-H126,IF(N126="Refunded, no refund",H126,M126))))) -> 0
A127: ORD26000126 | B127: 46267 | C127: CUST84607 | E127: Card | F127: 4999.0 | G127: Paid | H127: =VALUE(SUBSTITUTE(F127,",","")) -> 4999 | I127: =IF(TRIM(D127)="","Unknown",TRIM(D127)) -> Unknown | J127: =COUNTIFS(pg_transaction_cleaned!$O:$O,A127,pg_transaction_cleaned!$F:$F,"CAPTURE") -> 1 | K127: =SUMIFS(pg_transaction_cleaned!$H:$H,pg_transaction_cleaned!$O:$O,A127,pg_transaction_cleaned!$F:$F,"CAPTURE") -> 4999 | L127: =COUNTIFS(pg_transaction_cleaned!$O:$O,A127,pg_transaction_cleaned!$F:$F,"REFUND") -> 0 | M127: =SUMIFS(pg_transaction_cleaned!$H:$H,pg_transaction_cleaned!$O:$O,A127,pg_transaction_cleaned!$F:$F,"REFUND") -> 0 | N127: =IF(AND(G127="Paid",J127=0),"Paid, no payment",IF(AND(OR(G127="Failed",G127="Cancelled"),J127>0),"Payment on failed/cancelled",IF(J127>1,"Duplicate charge",IF(AND(J127=1,ROUND(K127-H127,2)<>0),"Amount difference",IF(AND(G127="Refunded",L127=0),"Refunded, no refund",IF(AND(G127<>"Refunded",L127>0),"Refund, order not Refunded",IF(AND(L127>0,ROUND(M127-H127,2)<>0),"Refund amount differs","OK"))))))) -> OK | O127: =IF(N127="OK",0,IF(N127="Paid, no payment",H127,IF(N127="Payment on failed/cancelled",K127,IF(OR(N127="Duplicate charge",N127="Amount difference"),K127-H127,IF(N127="Refunded, no refund",H127,M127))))) -> 0
A128: ORD26000127 | B128: 46280 | C128: CUST45683 | D128: Jaipur | E128: Card | F128: 1499.0 | G128: Paid | H128: =VALUE(SUBSTITUTE(F128,",","")) -> 1499 | I128: =IF(TRIM(D128)="","Unknown",TRIM(D128)) -> Jaipur | J128: =COUNTIFS(pg_transaction_cleaned!$O:$O,A128,pg_transaction_cleaned!$F:$F,"CAPTURE") -> 1 | K128: =SUMIFS(pg_transaction_cleaned!$H:$H,pg_transaction_cleaned!$O:$O,A128,pg_transaction_cleaned!$F:$F,"CAPTURE") -> 1499 | L128: =COUNTIFS(pg_transaction_cleaned!$O:$O,A128,pg_transaction_cleaned!$F:$F,"REFUND") -> 0 | M128: =SUMIFS(pg_transaction_cleaned!$H:$H,pg_transaction_cleaned!$O:$O,A128,pg_transaction_cleaned!$F:$F,"REFUND") -> 0 | N128: =IF(AND(G128="Paid",J128=0),"Paid, no payment",IF(AND(OR(G128="Failed",G128="Cancelled"),J128>0),"Payment on failed/cancelled",IF(J128>1,"Duplicate charge",IF(AND(J128=1,ROUND(K128-H128,2)<>0),"Amount difference",IF(AND(G128="Refunded",L128=0),"Refunded, no refund",IF(AND(G128<>"Refunded",L128>0),"Refund, order not Refunded",IF(AND(L128>0,ROUND(M128-H128,2)<>0),"Refund amount differs","OK"))))))) -> OK | O128: =IF(N128="OK",0,IF(N128="Paid, no payment",H128,IF(N128="Payment on failed/cancelled",K128,IF(OR(N128="Duplicate charge",N128="Amount difference"),K128-H128,IF(N128="Refunded, no refund",H128,M128))))) -> 0
A129: ORD26000128 | B129: 46283 | C129: CUST52247 | D129: Lucknow | E129: Wallet | F129: 1848.0 | G129: Paid | H129: =VALUE(SUBSTITUTE(F129,",","")) -> 1848 | I129: =IF(TRIM(D129)="","Unknown",TRIM(D129)) -> Lucknow | J129: =COUNTIFS(pg_transaction_cleaned!$O:$O,A129,pg_transaction_cleaned!$F:$F,"CAPTURE") -> 1 | K129: =SUMIFS(pg_transaction_cleaned!$H:$H,pg_transaction_cleaned!$O:$O,A129,pg_transaction_cleaned!$F:$F,"CAPTURE") -> 1848 | L129: =COUNTIFS(pg_transaction_cleaned!$O:$O,A129,pg_transaction_cleaned!$F:$F,"REFUND") -> 0 | M129: =SUMIFS(pg_transaction_cleaned!$H:$H,pg_transaction_cleaned!$O:$O,A129,pg_transaction_cleaned!$F:$F,"REFUND") -> 0 | N129: =IF(AND(G129="Paid",J129=0),"Paid, no payment",IF(AND(OR(G129="Failed",G129="Cancelled"),J129>0),"Payment on failed/cancelled",IF(J129>1,"Duplicate charge",IF(AND(J129=1,ROUND(K129-H129,2)<>0),"Amount difference",IF(AND(G129="Refunded",L129=0),"Refunded, no refund",IF(AND(G129<>"Refunded",L129>0),"Refund, order not Refunded",IF(AND(L129>0,ROUND(M129-H129,2)<>0),"Refund amount differs","OK"))))))) -> OK | O129: =IF(N129="OK",0,IF(N129="Paid, no payment",H129,IF(N129="Payment on failed/cancelled",K129,IF(OR(N129="Duplicate charge",N129="Amount difference"),K129-H129,IF(N129="Refunded, no refund",H129,M129))))) -> 0
A130: ORD26000129 | B130: 46274 | C130: CUST85392 | D130: Lucknow | E130: Card | F130: 349.0 | G130: Paid | H130: =VALUE(SUBSTITUTE(F130,",","")) -> 349 | I130: =IF(TRIM(D130)="","Unknown",TRIM(D130)) -> Lucknow | J130: =COUNTIFS(pg_transaction_cleaned!$O:$O,A130,pg_transaction_cleaned!$F:$F,"CAPTURE") -> 1 | K130: =SUMIFS(pg_transaction_cleaned!$H:$H,pg_transaction_cleaned!$O:$O,A130,pg_transaction_cleaned!$F:$F,"CAPTURE") -> 349 | L130: =COUNTIFS(pg_transaction_cleaned!$O:$O,A130,pg_transaction_cleaned!$F:$F,"REFUND") -> 0 | M130: =SUMIFS(pg_transaction_cleaned!$H:$H,pg_transaction_cleaned!$O:$O,A130,pg_transaction_cleaned!$F:$F,"REFUND") -> 0 | N130: =IF(AND(G130="Paid",J130=0),"Paid, no payment",IF(AND(OR(G130="Failed",G130="Cancelled"),J130>0),"Payment on failed/cancelled",IF(J130>1,"Duplicate charge",IF(AND(J130=1,ROUND(K130-H130,2)<>0),"Amount difference",IF(AND(G130="Refunded",L130=0),"Refunded, no refund",IF(AND(G130<>"Refunded",L130>0),"Refund, order not Refunded",IF(AND(L130>0,ROUND(M130-H130,2)<>0),"Refund amount differs","OK"))))))) -> OK | O130: =IF(N130="OK",0,IF(N130="Paid, no payment",H130,IF(N130="Payment on failed/cancelled",K130,IF(OR(N130="Duplicate charge",N130="Amount difference"),K130-H130,IF(N130="Refunded, no refund",H130,M130))))) -> 0
A131: ORD26000130 | B131: 46266 | C131: CUST71669 | D131: Jaipur | E131: Card | F131: 11297.0 | G131: Paid | H131: =VALUE(SUBSTITUTE(F131,",","")) -> 11297 | I131: =IF(TRIM(D131)="","Unknown",TRIM(D131)) -> Jaipur | J131: =COUNTIFS(pg_transaction_cleaned!$O:$O,A131,pg_transaction_cleaned!$F:$F,"CAPTURE") -> 1 | K131: =SUMIFS(pg_transaction_cleaned!$H:$H,pg_transaction_cleaned!$O:$O,A131,pg_transaction_cleaned!$F:$F,"CAPTURE") -> 11297 | L131: =COUNTIFS(pg_transaction_cleaned!$O:$O,A131,pg_transaction_cleaned!$F:$F,"REFUND") -> 0 | M131: =SUMIFS(pg_transaction_cleaned!$H:$H,pg_transaction_cleaned!$O:$O,A131,pg_transaction_cleaned!$F:$F,"REFUND") -> 0 | N131: =IF(AND(G131="Paid",J131=0),"Paid, no payment",IF(AND(OR(G131="Failed",G131="Cancelled"),J131>0),"Payment on failed/cancelled",IF(J131>1,"Duplicate charge",IF(AND(J131=1,ROUND(K131-H131,2)<>0),"Amount difference",IF(AND(G131="Refunded",L131=0),"Refunded, no refund",IF(AND(G131<>"Refunded",L131>0),"Refund, order not Refunded",IF(AND(L131>0,ROUND(M131-H131,2)<>0),"Refund amount differs","OK"))))))) -> OK | O131: =IF(N131="OK",0,IF(N131="Paid, no payment",H131,IF(N131="Payment on failed/cancelled",K131,IF(OR(N131="Duplicate charge",N131="Amount difference"),K131-H131,IF(N131="Refunded, no refund",H131,M131))))) -> 0
A132: ORD26000131 | B132: 46286 | C132: CUST74451 | D132: Pune | E132: UPI | F132: 1298.0 | G132: Refunded | H132: =VALUE(SUBSTITUTE(F132,",","")) -> 1298 | I132: =IF(TRIM(D132)="","Unknown",TRIM(D132)) -> Pune | J132: =COUNTIFS(pg_transaction_cleaned!$O:$O,A132,pg_transaction_cleaned!$F:$F,"CAPTURE") -> 1 | K132: =SUMIFS(pg_transaction_cleaned!$H:$H,pg_transaction_cleaned!$O:$O,A132,pg_transaction_cleaned!$F:$F,"CAPTURE") -> 1298 | L132: =COUNTIFS(pg_transaction_cleaned!$O:$O,A132,pg_transaction_cleaned!$F:$F,"REFUND") -> 1 | M132: =SUMIFS(pg_transaction_cleaned!$H:$H,pg_transaction_cleaned!$O:$O,A132,pg_transaction_cleaned!$F:$F,"REFUND") -> 1298 | N132: =IF(AND(G132="Paid",J132=0),"Paid, no payment",IF(AND(OR(G132="Failed",G132="Cancelled"),J132>0),"Payment on failed/cancelled",IF(J132>1,"Duplicate charge",IF(AND(J132=1,ROUND(K132-H132,2)<>0),"Amount difference",IF(AND(G132="Refunded",L132=0),"Refunded, no refund",IF(AND(G132<>"Refunded",L132>0),"Refund, order not Refunded",IF(AND(L132>0,ROUND(M132-H132,2)<>0),"Refund amount differs","OK"))))))) -> OK | O132: =IF(N132="OK",0,IF(N132="Paid, no payment",H132,IF(N132="Payment on failed/cancelled",K132,IF(OR(N132="Duplicate charge",N132="Amount difference"),K132-H132,IF(N132="Refunded, no refund",H132,M132))))) -> 0
A133: ORD26000132 | B133: 46281 | C133: CUST31079 | D133: Chennai | E133: Card | F133: 1299.0 | G133: Paid | H133: =VALUE(SUBSTITUTE(F133,",","")) -> 1299 | I133: =IF(TRIM(D133)="","Unknown",TRIM(D133)) -> Chennai | J133: =COUNTIFS(pg_transaction_cleaned!$O:$O,A133,pg_transaction_cleaned!$F:$F,"CAPTURE") -> 1 | K133: =SUMIFS(pg_transaction_cleaned!$H:$H,pg_transaction_cleaned!$O:$O,A133,pg_transaction_cleaned!$F:$F,"CAPTURE") -> 1299 | L133: =COUNTIFS(pg_transaction_cleaned!$O:$O,A133,pg_transaction_cleaned!$F:$F,"REFUND") -> 0 | M133: =SUMIFS(pg_transaction_cleaned!$H:$H,pg_transaction_cleaned!$O:$O,A133,pg_transaction_cleaned!$F:$F,"REFUND") -> 0 | N133: =IF(AND(G133="Paid",J133=0),"Paid, no payment",IF(AND(OR(G133="Failed",G133="Cancelled"),J133>0),"Payment on failed/cancelled",IF(J133>1,"Duplicate charge",IF(AND(J133=1,ROUND(K133-H133,2)<>0),"Amount difference",IF(AND(G133="Refunded",L133=0),"Refunded, no refund",IF(AND(G133<>"Refunded",L133>0),"Refund, order not Refunded",IF(AND(L133>0,ROUND(M133-H133,2)<>0),"Refund amount differs","OK"))))))) -> OK | O133: =IF(N133="OK",0,IF(N133="Paid, no payment",H133,IF(N133="Payment on failed/cancelled",K133,IF(OR(N133="Duplicate charge",N133="Amount difference"),K133-H133,IF(N133="Refunded, no refund",H133,M133))))) -> 0
A134: ORD26000133 | B134: 46279 | C134: CUST82102 | D134: Mumbai | E134: NetBanking | F134: 5297.0 | G134: Cancelled | H134: =VALUE(SUBSTITUTE(F134,",","")) -> 5297 | I134: =IF(TRIM(D134)="","Unknown",TRIM(D134)) -> Mumbai | J134: =COUNTIFS(pg_transaction_cleaned!$O:$O,A134,pg_transaction_cleaned!$F:$F,"CAPTURE") -> 0 | K134: =SUMIFS(pg_transaction_cleaned!$H:$H,pg_transaction_cleaned!$O:$O,A134,pg_transaction_cleaned!$F:$F,"CAPTURE") -> 0 | L134: =COUNTIFS(pg_transaction_cleaned!$O:$O,A134,pg_transaction_cleaned!$F:$F,"REFUND") -> 0 | M134: =SUMIFS(pg_transaction_cleaned!$H:$H,pg_transaction_cleaned!$O:$O,A134,pg_transaction_cleaned!$F:$F,"REFUND") -> 0 | N134: =IF(AND(G134="Paid",J134=0),"Paid, no payment",IF(AND(OR(G134="Failed",G134="Cancelled"),J134>0),"Payment on failed/cancelled",IF(J134>1,"Duplicate charge",IF(AND(J134=1,ROUND(K134-H134,2)<>0),"Amount difference",IF(AND(G134="Refunded",L134=0),"Refunded, no refund",IF(AND(G134<>"Refunded",L134>0),"Refund, order not Refunded",IF(AND(L134>0,ROUND(M134-H134,2)<>0),"Refund amount differs","OK"))))))) -> OK | O134: =IF(N134="OK",0,IF(N134="Paid, no payment",H134,IF(N134="Payment on failed/cancelled",K134,IF(OR(N134="Duplicate charge",N134="Amount difference"),K134-H134,IF(N134="Refunded, no refund",H134,M134))))) -> 0
A135: ORD26000134 | B135: 46280 | C135: CUST62976 | D135: Jaipur | E135: UPI | F135: 999.0 | G135: Paid | H135: =VALUE(SUBSTITUTE(F135,",","")) -> 999 | I135: =IF(TRIM(D135)="","Unknown",TRIM(D135)) -> Jaipur | J135: =COUNTIFS(pg_transaction_cleaned!$O:$O,A135,pg_transaction_cleaned!$F:$F,"CAPTURE") -> 1 | K135: =SUMIFS(pg_transaction_cleaned!$H:$H,pg_transaction_cleaned!$O:$O,A135,pg_transaction_cleaned!$F:$F,"CAPTURE") -> 999 | L135: =COUNTIFS(pg_transaction_cleaned!$O:$O,A135,pg_transaction_cleaned!$F:$F,"REFUND") -> 0 | M135: =SUMIFS(pg_transaction_cleaned!$H:$H,pg_transaction_cleaned!$O:$O,A135,pg_transaction_cleaned!$F:$F,"REFUND") -> 0 | N135: =IF(AND(G135="Paid",J135=0),"Paid, no payment",IF(AND(OR(G135="Failed",G135="Cancelled"),J135>0),"Payment on failed/cancelled",IF(J135>1,"Duplicate charge",IF(AND(J135=1,ROUND(K135-H135,2)<>0),"Amount difference",IF(AND(G135="Refunded",L135=0),"Refunded, no refund",IF(AND(G135<>"Refunded",L135>0),"Refund, order not Refunded",IF(AND(L135>0,ROUND(M135-H135,2)<>0),"Refund amount differs","OK"))))))) -> OK | O135: =IF(N135="OK",0,IF(N135="Paid, no payment",H135,IF(N135="Payment on failed/cancelled",K135,IF(OR(N135="Duplicate charge",N135="Amount difference"),K135-H135,IF(N135="Refunded, no refund",H135,M135))))) -> 0
A136: ORD26000135 | B136: 46292 | C136: CUST17104 | D136: Bengaluru | E136: UPI | F136: 2999.0 | G136: Paid | H136: =VALUE(SUBSTITUTE(F136,",","")) -> 2999 | I136: =IF(TRIM(D136)="","Unknown",TRIM(D136)) -> Bengaluru | J136: =COUNTIFS(pg_transaction_cleaned!$O:$O,A136,pg_transaction_cleaned!$F:$F,"CAPTURE") -> 1 | K136: =SUMIFS(pg_transaction_cleaned!$H:$H,pg_transaction_cleaned!$O:$O,A136,pg_transaction_cleaned!$F:$F,"CAPTURE") -> 2999 | L136: =COUNTIFS(pg_transaction_cleaned!$O:$O,A136,pg_transaction_cleaned!$F:$F,"REFUND") -> 0 | M136: =SUMIFS(pg_transaction_cleaned!$H:$H,pg_transaction_cleaned!$O:$O,A136,pg_transaction_cleaned!$F:$F,"REFUND") -> 0 | N136: =IF(AND(G136="Paid",J136=0),"Paid, no payment",IF(AND(OR(G136="Failed",G136="Cancelled"),J136>0),"Payment on failed/cancelled",IF(J136>1,"Duplicate charge",IF(AND(J136=1,ROUND(K136-H136,2)<>0),"Amount difference",IF(AND(G136="Refunded",L136=0),"Refunded, no refund",IF(AND(G136<>"Refunded",L136>0),"Refund, order not Refunded",IF(AND(L136>0,ROUND(M136-H136,2)<>0),"Refund amount differs","OK"))))))) -> OK | O136: =IF(N136="OK",0,IF(N136="Paid, no payment",H136,IF(N136="Payment on failed/cancelled",K136,IF(OR(N136="Duplicate charge",N136="Amount difference"),K136-H136,IF(N136="Refunded, no refund",H136,M136))))) -> 0
A137: ORD26000136 | B137: 46282 | C137: CUST16764 | D137: Bengaluru | E137: Card | F137: 2499.0 | G137: Paid | H137: =VALUE(SUBSTITUTE(F137,",","")) -> 2499 | I137: =IF(TRIM(D137)="","Unknown",TRIM(D137)) -> Bengaluru | J137: =COUNTIFS(pg_transaction_cleaned!$O:$O,A137,pg_transaction_cleaned!$F:$F,"CAPTURE") -> 1 | K137: =SUMIFS(pg_transaction_cleaned!$H:$H,pg_transaction_cleaned!$O:$O,A137,pg_transaction_cleaned!$F:$F,"CAPTURE") -> 2499 | L137: =COUNTIFS(pg_transaction_cleaned!$O:$O,A137,pg_transaction_cleaned!$F:$F,"REFUND") -> 0 | M137: =SUMIFS(pg_transaction_cleaned!$H:$H,pg_transaction_cleaned!$O:$O,A137,pg_transaction_cleaned!$F:$F,"REFUND") -> 0 | N137: =IF(AND(G137="Paid",J137=0),"Paid, no payment",IF(AND(OR(G137="Failed",G137="Cancelled"),J137>0),"Payment on failed/cancelled",IF(J137>1,"Duplicate charge",IF(AND(J137=1,ROUND(K137-H137,2)<>0),"Amount difference",IF(AND(G137="Refunded",L137=0),"Refunded, no refund",IF(AND(G137<>"Refunded",L137>0),"Refund, order not Refunded",IF(AND(L137>0,ROUND(M137-H137,2)<>0),"Refund amount differs","OK"))))))) -> OK | O137: =IF(N137="OK",0,IF(N137="Paid, no payment",H137,IF(N137="Payment on failed/cancelled",K137,IF(OR(N137="Duplicate charge",N137="Amount difference"),K137-H137,IF(N137="Refunded, no refund",H137,M137))))) -> 0
A138: ORD26000137 | B138: 46274 | C138: CUST25915 | E138: Card | F138: 1298.0 | G138: Paid | H138: =VALUE(SUBSTITUTE(F138,",","")) -> 1298 | I138: =IF(TRIM(D138)="","Unknown",TRIM(D138)) -> Unknown | J138: =COUNTIFS(pg_transaction_cleaned!$O:$O,A138,pg_transaction_cleaned!$F:$F,"CAPTURE") -> 1 | K138: =SUMIFS(pg_transaction_cleaned!$H:$H,pg_transaction_cleaned!$O:$O,A138,pg_transaction_cleaned!$F:$F,"CAPTURE") -> 1298 | L138: =COUNTIFS(pg_transaction_cleaned!$O:$O,A138,pg_transaction_cleaned!$F:$F,"REFUND") -> 0 | M138: =SUMIFS(pg_transaction_cleaned!$H:$H,pg_transaction_cleaned!$O:$O,A138,pg_transaction_cleaned!$F:$F,"REFUND") -> 0 | N138: =IF(AND(G138="Paid",J138=0),"Paid, no payment",IF(AND(OR(G138="Failed",G138="Cancelled"),J138>0),"Payment on failed/cancelled",IF(J138>1,"Duplicate charge",IF(AND(J138=1,ROUND(K138-H138,2)<>0),"Amount difference",IF(AND(G138="Refunded",L138=0),"Refunded, no refund",IF(AND(G138<>"Refunded",L138>0),"Refund, order not Refunded",IF(AND(L138>0,ROUND(M138-H138,2)<>0),"Refund amount differs","OK"))))))) -> OK | O138: =IF(N138="OK",0,IF(N138="Paid, no payment",H138,IF(N138="Payment on failed/cancelled",K138,IF(OR(N138="Duplicate charge",N138="Amount difference"),K138-H138,IF(N138="Refunded, no refund",H138,M138))))) -> 0
A139: ORD26000138 | B139: 46286 | C139: CUST11792 | D139: Jaipur | E139: UPI | F139: 5598.0 | G139: Paid | H139: =VALUE(SUBSTITUTE(F139,",","")) -> 5598 | I139: =IF(TRIM(D139)="","Unknown",TRIM(D139)) -> Jaipur | J139: =COUNTIFS(pg_transaction_cleaned!$O:$O,A139,pg_transaction_cleaned!$F:$F,"CAPTURE") -> 1 | K139: =SUMIFS(pg_transaction_cleaned!$H:$H,pg_transaction_cleaned!$O:$O,A139,pg_transaction_cleaned!$F:$F,"CAPTURE") -> 5598 | L139: =COUNTIFS(pg_transaction_cleaned!$O:$O,A139,pg_transaction_cleaned!$F:$F,"REFUND") -> 0 | M139: =SUMIFS(pg_transaction_cleaned!$H:$H,pg_transaction_cleaned!$O:$O,A139,pg_transaction_cleaned!$F:$F,"REFUND") -> 0 | N139: =IF(AND(G139="Paid",J139=0),"Paid, no payment",IF(AND(OR(G139="Failed",G139="Cancelled"),J139>0),"Payment on failed/cancelled",IF(J139>1,"Duplicate charge",IF(AND(J139=1,ROUND(K139-H139,2)<>0),"Amount difference",IF(AND(G139="Refunded",L139=0),"Refunded, no refund",IF(AND(G139<>"Refunded",L139>0),"Refund, order not Refunded",IF(AND(L139>0,ROUND(M139-H139,2)<>0),"Refund amount differs","OK"))))))) -> OK | O139: =IF(N139="OK",0,IF(N139="Paid, no payment",H139,IF(N139="Payment on failed/cancelled",K139,IF(OR(N139="Duplicate charge",N139="Amount difference"),K139-H139,IF(N139="Refunded, no refund",H139,M139))))) -> 0
A140: ORD26000139 | B140: 46279 | C140: CUST70482 | D140: Pune | E140: Wallet | F140: 599.0 | G140: Refunded | H140: =VALUE(SUBSTITUTE(F140,",","")) -> 599 | I140: =IF(TRIM(D140)="","Unknown",TRIM(D140)) -> Pune | J140: =COUNTIFS(pg_transaction_cleaned!$O:$O,A140,pg_transaction_cleaned!$F:$F,"CAPTURE") -> 1 | K140: =SUMIFS(pg_transaction_cleaned!$H:$H,pg_transaction_cleaned!$O:$O,A140,pg_transaction_cleaned!$F:$F,"CAPTURE") -> 599 | L140: =COUNTIFS(pg_transaction_cleaned!$O:$O,A140,pg_transaction_cleaned!$F:$F,"REFUND") -> 1 | M140: =SUMIFS(pg_transaction_cleaned!$H:$H,pg_transaction_cleaned!$O:$O,A140,pg_transaction_cleaned!$F:$F,"REFUND") -> 599 | N140: =IF(AND(G140="Paid",J140=0),"Paid, no payment",IF(AND(OR(G140="Failed",G140="Cancelled"),J140>0),"Payment on failed/cancelled",IF(J140>1,"Duplicate charge",IF(AND(J140=1,ROUND(K140-H140,2)<>0),"Amount difference",IF(AND(G140="Refunded",L140=0),"Refunded, no refund",IF(AND(G140<>"Refunded",L140>0),"Refund, order not Refunded",IF(AND(L140>0,ROUND(M140-H140,2)<>0),"Refund amount differs","OK"))))))) -> OK | O140: =IF(N140="OK",0,IF(N140="Paid, no payment",H140,IF(N140="Payment on failed/cancelled",K140,IF(OR(N140="Duplicate charge",N140="Amount difference"),K140-H140,IF(N140="Refunded, no refund",H140,M140))))) -> 0
A141: ORD26000140 | B141: 46286 | C141: CUST45838 | D141: Kolkata | E141: UPI | F141: 1499.0 | G141: Cancelled | H141: =VALUE(SUBSTITUTE(F141,",","")) -> 1499 | I141: =IF(TRIM(D141)="","Unknown",TRIM(D141)) -> Kolkata | J141: =COUNTIFS(pg_transaction_cleaned!$O:$O,A141,pg_transaction_cleaned!$F:$F,"CAPTURE") -> 0 | K141: =SUMIFS(pg_transaction_cleaned!$H:$H,pg_transaction_cleaned!$O:$O,A141,pg_transaction_cleaned!$F:$F,"CAPTURE") -> 0 | L141: =COUNTIFS(pg_transaction_cleaned!$O:$O,A141,pg_transaction_cleaned!$F:$F,"REFUND") -> 0 | M141: =SUMIFS(pg_transaction_cleaned!$H:$H,pg_transaction_cleaned!$O:$O,A141,pg_transaction_cleaned!$F:$F,"REFUND") -> 0 | N141: =IF(AND(G141="Paid",J141=0),"Paid, no payment",IF(AND(OR(G141="Failed",G141="Cancelled"),J141>0),"Payment on failed/cancelled",IF(J141>1,"Duplicate charge",IF(AND(J141=1,ROUND(K141-H141,2)<>0),"Amount difference",IF(AND(G141="Refunded",L141=0),"Refunded, no refund",IF(AND(G141<>"Refunded",L141>0),"Refund, order not Refunded",IF(AND(L141>0,ROUND(M141-H141,2)<>0),"Refund amount differs","OK"))))))) -> OK | O141: =IF(N141="OK",0,IF(N141="Paid, no payment",H141,IF(N141="Payment on failed/cancelled",K141,IF(OR(N141="Duplicate charge",N141="Amount difference"),K141-H141,IF(N141="Refunded, no refund",H141,M141))))) -> 0
A142: ORD26000141 | B142: 46292 | C142: CUST34983 | D142: Lucknow | E142: UPI | F142: 2098.0 | G142: Paid | H142: =VALUE(SUBSTITUTE(F142,",","")) -> 2098 | I142: =IF(TRIM(D142)="","Unknown",TRIM(D142)) -> Lucknow | J142: =COUNTIFS(pg_transaction_cleaned!$O:$O,A142,pg_transaction_cleaned!$F:$F,"CAPTURE") -> 1 | K142: =SUMIFS(pg_transaction_cleaned!$H:$H,pg_transaction_cleaned!$O:$O,A142,pg_transaction_cleaned!$F:$F,"CAPTURE") -> 2098 | L142: =COUNTIFS(pg_transaction_cleaned!$O:$O,A142,pg_transaction_cleaned!$F:$F,"REFUND") -> 0 | M142: =SUMIFS(pg_transaction_cleaned!$H:$H,pg_transaction_cleaned!$O:$O,A142,pg_transaction_cleaned!$F:$F,"REFUND") -> 0 | N142: =IF(AND(G142="Paid",J142=0),"Paid, no payment",IF(AND(OR(G142="Failed",G142="Cancelled"),J142>0),"Payment on failed/cancelled",IF(J142>1,"Duplicate charge",IF(AND(J142=1,ROUND(K142-H142,2)<>0),"Amount difference",IF(AND(G142="Refunded",L142=0),"Refunded, no refund",IF(AND(G142<>"Refunded",L142>0),"Refund, order not Refunded",IF(AND(L142>0,ROUND(M142-H142,2)<>0),"Refund amount differs","OK"))))))) -> OK | O142: =IF(N142="OK",0,IF(N142="Paid, no payment",H142,IF(N142="Payment on failed/cancelled",K142,IF(OR(N142="Duplicate charge",N142="Amount difference"),K142-H142,IF(N142="Refunded, no refund",H142,M142))))) -> 0
A143: ORD26000142 | B143: 46282 | C143: CUST64387 | D143: Chennai | E143: Card | F143: 8847.0 | G143: Paid | H143: =VALUE(SUBSTITUTE(F143,",","")) -> 8847 | I143: =IF(TRIM(D143)="","Unknown",TRIM(D143)) -> Chennai | J143: =COUNTIFS(pg_transaction_cleaned!$O:$O,A143,pg_transaction_cleaned!$F:$F,"CAPTURE") -> 1 | K143: =SUMIFS(pg_transaction_cleaned!$H:$H,pg_transaction_cleaned!$O:$O,A143,pg_transaction_cleaned!$F:$F,"CAPTURE") -> 8847 | L143: =COUNTIFS(pg_transaction_cleaned!$O:$O,A143,pg_transaction_cleaned!$F:$F,"REFUND") -> 0 | M143: =SUMIFS(pg_transaction_cleaned!$H:$H,pg_transaction_cleaned!$O:$O,A143,pg_transaction_cleaned!$F:$F,"REFUND") -> 0 | N143: =IF(AND(G143="Paid",J143=0),"Paid, no payment",IF(AND(OR(G143="Failed",G143="Cancelled"),J143>0),"Payment on failed/cancelled",IF(J143>1,"Duplicate charge",IF(AND(J143=1,ROUND(K143-H143,2)<>0),"Amount difference",IF(AND(G143="Refunded",L143=0),"Refunded, no refund",IF(AND(G143<>"Refunded",L143>0),"Refund, order not Refunded",IF(AND(L143>0,ROUND(M143-H143,2)<>0),"Refund amount differs","OK"))))))) -> OK | O143: =IF(N143="OK",0,IF(N143="Paid, no payment",H143,IF(N143="Payment on failed/cancelled",K143,IF(OR(N143="Duplicate charge",N143="Amount difference"),K143-H143,IF(N143="Refunded, no refund",H143,M143))))) -> 0
A144: ORD26000143 | B144: 46295 | C144: CUST86931 | D144: Lucknow | E144: Card | F144: 8798.0 | G144: Paid | H144: =VALUE(SUBSTITUTE(F144,",","")) -> 8798 | I144: =IF(TRIM(D144)="","Unknown",TRIM(D144)) -> Lucknow | J144: =COUNTIFS(pg_transaction_cleaned!$O:$O,A144,pg_transaction_cleaned!$F:$F,"CAPTURE") -> 1 | K144: =SUMIFS(pg_transaction_cleaned!$H:$H,pg_transaction_cleaned!$O:$O,A144,pg_transaction_cleaned!$F:$F,"CAPTURE") -> 8798 | L144: =COUNTIFS(pg_transaction_cleaned!$O:$O,A144,pg_transaction_cleaned!$F:$F,"REFUND") -> 0 | M144: =SUMIFS(pg_transaction_cleaned!$H:$H,pg_transaction_cleaned!$O:$O,A144,pg_transaction_cleaned!$F:$F,"REFUND") -> 0 | N144: =IF(AND(G144="Paid",J144=0),"Paid, no payment",IF(AND(OR(G144="Failed",G144="Cancelled"),J144>0),"Payment on failed/cancelled",IF(J144>1,"Duplicate charge",IF(AND(J144=1,ROUND(K144-H144,2)<>0),"Amount difference",IF(AND(G144="Refunded",L144=0),"Refunded, no refund",IF(AND(G144<>"Refunded",L144>0),"Refund, order not Refunded",IF(AND(L144>0,ROUND(M144-H144,2)<>0),"Refund amount differs","OK"))))))) -> OK | O144: =IF(N144="OK",0,IF(N144="Paid, no payment",H144,IF(N144="Payment on failed/cancelled",K144,IF(OR(N144="Duplicate charge",N144="Amount difference"),K144-H144,IF(N144="Refunded, no refund",H144,M144))))) -> 0
A145: ORD26000144 | B145: 46287 | C145: CUST53573 | D145: Jaipur | E145: UPI | F145: 8498.0 | G145: Paid | H145: =VALUE(SUBSTITUTE(F145,",","")) -> 8498 | I145: =IF(TRIM(D145)="","Unknown",TRIM(D145)) -> Jaipur | J145: =COUNTIFS(pg_transaction_cleaned!$O:$O,A145,pg_transaction_cleaned!$F:$F,"CAPTURE") -> 1 | K145: =SUMIFS(pg_transaction_cleaned!$H:$H,pg_transaction_cleaned!$O:$O,A145,pg_transaction_cleaned!$F:$F,"CAPTURE") -> 8498 | L145: =COUNTIFS(pg_transaction_cleaned!$O:$O,A145,pg_transaction_cleaned!$F:$F,"REFUND") -> 0 | M145: =SUMIFS(pg_transaction_cleaned!$H:$H,pg_transaction_cleaned!$O:$O,A145,pg_transaction_cleaned!$F:$F,"REFUND") -> 0 | N145: =IF(AND(G145="Paid",J145=0),"Paid, no payment",IF(AND(OR(G145="Failed",G145="Cancelled"),J145>0),"Payment on failed/cancelled",IF(J145>1,"Duplicate charge",IF(AND(J145=1,ROUND(K145-H145,2)<>0),"Amount difference",IF(AND(G145="Refunded",L145=0),"Refunded, no refund",IF(AND(G145<>"Refunded",L145>0),"Refund, order not Refunded",IF(AND(L145>0,ROUND(M145-H145,2)<>0),"Refund amount differs","OK"))))))) -> OK | O145: =IF(N145="OK",0,IF(N145="Paid, no payment",H145,IF(N145="Payment on failed/cancelled",K145,IF(OR(N145="Duplicate charge",N145="Amount difference"),K145-H145,IF(N145="Refunded, no refund",H145,M145))))) -> 0
A146: ORD26000145 | B146: 46290 | C146: CUST41300 | D146: Lucknow | E146: NetBanking | F146: 2798.0 | G146: Cancelled | H146: =VALUE(SUBSTITUTE(F146,",","")) -> 2798 | I146: =IF(TRIM(D146)="","Unknown",TRIM(D146)) -> Lucknow | J146: =COUNTIFS(pg_transaction_cleaned!$O:$O,A146,pg_transaction_cleaned!$F:$F,"CAPTURE") -> 0 | K146: =SUMIFS(pg_transaction_cleaned!$H:$H,pg_transaction_cleaned!$O:$O,A146,pg_transaction_cleaned!$F:$F,"CAPTURE") -> 0 | L146: =COUNTIFS(pg_transaction_cleaned!$O:$O,A146,pg_transaction_cleaned!$F:$F,"REFUND") -> 0 | M146: =SUMIFS(pg_transaction_cleaned!$H:$H,pg_transaction_cleaned!$O:$O,A146,pg_transaction_cleaned!$F:$F,"REFUND") -> 0 | N146: =IF(AND(G146="Paid",J146=0),"Paid, no payment",IF(AND(OR(G146="Failed",G146="Cancelled"),J146>0),"Payment on failed/cancelled",IF(J146>1,"Duplicate charge",IF(AND(J146=1,ROUND(K146-H146,2)<>0),"Amount difference",IF(AND(G146="Refunded",L146=0),"Refunded, no refund",IF(AND(G146<>"Refunded",L146>0),"Refund, order not Refunded",IF(AND(L146>0,ROUND(M146-H146,2)<>0),"Refund amount differs","OK"))))))) -> OK | O146: =IF(N146="OK",0,IF(N146="Paid, no payment",H146,IF(N146="Payment on failed/cancelled",K146,IF(OR(N146="Duplicate charge",N146="Amount difference"),K146-H146,IF(N146="Refunded, no refund",H146,M146))))) -> 0
A147: ORD26000146 | B147: 46278 | C147: CUST71993 | D147: Kolkata | E147: UPI | F147: 7999.0 | G147: Paid | H147: =VALUE(SUBSTITUTE(F147,",","")) -> 7999 | I147: =IF(TRIM(D147)="","Unknown",TRIM(D147)) -> Kolkata | J147: =COUNTIFS(pg_transaction_cleaned!$O:$O,A147,pg_transaction_cleaned!$F:$F,"CAPTURE") -> 1 | K147: =SUMIFS(pg_transaction_cleaned!$H:$H,pg_transaction_cleaned!$O:$O,A147,pg_transaction_cleaned!$F:$F,"CAPTURE") -> 7999 | L147: =COUNTIFS(pg_transaction_cleaned!$O:$O,A147,pg_transaction_cleaned!$F:$F,"REFUND") -> 0 | M147: =SUMIFS(pg_transaction_cleaned!$H:$H,pg_transaction_cleaned!$O:$O,A147,pg_transaction_cleaned!$F:$F,"REFUND") -> 0 | N147: =IF(AND(G147="Paid",J147=0),"Paid, no payment",IF(AND(OR(G147="Failed",G147="Cancelled"),J147>0),"Payment on failed/cancelled",IF(J147>1,"Duplicate charge",IF(AND(J147=1,ROUND(K147-H147,2)<>0),"Amount difference",IF(AND(G147="Refunded",L147=0),"Refunded, no refund",IF(AND(G147<>"Refunded",L147>0),"Refund, order not Refunded",IF(AND(L147>0,ROUND(M147-H147,2)<>0),"Refund amount differs","OK"))))))) -> OK | O147: =IF(N147="OK",0,IF(N147="Paid, no payment",H147,IF(N147="Payment on failed/cancelled",K147,IF(OR(N147="Duplicate charge",N147="Amount difference"),K147-H147,IF(N147="Refunded, no refund",H147,M147))))) -> 0
A148: ORD26000147 | B148: 46278 | C148: CUST14852 | D148: Delhi | E148: UPI | F148: 15997.0 | G148: Refunded | H148: =VALUE(SUBSTITUTE(F148,",","")) -> 15997 | I148: =IF(TRIM(D148)="","Unknown",TRIM(D148)) -> Delhi | J148: =COUNTIFS(pg_transaction_cleaned!$O:$O,A148,pg_transaction_cleaned!$F:$F,"CAPTURE") -> 1 | K148: =SUMIFS(pg_transaction_cleaned!$H:$H,pg_transaction_cleaned!$O:$O,A148,pg_transaction_cleaned!$F:$F,"CAPTURE") -> 15997 | L148: =COUNTIFS(pg_transaction_cleaned!$O:$O,A148,pg_transaction_cleaned!$F:$F,"REFUND") -> 1 | M148: =SUMIFS(pg_transaction_cleaned!$H:$H,pg_transaction_cleaned!$O:$O,A148,pg_transaction_cleaned!$F:$F,"REFUND") -> 15997 | N148: =IF(AND(G148="Paid",J148=0),"Paid, no payment",IF(AND(OR(G148="Failed",G148="Cancelled"),J148>0),"Payment on failed/cancelled",IF(J148>1,"Duplicate charge",IF(AND(J148=1,ROUND(K148-H148,2)<>0),"Amount difference",IF(AND(G148="Refunded",L148=0),"Refunded, no refund",IF(AND(G148<>"Refunded",L148>0),"Refund, order not Refunded",IF(AND(L148>0,ROUND(M148-H148,2)<>0),"Refund amount differs","OK"))))))) -> OK | O148: =IF(N148="OK",0,IF(N148="Paid, no payment",H148,IF(N148="Payment on failed/cancelled",K148,IF(OR(N148="Duplicate charge",N148="Amount difference"),K148-H148,IF(N148="Refunded, no refund",H148,M148))))) -> 0
A149: ORD26000148 | B149: 46282 | C149: CUST23069 | E149: NetBanking | F149: 8998.0 | G149: Paid | H149: =VALUE(SUBSTITUTE(F149,",","")) -> 8998 | I149: =IF(TRIM(D149)="","Unknown",TRIM(D149)) -> Unknown | J149: =COUNTIFS(pg_transaction_cleaned!$O:$O,A149,pg_transaction_cleaned!$F:$F,"CAPTURE") -> 1 | K149: =SUMIFS(pg_transaction_cleaned!$H:$H,pg_transaction_cleaned!$O:$O,A149,pg_transaction_cleaned!$F:$F,"CAPTURE") -> 8998 | L149: =COUNTIFS(pg_transaction_cleaned!$O:$O,A149,pg_transaction_cleaned!$F:$F,"REFUND") -> 0 | M149: =SUMIFS(pg_transaction_cleaned!$H:$H,pg_transaction_cleaned!$O:$O,A149,pg_transaction_cleaned!$F:$F,"REFUND") -> 0 | N149: =IF(AND(G149="Paid",J149=0),"Paid, no payment",IF(AND(OR(G149="Failed",G149="Cancelled"),J149>0),"Payment on failed/cancelled",IF(J149>1,"Duplicate charge",IF(AND(J149=1,ROUND(K149-H149,2)<>0),"Amount difference",IF(AND(G149="Refunded",L149=0),"Refunded, no refund",IF(AND(G149<>"Refunded",L149>0),"Refund, order not Refunded",IF(AND(L149>0,ROUND(M149-H149,2)<>0),"Refund amount differs","OK"))))))) -> OK | O149: =IF(N149="OK",0,IF(N149="Paid, no payment",H149,IF(N149="Payment on failed/cancelled",K149,IF(OR(N149="Duplicate charge",N149="Amount difference"),K149-H149,IF(N149="Refunded, no refund",H149,M149))))) -> 0
A150: ORD26000149 | B150: 46295 | C150: CUST30232 | D150: Pune | E150: NetBanking | F150: 3798.0 | G150: Paid | H150: =VALUE(SUBSTITUTE(F150,",","")) -> 3798 | I150: =IF(TRIM(D150)="","Unknown",TRIM(D150)) -> Pune | J150: =COUNTIFS(pg_transaction_cleaned!$O:$O,A150,pg_transaction_cleaned!$F:$F,"CAPTURE") -> 1 | K150: =SUMIFS(pg_transaction_cleaned!$H:$H,pg_transaction_cleaned!$O:$O,A150,pg_transaction_cleaned!$F:$F,"CAPTURE") -> 3798 | L150: =COUNTIFS(pg_transaction_cleaned!$O:$O,A150,pg_transaction_cleaned!$F:$F,"REFUND") -> 0 | M150: =SUMIFS(pg_transaction_cleaned!$H:$H,pg_transaction_cleaned!$O:$O,A150,pg_transaction_cleaned!$F:$F,"REFUND") -> 0 | N150: =IF(AND(G150="Paid",J150=0),"Paid, no payment",IF(AND(OR(G150="Failed",G150="Cancelled"),J150>0),"Payment on failed/cancelled",IF(J150>1,"Duplicate charge",IF(AND(J150=1,ROUND(K150-H150,2)<>0),"Amount difference",IF(AND(G150="Refunded",L150=0),"Refunded, no refund",IF(AND(G150<>"Refunded",L150>0),"Refund, order not Refunded",IF(AND(L150>0,ROUND(M150-H150,2)<>0),"Refund amount differs","OK"))))))) -> OK | O150: =IF(N150="OK",0,IF(N150="Paid, no payment",H150,IF(N150="Payment on failed/cancelled",K150,IF(OR(N150="Duplicate charge",N150="Amount difference"),K150-H150,IF(N150="Refunded, no refund",H150,M150))))) -> 0
A151: ORD26000150 | B151: 46281 | C151: CUST20527 | D151: Chennai | E151: UPI | F151: 999.0 | G151: Paid | H151: =VALUE(SUBSTITUTE(F151,",","")) -> 999 | I151: =IF(TRIM(D151)="","Unknown",TRIM(D151)) -> Chennai | J151: =COUNTIFS(pg_transaction_cleaned!$O:$O,A151,pg_transaction_cleaned!$F:$F,"CAPTURE") -> 1 | K151: =SUMIFS(pg_transaction_cleaned!$H:$H,pg_transaction_cleaned!$O:$O,A151,pg_transaction_cleaned!$F:$F,"CAPTURE") -> 999 | L151: =COUNTIFS(pg_transaction_cleaned!$O:$O,A151,pg_transaction_cleaned!$F:$F,"REFUND") -> 0 | M151: =SUMIFS(pg_transaction_cleaned!$H:$H,pg_transaction_cleaned!$O:$O,A151,pg_transaction_cleaned!$F:$F,"REFUND") -> 0 | N151: =IF(AND(G151="Paid",J151=0),"Paid, no payment",IF(AND(OR(G151="Failed",G151="Cancelled"),J151>0),"Payment on failed/cancelled",IF(J151>1,"Duplicate charge",IF(AND(J151=1,ROUND(K151-H151,2)<>0),"Amount difference",IF(AND(G151="Refunded",L151=0),"Refunded, no refund",IF(AND(G151<>"Refunded",L151>0),"Refund, order not Refunded",IF(AND(L151>0,ROUND(M151-H151,2)<>0),"Refund amount differs","OK"))))))) -> OK | O151: =IF(N151="OK",0,IF(N151="Paid, no payment",H151,IF(N151="Payment on failed/cancelled",K151,IF(OR(N151="Duplicate charge",N151="Amount difference"),K151-H151,IF(N151="Refunded, no refund",H151,M151))))) -> 0
A152: ORD26000151 | B152: 46293 | C152: CUST73956 | D152: Jaipur | E152: Card | F152: 11,097.00 | G152: Cancelled | H152: =VALUE(SUBSTITUTE(F152,",","")) -> 11097 | I152: =IF(TRIM(D152)="","Unknown",TRIM(D152)) -> Jaipur | J152: =COUNTIFS(pg_transaction_cleaned!$O:$O,A152,pg_transaction_cleaned!$F:$F,"CAPTURE") -> 0 | K152: =SUMIFS(pg_transaction_cleaned!$H:$H,pg_transaction_cleaned!$O:$O,A152,pg_transaction_cleaned!$F:$F,"CAPTURE") -> 0 | L152: =COUNTIFS(pg_transaction_cleaned!$O:$O,A152,pg_transaction_cleaned!$F:$F,"REFUND") -> 0 | M152: =SUMIFS(pg_transaction_cleaned!$H:$H,pg_transaction_cleaned!$O:$O,A152,pg_transaction_cleaned!$F:$F,"REFUND") -> 0 | N152: =IF(AND(G152="Paid",J152=0),"Paid, no payment",IF(AND(OR(G152="Failed",G152="Cancelled"),J152>0),"Payment on failed/cancelled",IF(J152>1,"Duplicate charge",IF(AND(J152=1,ROUND(K152-H152,2)<>0),"Amount difference",IF(AND(G152="Refunded",L152=0),"Refunded, no refund",IF(AND(G152<>"Refunded",L152>0),"Refund, order not Refunded",IF(AND(L152>0,ROUND(M152-H152,2)<>0),"Refund amount differs","OK"))))))) -> OK | O152: =IF(N152="OK",0,IF(N152="Paid, no payment",H152,IF(N152="Payment on failed/cancelled",K152,IF(OR(N152="Duplicate charge",N152="Amount difference"),K152-H152,IF(N152="Refunded, no refund",H152,M152))))) -> 0
A153: ORD26000152 | B153: 46267 | C153: CUST39817 | D153: Pune | E153: Wallet | F153: 948.0 | G153: Paid | H153: =VALUE(SUBSTITUTE(F153,",","")) -> 948 | I153: =IF(TRIM(D153)="","Unknown",TRIM(D153)) -> Pune | J153: =COUNTIFS(pg_transaction_cleaned!$O:$O,A153,pg_transaction_cleaned!$F:$F,"CAPTURE") -> 1 | K153: =SUMIFS(pg_transaction_cleaned!$H:$H,pg_transaction_cleaned!$O:$O,A153,pg_transaction_cleaned!$F:$F,"CAPTURE") -> 948 | L153: =COUNTIFS(pg_transaction_cleaned!$O:$O,A153,pg_transaction_cleaned!$F:$F,"REFUND") -> 0 | M153: =SUMIFS(pg_transaction_cleaned!$H:$H,pg_transaction_cleaned!$O:$O,A153,pg_transaction_cleaned!$F:$F,"REFUND") -> 0 | N153: =IF(AND(G153="Paid",J153=0),"Paid, no payment",IF(AND(OR(G153="Failed",G153="Cancelled"),J153>0),"Payment on failed/cancelled",IF(J153>1,"Duplicate charge",IF(AND(J153=1,ROUND(K153-H153,2)<>0),"Amount difference",IF(AND(G153="Refunded",L153=0),"Refunded, no refund",IF(AND(G153<>"Refunded",L153>0),"Refund, order not Refunded",IF(AND(L153>0,ROUND(M153-H153,2)<>0),"Refund amount differs","OK"))))))) -> OK | O153: =IF(N153="OK",0,IF(N153="Paid, no payment",H153,IF(N153="Payment on failed/cancelled",K153,IF(OR(N153="Duplicate charge",N153="Amount difference"),K153-H153,IF(N153="Refunded, no refund",H153,M153))))) -> 0
A154: ORD26000153 | B154: 46279 | C154: CUST68153 | D154: Delhi | E154: NetBanking | F154: 4999.0 | G154: Paid | H154: =VALUE(SUBSTITUTE(F154,",","")) -> 4999 | I154: =IF(TRIM(D154)="","Unknown",TRIM(D154)) -> Delhi | J154: =COUNTIFS(pg_transaction_cleaned!$O:$O,A154,pg_transaction_cleaned!$F:$F,"CAPTURE") -> 1 | K154: =SUMIFS(pg_transaction_cleaned!$H:$H,pg_transaction_cleaned!$O:$O,A154,pg_transaction_cleaned!$F:$F,"CAPTURE") -> 4999 | L154: =COUNTIFS(pg_transaction_cleaned!$O:$O,A154,pg_transaction_cleaned!$F:$F,"REFUND") -> 0 | M154: =SUMIFS(pg_transaction_cleaned!$H:$H,pg_transaction_cleaned!$O:$O,A154,pg_transaction_cleaned!$F:$F,"REFUND") -> 0 | N154: =IF(AND(G154="Paid",J154=0),"Paid, no payment",IF(AND(OR(G154="Failed",G154="Cancelled"),J154>0),"Payment on failed/cancelled",IF(J154>1,"Duplicate charge",IF(AND(J154=1,ROUND(K154-H154,2)<>0),"Amount difference",IF(AND(G154="Refunded",L154=0),"Refunded, no refund",IF(AND(G154<>"Refunded",L154>0),"Refund, order not Refunded",IF(AND(L154>0,ROUND(M154-H154,2)<>0),"Refund amount differs","OK"))))))) -> OK | O154: =IF(N154="OK",0,IF(N154="Paid, no payment",H154,IF(N154="Payment on failed/cancelled",K154,IF(OR(N154="Duplicate charge",N154="Amount difference"),K154-H154,IF(N154="Refunded, no refund",H154,M154))))) -> 0
A155: ORD26000154 | B155: 46288 | C155: CUST48452 | D155: Chennai | E155: Card | F155: 299.0 | G155: Paid | H155: =VALUE(SUBSTITUTE(F155,",","")) -> 299 | I155: =IF(TRIM(D155)="","Unknown",TRIM(D155)) -> Chennai | J155: =COUNTIFS(pg_transaction_cleaned!$O:$O,A155,pg_transaction_cleaned!$F:$F,"CAPTURE") -> 1 | K155: =SUMIFS(pg_transaction_cleaned!$H:$H,pg_transaction_cleaned!$O:$O,A155,pg_transaction_cleaned!$F:$F,"CAPTURE") -> 299 | L155: =COUNTIFS(pg_transaction_cleaned!$O:$O,A155,pg_transaction_cleaned!$F:$F,"REFUND") -> 0 | M155: =SUMIFS(pg_transaction_cleaned!$H:$H,pg_transaction_cleaned!$O:$O,A155,pg_transaction_cleaned!$F:$F,"REFUND") -> 0 | N155: =IF(AND(G155="Paid",J155=0),"Paid, no payment",IF(AND(OR(G155="Failed",G155="Cancelled"),J155>0),"Payment on failed/cancelled",IF(J155>1,"Duplicate charge",IF(AND(J155=1,ROUND(K155-H155,2)<>0),"Amount difference",IF(AND(G155="Refunded",L155=0),"Refunded, no refund",IF(AND(G155<>"Refunded",L155>0),"Refund, order not Refunded",IF(AND(L155>0,ROUND(M155-H155,2)<>0),"Refund amount differs","OK"))))))) -> OK | O155: =IF(N155="OK",0,IF(N155="Paid, no payment",H155,IF(N155="Payment on failed/cancelled",K155,IF(OR(N155="Duplicate charge",N155="Amount difference"),K155-H155,IF(N155="Refunded, no refund",H155,M155))))) -> 0
A156: ORD26000155 | B156: 46277 | C156: CUST33600 | D156: Delhi | E156: Card | F156: 1098.0 | G156: Paid | H156: =VALUE(SUBSTITUTE(F156,",","")) -> 1098 | I156: =IF(TRIM(D156)="","Unknown",TRIM(D156)) -> Delhi | J156: =COUNTIFS(pg_transaction_cleaned!$O:$O,A156,pg_transaction_cleaned!$F:$F,"CAPTURE") -> 1 | K156: =SUMIFS(pg_transaction_cleaned!$H:$H,pg_transaction_cleaned!$O:$O,A156,pg_transaction_cleaned!$F:$F,"CAPTURE") -> 1098 | L156: =COUNTIFS(pg_transaction_cleaned!$O:$O,A156,pg_transaction_cleaned!$F:$F,"REFUND") -> 0 | M156: =SUMIFS(pg_transaction_cleaned!$H:$H,pg_transaction_cleaned!$O:$O,A156,pg_transaction_cleaned!$F:$F,"REFUND") -> 0 | N156: =IF(AND(G156="Paid",J156=0),"Paid, no payment",IF(AND(OR(G156="Failed",G156="Cancelled"),J156>0),"Payment on failed/cancelled",IF(J156>1,"Duplicate charge",IF(AND(J156=1,ROUND(K156-H156,2)<>0),"Amount difference",IF(AND(G156="Refunded",L156=0),"Refunded, no refund",IF(AND(G156<>"Refunded",L156>0),"Refund, order not Refunded",IF(AND(L156>0,ROUND(M156-H156,2)<>0),"Refund amount differs","OK"))))))) -> OK | O156: =IF(N156="OK",0,IF(N156="Paid, no payment",H156,IF(N156="Payment on failed/cancelled",K156,IF(OR(N156="Duplicate charge",N156="Amount difference"),K156-H156,IF(N156="Refunded, no refund",H156,M156))))) -> 0
A157: ORD26000156 | B157: 46271 | C157: CUST41566 | D157: Ahmedabad | E157: Card | F157: 2499.0 | G157: Paid | H157: =VALUE(SUBSTITUTE(F157,",","")) -> 2499 | I157: =IF(TRIM(D157)="","Unknown",TRIM(D157)) -> Ahmedabad | J157: =COUNTIFS(pg_transaction_cleaned!$O:$O,A157,pg_transaction_cleaned!$F:$F,"CAPTURE") -> 1 | K157: =SUMIFS(pg_transaction_cleaned!$H:$H,pg_transaction_cleaned!$O:$O,A157,pg_transaction_cleaned!$F:$F,"CAPTURE") -> 2499 | L157: =COUNTIFS(pg_transaction_cleaned!$O:$O,A157,pg_transaction_cleaned!$F:$F,"REFUND") -> 0 | M157: =SUMIFS(pg_transaction_cleaned!$H:$H,pg_transaction_cleaned!$O:$O,A157,pg_transaction_cleaned!$F:$F,"REFUND") -> 0 | N157: =IF(AND(G157="Paid",J157=0),"Paid, no payment",IF(AND(OR(G157="Failed",G157="Cancelled"),J157>0),"Payment on failed/cancelled",IF(J157>1,"Duplicate charge",IF(AND(J157=1,ROUND(K157-H157,2)<>0),"Amount difference",IF(AND(G157="Refunded",L157=0),"Refunded, no refund",IF(AND(G157<>"Refunded",L157>0),"Refund, order not Refunded",IF(AND(L157>0,ROUND(M157-H157,2)<>0),"Refund amount differs","OK"))))))) -> OK | O157: =IF(N157="OK",0,IF(N157="Paid, no payment",H157,IF(N157="Payment on failed/cancelled",K157,IF(OR(N157="Duplicate charge",N157="Amount difference"),K157-H157,IF(N157="Refunded, no refund",H157,M157))))) -> 0
A158: ORD26000157 | B158: 46295 | C158: CUST43466 | D158: Mumbai | E158: UPI | F158: 1098.0 | G158: Paid | H158: =VALUE(SUBSTITUTE(F158,",","")) -> 1098 | I158: =IF(TRIM(D158)="","Unknown",TRIM(D158)) -> Mumbai | J158: =COUNTIFS(pg_transaction_cleaned!$O:$O,A158,pg_transaction_cleaned!$F:$F,"CAPTURE") -> 1 | K158: =SUMIFS(pg_transaction_cleaned!$H:$H,pg_transaction_cleaned!$O:$O,A158,pg_transaction_cleaned!$F:$F,"CAPTURE") -> 1098 | L158: =COUNTIFS(pg_transaction_cleaned!$O:$O,A158,pg_transaction_cleaned!$F:$F,"REFUND") -> 0 | M158: =SUMIFS(pg_transaction_cleaned!$H:$H,pg_transaction_cleaned!$O:$O,A158,pg_transaction_cleaned!$F:$F,"REFUND") -> 0 | N158: =IF(AND(G158="Paid",J158=0),"Paid, no payment",IF(AND(OR(G158="Failed",G158="Cancelled"),J158>0),"Payment on failed/cancelled",IF(J158>1,"Duplicate charge",IF(AND(J158=1,ROUND(K158-H158,2)<>0),"Amount difference",IF(AND(G158="Refunded",L158=0),"Refunded, no refund",IF(AND(G158<>"Refunded",L158>0),"Refund, order not Refunded",IF(AND(L158>0,ROUND(M158-H158,2)<>0),"Refund amount differs","OK"))))))) -> OK | O158: =IF(N158="OK",0,IF(N158="Paid, no payment",H158,IF(N158="Payment on failed/cancelled",K158,IF(OR(N158="Duplicate charge",N158="Amount difference"),K158-H158,IF(N158="Refunded, no refund",H158,M158))))) -> 0
A159: ORD26000158 | B159: 46294 | C159: CUST55293 | D159: Lucknow | E159: UPI | F159: 3798.0 | G159: Paid | H159: =VALUE(SUBSTITUTE(F159,",","")) -> 3798 | I159: =IF(TRIM(D159)="","Unknown",TRIM(D159)) -> Lucknow | J159: =COUNTIFS(pg_transaction_cleaned!$O:$O,A159,pg_transaction_cleaned!$F:$F,"CAPTURE") -> 1 | K159: =SUMIFS(pg_transaction_cleaned!$H:$H,pg_transaction_cleaned!$O:$O,A159,pg_transaction_cleaned!$F:$F,"CAPTURE") -> 3798 | L159: =COUNTIFS(pg_transaction_cleaned!$O:$O,A159,pg_transaction_cleaned!$F:$F,"REFUND") -> 0 | M159: =SUMIFS(pg_transaction_cleaned!$H:$H,pg_transaction_cleaned!$O:$O,A159,pg_transaction_cleaned!$F:$F,"REFUND") -> 0 | N159: =IF(AND(G159="Paid",J159=0),"Paid, no payment",IF(AND(OR(G159="Failed",G159="Cancelled"),J159>0),"Payment on failed/cancelled",IF(J159>1,"Duplicate charge",IF(AND(J159=1,ROUND(K159-H159,2)<>0),"Amount difference",IF(AND(G159="Refunded",L159=0),"Refunded, no refund",IF(AND(G159<>"Refunded",L159>0),"Refund, order not Refunded",IF(AND(L159>0,ROUND(M159-H159,2)<>0),"Refund amount differs","OK"))))))) -> OK | O159: =IF(N159="OK",0,IF(N159="Paid, no payment",H159,IF(N159="Payment on failed/cancelled",K159,IF(OR(N159="Duplicate charge",N159="Amount difference"),K159-H159,IF(N159="Refunded, no refund",H159,M159))))) -> 0
A160: ORD26000159 | B160: 46275 | C160: CUST60422 | D160: Ahmedabad | E160: UPI | F160: 5597.0 | G160: Paid | H160: =VALUE(SUBSTITUTE(F160,",","")) -> 5597 | I160: =IF(TRIM(D160)="","Unknown",TRIM(D160)) -> Ahmedabad | J160: =COUNTIFS(pg_transaction_cleaned!$O:$O,A160,pg_transaction_cleaned!$F:$F,"CAPTURE") -> 1 | K160: =SUMIFS(pg_transaction_cleaned!$H:$H,pg_transaction_cleaned!$O:$O,A160,pg_transaction_cleaned!$F:$F,"CAPTURE") -> 5597 | L160: =COUNTIFS(pg_transaction_cleaned!$O:$O,A160,pg_transaction_cleaned!$F:$F,"REFUND") -> 0 | M160: =SUMIFS(pg_transaction_cleaned!$H:$H,pg_transaction_cleaned!$O:$O,A160,pg_transaction_cleaned!$F:$F,"REFUND") -> 0 | N160: =IF(AND(G160="Paid",J160=0),"Paid, no payment",IF(AND(OR(G160="Failed",G160="Cancelled"),J160>0),"Payment on failed/cancelled",IF(J160>1,"Duplicate charge",IF(AND(J160=1,ROUND(K160-H160,2)<>0),"Amount difference",IF(AND(G160="Refunded",L160=0),"Refunded, no refund",IF(AND(G160<>"Refunded",L160>0),"Refund, order not Refunded",IF(AND(L160>0,ROUND(M160-H160,2)<>0),"Refund amount differs","OK"))))))) -> OK | O160: =IF(N160="OK",0,IF(N160="Paid, no payment",H160,IF(N160="Payment on failed/cancelled",K160,IF(OR(N160="Duplicate charge",N160="Amount difference"),K160-H160,IF(N160="Refunded, no refund",H160,M160))))) -> 0
A161: ORD26000160 | B161: 46269 | C161: CUST48696 | D161: Mumbai | E161: Card | F161: 1299.0 | G161: Paid | H161: =VALUE(SUBSTITUTE(F161,",","")) -> 1299 | I161: =IF(TRIM(D161)="","Unknown",TRIM(D161)) -> Mumbai | J161: =COUNTIFS(pg_transaction_cleaned!$O:$O,A161,pg_transaction_cleaned!$F:$F,"CAPTURE") -> 1 | K161: =SUMIFS(pg_transaction_cleaned!$H:$H,pg_transaction_cleaned!$O:$O,A161,pg_transaction_cleaned!$F:$F,"CAPTURE") -> 1299 | L161: =COUNTIFS(pg_transaction_cleaned!$O:$O,A161,pg_transaction_cleaned!$F:$F,"REFUND") -> 0 | M161: =SUMIFS(pg_transaction_cleaned!$H:$H,pg_transaction_cleaned!$O:$O,A161,pg_transaction_cleaned!$F:$F,"REFUND") -> 0 | N161: =IF(AND(G161="Paid",J161=0),"Paid, no payment",IF(AND(OR(G161="Failed",G161="Cancelled"),J161>0),"Payment on failed/cancelled",IF(J161>1,"Duplicate charge",IF(AND(J161=1,ROUND(K161-H161,2)<>0),"Amount difference",IF(AND(G161="Refunded",L161=0),"Refunded, no refund",IF(AND(G161<>"Refunded",L161>0),"Refund, order not Refunded",IF(AND(L161>0,ROUND(M161-H161,2)<>0),"Refund amount differs","OK"))))))) -> OK | O161: =IF(N161="OK",0,IF(N161="Paid, no payment",H161,IF(N161="Payment on failed/cancelled",K161,IF(OR(N161="Duplicate charge",N161="Amount difference"),K161-H161,IF(N161="Refunded, no refund",H161,M161))))) -> 0
A162: ORD26000161 | B162: 46292 | C162: CUST16428 | D162: Lucknow | E162: Card | F162: 2397.0 | G162: Paid | H162: =VALUE(SUBSTITUTE(F162,",","")) -> 2397 | I162: =IF(TRIM(D162)="","Unknown",TRIM(D162)) -> Lucknow | J162: =COUNTIFS(pg_transaction_cleaned!$O:$O,A162,pg_transaction_cleaned!$F:$F,"CAPTURE") -> 1 | K162: =SUMIFS(pg_transaction_cleaned!$H:$H,pg_transaction_cleaned!$O:$O,A162,pg_transaction_cleaned!$F:$F,"CAPTURE") -> 2397 | L162: =COUNTIFS(pg_transaction_cleaned!$O:$O,A162,pg_transaction_cleaned!$F:$F,"REFUND") -> 0 | M162: =SUMIFS(pg_transaction_cleaned!$H:$H,pg_transaction_cleaned!$O:$O,A162,pg_transaction_cleaned!$F:$F,"REFUND") -> 0 | N162: =IF(AND(G162="Paid",J162=0),"Paid, no payment",IF(AND(OR(G162="Failed",G162="Cancelled"),J162>0),"Payment on failed/cancelled",IF(J162>1,"Duplicate charge",IF(AND(J162=1,ROUND(K162-H162,2)<>0),"Amount difference",IF(AND(G162="Refunded",L162=0),"Refunded, no refund",IF(AND(G162<>"Refunded",L162>0),"Refund, order not Refunded",IF(AND(L162>0,ROUND(M162-H162,2)<>0),"Refund amount differs","OK"))))))) -> OK | O162: =IF(N162="OK",0,IF(N162="Paid, no payment",H162,IF(N162="Payment on failed/cancelled",K162,IF(OR(N162="Duplicate charge",N162="Amount difference"),K162-H162,IF(N162="Refunded, no refund",H162,M162))))) -> 0
A163: ORD26000162 | B163: 46289 | C163: CUST56179 | E163: UPI | F163: 8,798.00 | G163: Paid | H163: =VALUE(SUBSTITUTE(F163,",","")) -> 8798 | I163: =IF(TRIM(D163)="","Unknown",TRIM(D163)) -> Unknown | J163: =COUNTIFS(pg_transaction_cleaned!$O:$O,A163,pg_transaction_cleaned!$F:$F,"CAPTURE") -> 1 | K163: =SUMIFS(pg_transaction_cleaned!$H:$H,pg_transaction_cleaned!$O:$O,A163,pg_transaction_cleaned!$F:$F,"CAPTURE") -> 8798 | L163: =COUNTIFS(pg_transaction_cleaned!$O:$O,A163,pg_transaction_cleaned!$F:$F,"REFUND") -> 0 | M163: =SUMIFS(pg_transaction_cleaned!$H:$H,pg_transaction_cleaned!$O:$O,A163,pg_transaction_cleaned!$F:$F,"REFUND") -> 0 | N163: =IF(AND(G163="Paid",J163=0),"Paid, no payment",IF(AND(OR(G163="Failed",G163="Cancelled"),J163>0),"Payment on failed/cancelled",IF(J163>1,"Duplicate charge",IF(AND(J163=1,ROUND(K163-H163,2)<>0),"Amount difference",IF(AND(G163="Refunded",L163=0),"Refunded, no refund",IF(AND(G163<>"Refunded",L163>0),"Refund, order not Refunded",IF(AND(L163>0,ROUND(M163-H163,2)<>0),"Refund amount differs","OK"))))))) -> OK | O163: =IF(N163="OK",0,IF(N163="Paid, no payment",H163,IF(N163="Payment on failed/cancelled",K163,IF(OR(N163="Duplicate charge",N163="Amount difference"),K163-H163,IF(N163="Refunded, no refund",H163,M163))))) -> 0
A164: ORD26000163 | B164: 46286 | C164: CUST96400 | D164: Delhi | E164: Card | F164: 2499.0 | G164: Paid | H164: =VALUE(SUBSTITUTE(F164,",","")) -> 2499 | I164: =IF(TRIM(D164)="","Unknown",TRIM(D164)) -> Delhi | J164: =COUNTIFS(pg_transaction_cleaned!$O:$O,A164,pg_transaction_cleaned!$F:$F,"CAPTURE") -> 1 | K164: =SUMIFS(pg_transaction_cleaned!$H:$H,pg_transaction_cleaned!$O:$O,A164,pg_transaction_cleaned!$F:$F,"CAPTURE") -> 2499 | L164: =COUNTIFS(pg_transaction_cleaned!$O:$O,A164,pg_transaction_cleaned!$F:$F,"REFUND") -> 0 | M164: =SUMIFS(pg_transaction_cleaned!$H:$H,pg_transaction_cleaned!$O:$O,A164,pg_transaction_cleaned!$F:$F,"REFUND") -> 0 | N164: =IF(AND(G164="Paid",J164=0),"Paid, no payment",IF(AND(OR(G164="Failed",G164="Cancelled"),J164>0),"Payment on failed/cancelled",IF(J164>1,"Duplicate charge",IF(AND(J164=1,ROUND(K164-H164,2)<>0),"Amount difference",IF(AND(G164="Refunded",L164=0),"Refunded, no refund",IF(AND(G164<>"Refunded",L164>0),"Refund, order not Refunded",IF(AND(L164>0,ROUND(M164-H164,2)<>0),"Refund amount differs","OK"))))))) -> OK | O164: =IF(N164="OK",0,IF(N164="Paid, no payment",H164,IF(N164="Payment on failed/cancelled",K164,IF(OR(N164="Duplicate charge",N164="Amount difference"),K164-H164,IF(N164="Refunded, no refund",H164,M164))))) -> 0
A165: ORD26000164 | B165: 46286 | C165: CUST67779 | D165: Mumbai | E165: UPI | F165: 2999.0 | G165: Paid | H165: =VALUE(SUBSTITUTE(F165,",","")) -> 2999 | I165: =IF(TRIM(D165)="","Unknown",TRIM(D165)) -> Mumbai | J165: =COUNTIFS(pg_transaction_cleaned!$O:$O,A165,pg_transaction_cleaned!$F:$F,"CAPTURE") -> 1 | K165: =SUMIFS(pg_transaction_cleaned!$H:$H,pg_transaction_cleaned!$O:$O,A165,pg_transaction_cleaned!$F:$F,"CAPTURE") -> 2999 | L165: =COUNTIFS(pg_transaction_cleaned!$O:$O,A165,pg_transaction_cleaned!$F:$F,"REFUND") -> 0 | M165: =SUMIFS(pg_transaction_cleaned!$H:$H,pg_transaction_cleaned!$O:$O,A165,pg_transaction_cleaned!$F:$F,"REFUND") -> 0 | N165: =IF(AND(G165="Paid",J165=0),"Paid, no payment",IF(AND(OR(G165="Failed",G165="Cancelled"),J165>0),"Payment on failed/cancelled",IF(J165>1,"Duplicate charge",IF(AND(J165=1,ROUND(K165-H165,2)<>0),"Amount difference",IF(AND(G165="Refunded",L165=0),"Refunded, no refund",IF(AND(G165<>"Refunded",L165>0),"Refund, order not Refunded",IF(AND(L165>0,ROUND(M165-H165,2)<>0),"Refund amount differs","OK"))))))) -> OK | O165: =IF(N165="OK",0,IF(N165="Paid, no payment",H165,IF(N165="Payment on failed/cancelled",K165,IF(OR(N165="Duplicate charge",N165="Amount difference"),K165-H165,IF(N165="Refunded, no refund",H165,M165))))) -> 0
A166: ORD26000165 | B166: 46284 | C166: CUST52823 | D166: Kolkata | E166: Wallet | F166: 3499.0 | G166: Paid | H166: =VALUE(SUBSTITUTE(F166,",","")) -> 3499 | I166: =IF(TRIM(D166)="","Unknown",TRIM(D166)) -> Kolkata | J166: =COUNTIFS(pg_transaction_cleaned!$O:$O,A166,pg_transaction_cleaned!$F:$F,"CAPTURE") -> 1 | K166: =SUMIFS(pg_transaction_cleaned!$H:$H,pg_transaction_cleaned!$O:$O,A166,pg_transaction_cleaned!$F:$F,"CAPTURE") -> 3499 | L166: =COUNTIFS(pg_transaction_cleaned!$O:$O,A166,pg_transaction_cleaned!$F:$F,"REFUND") -> 0 | M166: =SUMIFS(pg_transaction_cleaned!$H:$H,pg_transaction_cleaned!$O:$O,A166,pg_transaction_cleaned!$F:$F,"REFUND") -> 0 | N166: =IF(AND(G166="Paid",J166=0),"Paid, no payment",IF(AND(OR(G166="Failed",G166="Cancelled"),J166>0),"Payment on failed/cancelled",IF(J166>1,"Duplicate charge",IF(AND(J166=1,ROUND(K166-H166,2)<>0),"Amount difference",IF(AND(G166="Refunded",L166=0),"Refunded, no refund",IF(AND(G166<>"Refunded",L166>0),"Refund, order not Refunded",IF(AND(L166>0,ROUND(M166-H166,2)<>0),"Refund amount differs","OK"))))))) -> OK | O166: =IF(N166="OK",0,IF(N166="Paid, no payment",H166,IF(N166="Payment on failed/cancelled",K166,IF(OR(N166="Duplicate charge",N166="Amount difference"),K166-H166,IF(N166="Refunded, no refund",H166,M166))))) -> 0
A167: ORD26000166 | B167: 46271 | C167: CUST57953 | D167: Jaipur | E167: NetBanking | F167: 499.0 | G167: Paid | H167: =VALUE(SUBSTITUTE(F167,",","")) -> 499 | I167: =IF(TRIM(D167)="","Unknown",TRIM(D167)) -> Jaipur | J167: =COUNTIFS(pg_transaction_cleaned!$O:$O,A167,pg_transaction_cleaned!$F:$F,"CAPTURE") -> 1 | K167: =SUMIFS(pg_transaction_cleaned!$H:$H,pg_transaction_cleaned!$O:$O,A167,pg_transaction_cleaned!$F:$F,"CAPTURE") -> 499 | L167: =COUNTIFS(pg_transaction_cleaned!$O:$O,A167,pg_transaction_cleaned!$F:$F,"REFUND") -> 0 | M167: =SUMIFS(pg_transaction_cleaned!$H:$H,pg_transaction_cleaned!$O:$O,A167,pg_transaction_cleaned!$F:$F,"REFUND") -> 0 | N167: =IF(AND(G167="Paid",J167=0),"Paid, no payment",IF(AND(OR(G167="Failed",G167="Cancelled"),J167>0),"Payment on failed/cancelled",IF(J167>1,"Duplicate charge",IF(AND(J167=1,ROUND(K167-H167,2)<>0),"Amount difference",IF(AND(G167="Refunded",L167=0),"Refunded, no refund",IF(AND(G167<>"Refunded",L167>0),"Refund, order not Refunded",IF(AND(L167>0,ROUND(M167-H167,2)<>0),"Refund amount differs","OK"))))))) -> OK | O167: =IF(N167="OK",0,IF(N167="Paid, no payment",H167,IF(N167="Payment on failed/cancelled",K167,IF(OR(N167="Duplicate charge",N167="Amount difference"),K167-H167,IF(N167="Refunded, no refund",H167,M167))))) -> 0
A168: ORD26000167 | B168: 46282 | C168: CUST73156 | D168: Hyderabad | E168: Wallet | F168: 7999.0 | G168: Paid | H168: =VALUE(SUBSTITUTE(F168,",","")) -> 7999 | I168: =IF(TRIM(D168)="","Unknown",TRIM(D168)) -> Hyderabad | J168: =COUNTIFS(pg_transaction_cleaned!$O:$O,A168,pg_transaction_cleaned!$F:$F,"CAPTURE") -> 1 | K168: =SUMIFS(pg_transaction_cleaned!$H:$H,pg_transaction_cleaned!$O:$O,A168,pg_transaction_cleaned!$F:$F,"CAPTURE") -> 7999 | L168: =COUNTIFS(pg_transaction_cleaned!$O:$O,A168,pg_transaction_cleaned!$F:$F,"REFUND") -> 0 | M168: =SUMIFS(pg_transaction_cleaned!$H:$H,pg_transaction_cleaned!$O:$O,A168,pg_transaction_cleaned!$F:$F,"REFUND") -> 0 | N168: =IF(AND(G168="Paid",J168=0),"Paid, no payment",IF(AND(OR(G168="Failed",G168="Cancelled"),J168>0),"Payment on failed/cancelled",IF(J168>1,"Duplicate charge",IF(AND(J168=1,ROUND(K168-H168,2)<>0),"Amount difference",IF(AND(G168="Refunded",L168=0),"Refunded, no refund",IF(AND(G168<>"Refunded",L168>0),"Refund, order not Refunded",IF(AND(L168>0,ROUND(M168-H168,2)<>0),"Refund amount differs","OK"))))))) -> OK | O168: =IF(N168="OK",0,IF(N168="Paid, no payment",H168,IF(N168="Payment on failed/cancelled",K168,IF(OR(N168="Duplicate charge",N168="Amount difference"),K168-H168,IF(N168="Refunded, no refund",H168,M168))))) -> 0
A169: ORD26000168 | B169: 46289 | C169: CUST28449 | D169: Bengaluru | E169: Wallet | F169: 4999.0 | G169: Paid | H169: =VALUE(SUBSTITUTE(F169,",","")) -> 4999 | I169: =IF(TRIM(D169)="","Unknown",TRIM(D169)) -> Bengaluru | J169: =COUNTIFS(pg_transaction_cleaned!$O:$O,A169,pg_transaction_cleaned!$F:$F,"CAPTURE") -> 1 | K169: =SUMIFS(pg_transaction_cleaned!$H:$H,pg_transaction_cleaned!$O:$O,A169,pg_transaction_cleaned!$F:$F,"CAPTURE") -> 4999 | L169: =COUNTIFS(pg_transaction_cleaned!$O:$O,A169,pg_transaction_cleaned!$F:$F,"REFUND") -> 0 | M169: =SUMIFS(pg_transaction_cleaned!$H:$H,pg_transaction_cleaned!$O:$O,A169,pg_transaction_cleaned!$F:$F,"REFUND") -> 0 | N169: =IF(AND(G169="Paid",J169=0),"Paid, no payment",IF(AND(OR(G169="Failed",G169="Cancelled"),J169>0),"Payment on failed/cancelled",IF(J169>1,"Duplicate charge",IF(AND(J169=1,ROUND(K169-H169,2)<>0),"Amount difference",IF(AND(G169="Refunded",L169=0),"Refunded, no refund",IF(AND(G169<>"Refunded",L169>0),"Refund, order not Refunded",IF(AND(L169>0,ROUND(M169-H169,2)<>0),"Refund amount differs","OK"))))))) -> OK | O169: =IF(N169="OK",0,IF(N169="Paid, no payment",H169,IF(N169="Payment on failed/cancelled",K169,IF(OR(N169="Duplicate charge",N169="Amount difference"),K169-H169,IF(N169="Refunded, no refund",H169,M169))))) -> 0
A170: ORD26000169 | B170: 46293 | C170: CUST57942 | D170: Pune | E170: NetBanking | F170: 7797.0 | G170: Refunded | H170: =VALUE(SUBSTITUTE(F170,",","")) -> 7797 | I170: =IF(TRIM(D170)="","Unknown",TRIM(D170)) -> Pune | J170: =COUNTIFS(pg_transaction_cleaned!$O:$O,A170,pg_transaction_cleaned!$F:$F,"CAPTURE") -> 1 | K170: =SUMIFS(pg_transaction_cleaned!$H:$H,pg_transaction_cleaned!$O:$O,A170,pg_transaction_cleaned!$F:$F,"CAPTURE") -> 7797 | L170: =COUNTIFS(pg_transaction_cleaned!$O:$O,A170,pg_transaction_cleaned!$F:$F,"REFUND") -> 1 | M170: =SUMIFS(pg_transaction_cleaned!$H:$H,pg_transaction_cleaned!$O:$O,A170,pg_transaction_cleaned!$F:$F,"REFUND") -> 7797 | N170: =IF(AND(G170="Paid",J170=0),"Paid, no payment",IF(AND(OR(G170="Failed",G170="Cancelled"),J170>0),"Payment on failed/cancelled",IF(J170>1,"Duplicate charge",IF(AND(J170=1,ROUND(K170-H170,2)<>0),"Amount difference",IF(AND(G170="Refunded",L170=0),"Refunded, no refund",IF(AND(G170<>"Refunded",L170>0),"Refund, order not Refunded",IF(AND(L170>0,ROUND(M170-H170,2)<>0),"Refund amount differs","OK"))))))) -> OK | O170: =IF(N170="OK",0,IF(N170="Paid, no payment",H170,IF(N170="Payment on failed/cancelled",K170,IF(OR(N170="Duplicate charge",N170="Amount difference"),K170-H170,IF(N170="Refunded, no refund",H170,M170))))) -> 0
A171: ORD26000170 | B171: 46291 | C171: CUST98188 | E171: UPI | F171: 1098.0 | G171: Paid | H171: =VALUE(SUBSTITUTE(F171,",","")) -> 1098 | I171: =IF(TRIM(D171)="","Unknown",TRIM(D171)) -> Unknown | J171: =COUNTIFS(pg_transaction_cleaned!$O:$O,A171,pg_transaction_cleaned!$F:$F,"CAPTURE") -> 1 | K171: =SUMIFS(pg_transaction_cleaned!$H:$H,pg_transaction_cleaned!$O:$O,A171,pg_transaction_cleaned!$F:$F,"CAPTURE") -> 1098 | L171: =COUNTIFS(pg_transaction_cleaned!$O:$O,A171,pg_transaction_cleaned!$F:$F,"REFUND") -> 0 | M171: =SUMIFS(pg_transaction_cleaned!$H:$H,pg_transaction_cleaned!$O:$O,A171,pg_transaction_cleaned!$F:$F,"REFUND") -> 0 | N171: =IF(AND(G171="Paid",J171=0),"Paid, no payment",IF(AND(OR(G171="Failed",G171="Cancelled"),J171>0),"Payment on failed/cancelled",IF(J171>1,"Duplicate charge",IF(AND(J171=1,ROUND(K171-H171,2)<>0),"Amount difference",IF(AND(G171="Refunded",L171=0),"Refunded, no refund",IF(AND(G171<>"Refunded",L171>0),"Refund, order not Refunded",IF(AND(L171>0,ROUND(M171-H171,2)<>0),"Refund amount differs","OK"))))))) -> OK | O171: =IF(N171="OK",0,IF(N171="Paid, no payment",H171,IF(N171="Payment on failed/cancelled",K171,IF(OR(N171="Duplicate charge",N171="Amount difference"),K171-H171,IF(N171="Refunded, no refund",H171,M171))))) -> 0
A172: ORD26000171 | B172: 46284 | C172: CUST40647 | D172: Ahmedabad | E172: UPI | F172: 10998.0 | G172: Cancelled | H172: =VALUE(SUBSTITUTE(F172,",","")) -> 10998 | I172: =IF(TRIM(D172)="","Unknown",TRIM(D172)) -> Ahmedabad | J172: =COUNTIFS(pg_transaction_cleaned!$O:$O,A172,pg_transaction_cleaned!$F:$F,"CAPTURE") -> 0 | K172: =SUMIFS(pg_transaction_cleaned!$H:$H,pg_transaction_cleaned!$O:$O,A172,pg_transaction_cleaned!$F:$F,"CAPTURE") -> 0 | L172: =COUNTIFS(pg_transaction_cleaned!$O:$O,A172,pg_transaction_cleaned!$F:$F,"REFUND") -> 0 | M172: =SUMIFS(pg_transaction_cleaned!$H:$H,pg_transaction_cleaned!$O:$O,A172,pg_transaction_cleaned!$F:$F,"REFUND") -> 0 | N172: =IF(AND(G172="Paid",J172=0),"Paid, no payment",IF(AND(OR(G172="Failed",G172="Cancelled"),J172>0),"Payment on failed/cancelled",IF(J172>1,"Duplicate charge",IF(AND(J172=1,ROUND(K172-H172,2)<>0),"Amount difference",IF(AND(G172="Refunded",L172=0),"Refunded, no refund",IF(AND(G172<>"Refunded",L172>0),"Refund, order not Refunded",IF(AND(L172>0,ROUND(M172-H172,2)<>0),"Refund amount differs","OK"))))))) -> OK | O172: =IF(N172="OK",0,IF(N172="Paid, no payment",H172,IF(N172="Payment on failed/cancelled",K172,IF(OR(N172="Duplicate charge",N172="Amount difference"),K172-H172,IF(N172="Refunded, no refund",H172,M172))))) -> 0
A173: ORD26000172 | B173: 46266 | C173: CUST18285 | D173: Ahmedabad | E173: UPI | F173: 2798.0 | G173: Failed | H173: =VALUE(SUBSTITUTE(F173,",","")) -> 2798 | I173: =IF(TRIM(D173)="","Unknown",TRIM(D173)) -> Ahmedabad | J173: =COUNTIFS(pg_transaction_cleaned!$O:$O,A173,pg_transaction_cleaned!$F:$F,"CAPTURE") -> 0 | K173: =SUMIFS(pg_transaction_cleaned!$H:$H,pg_transaction_cleaned!$O:$O,A173,pg_transaction_cleaned!$F:$F,"CAPTURE") -> 0 | L173: =COUNTIFS(pg_transaction_cleaned!$O:$O,A173,pg_transaction_cleaned!$F:$F,"REFUND") -> 0 | M173: =SUMIFS(pg_transaction_cleaned!$H:$H,pg_transaction_cleaned!$O:$O,A173,pg_transaction_cleaned!$F:$F,"REFUND") -> 0 | N173: =IF(AND(G173="Paid",J173=0),"Paid, no payment",IF(AND(OR(G173="Failed",G173="Cancelled"),J173>0),"Payment on failed/cancelled",IF(J173>1,"Duplicate charge",IF(AND(J173=1,ROUND(K173-H173,2)<>0),"Amount difference",IF(AND(G173="Refunded",L173=0),"Refunded, no refund",IF(AND(G173<>"Refunded",L173>0),"Refund, order not Refunded",IF(AND(L173>0,ROUND(M173-H173,2)<>0),"Refund amount differs","OK"))))))) -> OK | O173: =IF(N173="OK",0,IF(N173="Paid, no payment",H173,IF(N173="Payment on failed/cancelled",K173,IF(OR(N173="Duplicate charge",N173="Amount difference"),K173-H173,IF(N173="Refunded, no refund",H173,M173))))) -> 0
A174: ORD26000173 | B174: 46295 | C174: CUST14877 | D174: Hyderabad | E174: UPI | F174: 5097.0 | G174: Paid | H174: =VALUE(SUBSTITUTE(F174,",","")) -> 5097 | I174: =IF(TRIM(D174)="","Unknown",TRIM(D174)) -> Hyderabad | J174: =COUNTIFS(pg_transaction_cleaned!$O:$O,A174,pg_transaction_cleaned!$F:$F,"CAPTURE") -> 1 | K174: =SUMIFS(pg_transaction_cleaned!$H:$H,pg_transaction_cleaned!$O:$O,A174,pg_transaction_cleaned!$F:$F,"CAPTURE") -> 5097 | L174: =COUNTIFS(pg_transaction_cleaned!$O:$O,A174,pg_transaction_cleaned!$F:$F,"REFUND") -> 0 | M174: =SUMIFS(pg_transaction_cleaned!$H:$H,pg_transaction_cleaned!$O:$O,A174,pg_transaction_cleaned!$F:$F,"REFUND") -> 0 | N174: =IF(AND(G174="Paid",J174=0),"Paid, no payment",IF(AND(OR(G174="Failed",G174="Cancelled"),J174>0),"Payment on failed/cancelled",IF(J174>1,"Duplicate charge",IF(AND(J174=1,ROUND(K174-H174,2)<>0),"Amount difference",IF(AND(G174="Refunded",L174=0),"Refunded, no refund",IF(AND(G174<>"Refunded",L174>0),"Refund, order not Refunded",IF(AND(L174>0,ROUND(M174-H174,2)<>0),"Refund amount differs","OK"))))))) -> OK | O174: =IF(N174="OK",0,IF(N174="Paid, no payment",H174,IF(N174="Payment on failed/cancelled",K174,IF(OR(N174="Duplicate charge",N174="Amount difference"),K174-H174,IF(N174="Refunded, no refund",H174,M174))))) -> 0
A175: ORD26000174 | B175: 46281 | C175: CUST60940 | D175: Ahmedabad | E175: UPI | F175: 349.0 | G175: Paid | H175: =VALUE(SUBSTITUTE(F175,",","")) -> 349 | I175: =IF(TRIM(D175)="","Unknown",TRIM(D175)) -> Ahmedabad | J175: =COUNTIFS(pg_transaction_cleaned!$O:$O,A175,pg_transaction_cleaned!$F:$F,"CAPTURE") -> 1 | K175: =SUMIFS(pg_transaction_cleaned!$H:$H,pg_transaction_cleaned!$O:$O,A175,pg_transaction_cleaned!$F:$F,"CAPTURE") -> 349 | L175: =COUNTIFS(pg_transaction_cleaned!$O:$O,A175,pg_transaction_cleaned!$F:$F,"REFUND") -> 0 | M175: =SUMIFS(pg_transaction_cleaned!$H:$H,pg_transaction_cleaned!$O:$O,A175,pg_transaction_cleaned!$F:$F,"REFUND") -> 0 | N175: =IF(AND(G175="Paid",J175=0),"Paid, no payment",IF(AND(OR(G175="Failed",G175="Cancelled"),J175>0),"Payment on failed/cancelled",IF(J175>1,"Duplicate charge",IF(AND(J175=1,ROUND(K175-H175,2)<>0),"Amount difference",IF(AND(G175="Refunded",L175=0),"Refunded, no refund",IF(AND(G175<>"Refunded",L175>0),"Refund, order not Refunded",IF(AND(L175>0,ROUND(M175-H175,2)<>0),"Refund amount differs","OK"))))))) -> OK | O175: =IF(N175="OK",0,IF(N175="Paid, no payment",H175,IF(N175="Payment on failed/cancelled",K175,IF(OR(N175="Duplicate charge",N175="Amount difference"),K175-H175,IF(N175="Refunded, no refund",H175,M175))))) -> 0
A176: ORD26000175 | B176: 46277 | C176: CUST30253 | D176: Kolkata | E176: Card | F176: 8797.0 | G176: Paid | H176: =VALUE(SUBSTITUTE(F176,",","")) -> 8797 | I176: =IF(TRIM(D176)="","Unknown",TRIM(D176)) -> Kolkata | J176: =COUNTIFS(pg_transaction_cleaned!$O:$O,A176,pg_transaction_cleaned!$F:$F,"CAPTURE") -> 1 | K176: =SUMIFS(pg_transaction_cleaned!$H:$H,pg_transaction_cleaned!$O:$O,A176,pg_transaction_cleaned!$F:$F,"CAPTURE") -> 8797 | L176: =COUNTIFS(pg_transaction_cleaned!$O:$O,A176,pg_transaction_cleaned!$F:$F,"REFUND") -> 0 | M176: =SUMIFS(pg_transaction_cleaned!$H:$H,pg_transaction_cleaned!$O:$O,A176,pg_transaction_cleaned!$F:$F,"REFUND") -> 0 | N176: =IF(AND(G176="Paid",J176=0),"Paid, no payment",IF(AND(OR(G176="Failed",G176="Cancelled"),J176>0),"Payment on failed/cancelled",IF(J176>1,"Duplicate charge",IF(AND(J176=1,ROUND(K176-H176,2)<>0),"Amount difference",IF(AND(G176="Refunded",L176=0),"Refunded, no refund",IF(AND(G176<>"Refunded",L176>0),"Refund, order not Refunded",IF(AND(L176>0,ROUND(M176-H176,2)<>0),"Refund amount differs","OK"))))))) -> OK | O176: =IF(N176="OK",0,IF(N176="Paid, no payment",H176,IF(N176="Payment on failed/cancelled",K176,IF(OR(N176="Duplicate charge",N176="Amount difference"),K176-H176,IF(N176="Refunded, no refund",H176,M176))))) -> 0
A177: ORD26000176 | B177: 46286 | C177: CUST46666 | D177: Mumbai | E177: UPI | F177: 7999.0 | G177: Paid | H177: =VALUE(SUBSTITUTE(F177,",","")) -> 7999 | I177: =IF(TRIM(D177)="","Unknown",TRIM(D177)) -> Mumbai | J177: =COUNTIFS(pg_transaction_cleaned!$O:$O,A177,pg_transaction_cleaned!$F:$F,"CAPTURE") -> 1 | K177: =SUMIFS(pg_transaction_cleaned!$H:$H,pg_transaction_cleaned!$O:$O,A177,pg_transaction_cleaned!$F:$F,"CAPTURE") -> 7999 | L177: =COUNTIFS(pg_transaction_cleaned!$O:$O,A177,pg_transaction_cleaned!$F:$F,"REFUND") -> 0 | M177: =SUMIFS(pg_transaction_cleaned!$H:$H,pg_transaction_cleaned!$O:$O,A177,pg_transaction_cleaned!$F:$F,"REFUND") -> 0 | N177: =IF(AND(G177="Paid",J177=0),"Paid, no payment",IF(AND(OR(G177="Failed",G177="Cancelled"),J177>0),"Payment on failed/cancelled",IF(J177>1,"Duplicate charge",IF(AND(J177=1,ROUND(K177-H177,2)<>0),"Amount difference",IF(AND(G177="Refunded",L177=0),"Refunded, no refund",IF(AND(G177<>"Refunded",L177>0),"Refund, order not Refunded",IF(AND(L177>0,ROUND(M177-H177,2)<>0),"Refund amount differs","OK"))))))) -> OK | O177: =IF(N177="OK",0,IF(N177="Paid, no payment",H177,IF(N177="Payment on failed/cancelled",K177,IF(OR(N177="Duplicate charge",N177="Amount difference"),K177-H177,IF(N177="Refunded, no refund",H177,M177))))) -> 0
A178: ORD26000177 | B178: 46288 | C178: CUST57537 | D178: Pune | E178: Wallet | F178: 599.0 | G178: Paid | H178: =VALUE(SUBSTITUTE(F178,",","")) -> 599 | I178: =IF(TRIM(D178)="","Unknown",TRIM(D178)) -> Pune | J178: =COUNTIFS(pg_transaction_cleaned!$O:$O,A178,pg_transaction_cleaned!$F:$F,"CAPTURE") -> 1 | K178: =SUMIFS(pg_transaction_cleaned!$H:$H,pg_transaction_cleaned!$O:$O,A178,pg_transaction_cleaned!$F:$F,"CAPTURE") -> 599 | L178: =COUNTIFS(pg_transaction_cleaned!$O:$O,A178,pg_transaction_cleaned!$F:$F,"REFUND") -> 0 | M178: =SUMIFS(pg_transaction_cleaned!$H:$H,pg_transaction_cleaned!$O:$O,A178,pg_transaction_cleaned!$F:$F,"REFUND") -> 0 | N178: =IF(AND(G178="Paid",J178=0),"Paid, no payment",IF(AND(OR(G178="Failed",G178="Cancelled"),J178>0),"Payment on failed/cancelled",IF(J178>1,"Duplicate charge",IF(AND(J178=1,ROUND(K178-H178,2)<>0),"Amount difference",IF(AND(G178="Refunded",L178=0),"Refunded, no refund",IF(AND(G178<>"Refunded",L178>0),"Refund, order not Refunded",IF(AND(L178>0,ROUND(M178-H178,2)<>0),"Refund amount differs","OK"))))))) -> OK | O178: =IF(N178="OK",0,IF(N178="Paid, no payment",H178,IF(N178="Payment on failed/cancelled",K178,IF(OR(N178="Duplicate charge",N178="Amount difference"),K178-H178,IF(N178="Refunded, no refund",H178,M178))))) -> 0
A179: ORD26000178 | B179: 46287 | C179: CUST17936 | D179: Kolkata | E179: Card | F179: 1799.0 | G179: Failed | H179: =VALUE(SUBSTITUTE(F179,",","")) -> 1799 | I179: =IF(TRIM(D179)="","Unknown",TRIM(D179)) -> Kolkata | J179: =COUNTIFS(pg_transaction_cleaned!$O:$O,A179,pg_transaction_cleaned!$F:$F,"CAPTURE") -> 0 | K179: =SUMIFS(pg_transaction_cleaned!$H:$H,pg_transaction_cleaned!$O:$O,A179,pg_transaction_cleaned!$F:$F,"CAPTURE") -> 0 | L179: =COUNTIFS(pg_transaction_cleaned!$O:$O,A179,pg_transaction_cleaned!$F:$F,"REFUND") -> 0 | M179: =SUMIFS(pg_transaction_cleaned!$H:$H,pg_transaction_cleaned!$O:$O,A179,pg_transaction_cleaned!$F:$F,"REFUND") -> 0 | N179: =IF(AND(G179="Paid",J179=0),"Paid, no payment",IF(AND(OR(G179="Failed",G179="Cancelled"),J179>0),"Payment on failed/cancelled",IF(J179>1,"Duplicate charge",IF(AND(J179=1,ROUND(K179-H179,2)<>0),"Amount difference",IF(AND(G179="Refunded",L179=0),"Refunded, no refund",IF(AND(G179<>"Refunded",L179>0),"Refund, order not Refunded",IF(AND(L179>0,ROUND(M179-H179,2)<>0),"Refund amount differs","OK"))))))) -> OK | O179: =IF(N179="OK",0,IF(N179="Paid, no payment",H179,IF(N179="Payment on failed/cancelled",K179,IF(OR(N179="Duplicate charge",N179="Amount difference"),K179-H179,IF(N179="Refunded, no refund",H179,M179))))) -> 0
A180: ORD26000179 | B180: 46274 | C180: CUST22015 | D180: Bengaluru | E180: NetBanking | F180: 349.0 | G180: Cancelled | H180: =VALUE(SUBSTITUTE(F180,",","")) -> 349 | I180: =IF(TRIM(D180)="","Unknown",TRIM(D180)) -> Bengaluru | J180: =COUNTIFS(pg_transaction_cleaned!$O:$O,A180,pg_transaction_cleaned!$F:$F,"CAPTURE") -> 0 | K180: =SUMIFS(pg_transaction_cleaned!$H:$H,pg_transaction_cleaned!$O:$O,A180,pg_transaction_cleaned!$F:$F,"CAPTURE") -> 0 | L180: =COUNTIFS(pg_transaction_cleaned!$O:$O,A180,pg_transaction_cleaned!$F:$F,"REFUND") -> 0 | M180: =SUMIFS(pg_transaction_cleaned!$H:$H,pg_transaction_cleaned!$O:$O,A180,pg_transaction_cleaned!$F:$F,"REFUND") -> 0 | N180: =IF(AND(G180="Paid",J180=0),"Paid, no payment",IF(AND(OR(G180="Failed",G180="Cancelled"),J180>0),"Payment on failed/cancelled",IF(J180>1,"Duplicate charge",IF(AND(J180=1,ROUND(K180-H180,2)<>0),"Amount difference",IF(AND(G180="Refunded",L180=0),"Refunded, no refund",IF(AND(G180<>"Refunded",L180>0),"Refund, order not Refunded",IF(AND(L180>0,ROUND(M180-H180,2)<>0),"Refund amount differs","OK"))))))) -> OK | O180: =IF(N180="OK",0,IF(N180="Paid, no payment",H180,IF(N180="Payment on failed/cancelled",K180,IF(OR(N180="Duplicate charge",N180="Amount difference"),K180-H180,IF(N180="Refunded, no refund",H180,M180))))) -> 0
A181: ORD26000180 | B181: 46286 | C181: CUST26505 | E181: UPI | F181: 3097.0 | G181: Paid | H181: =VALUE(SUBSTITUTE(F181,",","")) -> 3097 | I181: =IF(TRIM(D181)="","Unknown",TRIM(D181)) -> Unknown | J181: =COUNTIFS(pg_transaction_cleaned!$O:$O,A181,pg_transaction_cleaned!$F:$F,"CAPTURE") -> 1 | K181: =SUMIFS(pg_transaction_cleaned!$H:$H,pg_transaction_cleaned!$O:$O,A181,pg_transaction_cleaned!$F:$F,"CAPTURE") -> 3097 | L181: =COUNTIFS(pg_transaction_cleaned!$O:$O,A181,pg_transaction_cleaned!$F:$F,"REFUND") -> 0 | M181: =SUMIFS(pg_transaction_cleaned!$H:$H,pg_transaction_cleaned!$O:$O,A181,pg_transaction_cleaned!$F:$F,"REFUND") -> 0 | N181: =IF(AND(G181="Paid",J181=0),"Paid, no payment",IF(AND(OR(G181="Failed",G181="Cancelled"),J181>0),"Payment on failed/cancelled",IF(J181>1,"Duplicate charge",IF(AND(J181=1,ROUND(K181-H181,2)<>0),"Amount difference",IF(AND(G181="Refunded",L181=0),"Refunded, no refund",IF(AND(G181<>"Refunded",L181>0),"Refund, order not Refunded",IF(AND(L181>0,ROUND(M181-H181,2)<>0),"Refund amount differs","OK"))))))) -> OK | O181: =IF(N181="OK",0,IF(N181="Paid, no payment",H181,IF(N181="Payment on failed/cancelled",K181,IF(OR(N181="Duplicate charge",N181="Amount difference"),K181-H181,IF(N181="Refunded, no refund",H181,M181))))) -> 0
A182: ORD26000181 | B182: 46272 | C182: CUST38305 | D182: Bengaluru | E182: UPI | F182: 7999.0 | G182: Paid | H182: =VALUE(SUBSTITUTE(F182,",","")) -> 7999 | I182: =IF(TRIM(D182)="","Unknown",TRIM(D182)) -> Bengaluru | J182: =COUNTIFS(pg_transaction_cleaned!$O:$O,A182,pg_transaction_cleaned!$F:$F,"CAPTURE") -> 1 | K182: =SUMIFS(pg_transaction_cleaned!$H:$H,pg_transaction_cleaned!$O:$O,A182,pg_transaction_cleaned!$F:$F,"CAPTURE") -> 7999 | L182: =COUNTIFS(pg_transaction_cleaned!$O:$O,A182,pg_transaction_cleaned!$F:$F,"REFUND") -> 0 | M182: =SUMIFS(pg_transaction_cleaned!$H:$H,pg_transaction_cleaned!$O:$O,A182,pg_transaction_cleaned!$F:$F,"REFUND") -> 0 | N182: =IF(AND(G182="Paid",J182=0),"Paid, no payment",IF(AND(OR(G182="Failed",G182="Cancelled"),J182>0),"Payment on failed/cancelled",IF(J182>1,"Duplicate charge",IF(AND(J182=1,ROUND(K182-H182,2)<>0),"Amount difference",IF(AND(G182="Refunded",L182=0),"Refunded, no refund",IF(AND(G182<>"Refunded",L182>0),"Refund, order not Refunded",IF(AND(L182>0,ROUND(M182-H182,2)<>0),"Refund amount differs","OK"))))))) -> OK | O182: =IF(N182="OK",0,IF(N182="Paid, no payment",H182,IF(N182="Payment on failed/cancelled",K182,IF(OR(N182="Duplicate charge",N182="Amount difference"),K182-H182,IF(N182="Refunded, no refund",H182,M182))))) -> 0
A183: ORD26000182 | B183: 46276 | C183: CUST28964 | D183: Delhi | E183: UPI | F183: 4999.0 | G183: Failed | H183: =VALUE(SUBSTITUTE(F183,",","")) -> 4999 | I183: =IF(TRIM(D183)="","Unknown",TRIM(D183)) -> Delhi | J183: =COUNTIFS(pg_transaction_cleaned!$O:$O,A183,pg_transaction_cleaned!$F:$F,"CAPTURE") -> 0 | K183: =SUMIFS(pg_transaction_cleaned!$H:$H,pg_transaction_cleaned!$O:$O,A183,pg_transaction_cleaned!$F:$F,"CAPTURE") -> 0 | L183: =COUNTIFS(pg_transaction_cleaned!$O:$O,A183,pg_transaction_cleaned!$F:$F,"REFUND") -> 0 | M183: =SUMIFS(pg_transaction_cleaned!$H:$H,pg_transaction_cleaned!$O:$O,A183,pg_transaction_cleaned!$F:$F,"REFUND") -> 0 | N183: =IF(AND(G183="Paid",J183=0),"Paid, no payment",IF(AND(OR(G183="Failed",G183="Cancelled"),J183>0),"Payment on failed/cancelled",IF(J183>1,"Duplicate charge",IF(AND(J183=1,ROUND(K183-H183,2)<>0),"Amount difference",IF(AND(G183="Refunded",L183=0),"Refunded, no refund",IF(AND(G183<>"Refunded",L183>0),"Refund, order not Refunded",IF(AND(L183>0,ROUND(M183-H183,2)<>0),"Refund amount differs","OK"))))))) -> OK | O183: =IF(N183="OK",0,IF(N183="Paid, no payment",H183,IF(N183="Payment on failed/cancelled",K183,IF(OR(N183="Duplicate charge",N183="Amount difference"),K183-H183,IF(N183="Refunded, no refund",H183,M183))))) -> 0
A184: ORD26000183 | B184: 46283 | C184: CUST13379 | D184: Delhi | E184: Card | F184: 4999.0 | G184: Paid | H184: =VALUE(SUBSTITUTE(F184,",","")) -> 4999 | I184: =IF(TRIM(D184)="","Unknown",TRIM(D184)) -> Delhi | J184: =COUNTIFS(pg_transaction_cleaned!$O:$O,A184,pg_transaction_cleaned!$F:$F,"CAPTURE") -> 1 | K184: =SUMIFS(pg_transaction_cleaned!$H:$H,pg_transaction_cleaned!$O:$O,A184,pg_transaction_cleaned!$F:$F,"CAPTURE") -> 4999 | L184: =COUNTIFS(pg_transaction_cleaned!$O:$O,A184,pg_transaction_cleaned!$F:$F,"REFUND") -> 0 | M184: =SUMIFS(pg_transaction_cleaned!$H:$H,pg_transaction_cleaned!$O:$O,A184,pg_transaction_cleaned!$F:$F,"REFUND") -> 0 | N184: =IF(AND(G184="Paid",J184=0),"Paid, no payment",IF(AND(OR(G184="Failed",G184="Cancelled"),J184>0),"Payment on failed/cancelled",IF(J184>1,"Duplicate charge",IF(AND(J184=1,ROUND(K184-H184,2)<>0),"Amount difference",IF(AND(G184="Refunded",L184=0),"Refunded, no refund",IF(AND(G184<>"Refunded",L184>0),"Refund, order not Refunded",IF(AND(L184>0,ROUND(M184-H184,2)<>0),"Refund amount differs","OK"))))))) -> OK | O184: =IF(N184="OK",0,IF(N184="Paid, no payment",H184,IF(N184="Payment on failed/cancelled",K184,IF(OR(N184="Duplicate charge",N184="Amount difference"),K184-H184,IF(N184="Refunded, no refund",H184,M184))))) -> 0
A185: ORD26000184 | B185: 46266 | C185: CUST12068 | D185: Delhi | E185: Card | F185: 4999.0 | G185: Paid | H185: =VALUE(SUBSTITUTE(F185,",","")) -> 4999 | I185: =IF(TRIM(D185)="","Unknown",TRIM(D185)) -> Delhi | J185: =COUNTIFS(pg_transaction_cleaned!$O:$O,A185,pg_transaction_cleaned!$F:$F,"CAPTURE") -> 1 | K185: =SUMIFS(pg_transaction_cleaned!$H:$H,pg_transaction_cleaned!$O:$O,A185,pg_transaction_cleaned!$F:$F,"CAPTURE") -> 4999 | L185: =COUNTIFS(pg_transaction_cleaned!$O:$O,A185,pg_transaction_cleaned!$F:$F,"REFUND") -> 0 | M185: =SUMIFS(pg_transaction_cleaned!$H:$H,pg_transaction_cleaned!$O:$O,A185,pg_transaction_cleaned!$F:$F,"REFUND") -> 0 | N185: =IF(AND(G185="Paid",J185=0),"Paid, no payment",IF(AND(OR(G185="Failed",G185="Cancelled"),J185>0),"Payment on failed/cancelled",IF(J185>1,"Duplicate charge",IF(AND(J185=1,ROUND(K185-H185,2)<>0),"Amount difference",IF(AND(G185="Refunded",L185=0),"Refunded, no refund",IF(AND(G185<>"Refunded",L185>0),"Refund, order not Refunded",IF(AND(L185>0,ROUND(M185-H185,2)<>0),"Refund amount differs","OK"))))))) -> OK | O185: =IF(N185="OK",0,IF(N185="Paid, no payment",H185,IF(N185="Payment on failed/cancelled",K185,IF(OR(N185="Duplicate charge",N185="Amount difference"),K185-H185,IF(N185="Refunded, no refund",H185,M185))))) -> 0
A186: ORD26000185 | B186: 46274 | C186: CUST18330 | D186: Ahmedabad | E186: UPI | F186: 499.0 | G186: Paid | H186: =VALUE(SUBSTITUTE(F186,",","")) -> 499 | I186: =IF(TRIM(D186)="","Unknown",TRIM(D186)) -> Ahmedabad | J186: =COUNTIFS(pg_transaction_cleaned!$O:$O,A186,pg_transaction_cleaned!$F:$F,"CAPTURE") -> 1 | K186: =SUMIFS(pg_transaction_cleaned!$H:$H,pg_transaction_cleaned!$O:$O,A186,pg_transaction_cleaned!$F:$F,"CAPTURE") -> 499 | L186: =COUNTIFS(pg_transaction_cleaned!$O:$O,A186,pg_transaction_cleaned!$F:$F,"REFUND") -> 0 | M186: =SUMIFS(pg_transaction_cleaned!$H:$H,pg_transaction_cleaned!$O:$O,A186,pg_transaction_cleaned!$F:$F,"REFUND") -> 0 | N186: =IF(AND(G186="Paid",J186=0),"Paid, no payment",IF(AND(OR(G186="Failed",G186="Cancelled"),J186>0),"Payment on failed/cancelled",IF(J186>1,"Duplicate charge",IF(AND(J186=1,ROUND(K186-H186,2)<>0),"Amount difference",IF(AND(G186="Refunded",L186=0),"Refunded, no refund",IF(AND(G186<>"Refunded",L186>0),"Refund, order not Refunded",IF(AND(L186>0,ROUND(M186-H186,2)<>0),"Refund amount differs","OK"))))))) -> OK | O186: =IF(N186="OK",0,IF(N186="Paid, no payment",H186,IF(N186="Payment on failed/cancelled",K186,IF(OR(N186="Duplicate charge",N186="Amount difference"),K186-H186,IF(N186="Refunded, no refund",H186,M186))))) -> 0
A187: ORD26000186 | B187: 46280 | C187: CUST39038 | D187: Lucknow | E187: UPI | F187: 1799.0 | G187: Paid | H187: =VALUE(SUBSTITUTE(F187,",","")) -> 1799 | I187: =IF(TRIM(D187)="","Unknown",TRIM(D187)) -> Lucknow | J187: =COUNTIFS(pg_transaction_cleaned!$O:$O,A187,pg_transaction_cleaned!$F:$F,"CAPTURE") -> 1 | K187: =SUMIFS(pg_transaction_cleaned!$H:$H,pg_transaction_cleaned!$O:$O,A187,pg_transaction_cleaned!$F:$F,"CAPTURE") -> 1799 | L187: =COUNTIFS(pg_transaction_cleaned!$O:$O,A187,pg_transaction_cleaned!$F:$F,"REFUND") -> 0 | M187: =SUMIFS(pg_transaction_cleaned!$H:$H,pg_transaction_cleaned!$O:$O,A187,pg_transaction_cleaned!$F:$F,"REFUND") -> 0 | N187: =IF(AND(G187="Paid",J187=0),"Paid, no payment",IF(AND(OR(G187="Failed",G187="Cancelled"),J187>0),"Payment on failed/cancelled",IF(J187>1,"Duplicate charge",IF(AND(J187=1,ROUND(K187-H187,2)<>0),"Amount difference",IF(AND(G187="Refunded",L187=0),"Refunded, no refund",IF(AND(G187<>"Refunded",L187>0),"Refund, order not Refunded",IF(AND(L187>0,ROUND(M187-H187,2)<>0),"Refund amount differs","OK"))))))) -> OK | O187: =IF(N187="OK",0,IF(N187="Paid, no payment",H187,IF(N187="Payment on failed/cancelled",K187,IF(OR(N187="Duplicate charge",N187="Amount difference"),K187-H187,IF(N187="Refunded, no refund",H187,M187))))) -> 0
A188: ORD26000187 | B188: 46267 | C188: CUST14082 | D188: Mumbai | E188: UPI | F188: 15997.0 | G188: Paid | H188: =VALUE(SUBSTITUTE(F188,",","")) -> 15997 | I188: =IF(TRIM(D188)="","Unknown",TRIM(D188)) -> Mumbai | J188: =COUNTIFS(pg_transaction_cleaned!$O:$O,A188,pg_transaction_cleaned!$F:$F,"CAPTURE") -> 1 | K188: =SUMIFS(pg_transaction_cleaned!$H:$H,pg_transaction_cleaned!$O:$O,A188,pg_transaction_cleaned!$F:$F,"CAPTURE") -> 15997 | L188: =COUNTIFS(pg_transaction_cleaned!$O:$O,A188,pg_transaction_cleaned!$F:$F,"REFUND") -> 0 | M188: =SUMIFS(pg_transaction_cleaned!$H:$H,pg_transaction_cleaned!$O:$O,A188,pg_transaction_cleaned!$F:$F,"REFUND") -> 0 | N188: =IF(AND(G188="Paid",J188=0),"Paid, no payment",IF(AND(OR(G188="Failed",G188="Cancelled"),J188>0),"Payment on failed/cancelled",IF(J188>1,"Duplicate charge",IF(AND(J188=1,ROUND(K188-H188,2)<>0),"Amount difference",IF(AND(G188="Refunded",L188=0),"Refunded, no refund",IF(AND(G188<>"Refunded",L188>0),"Refund, order not Refunded",IF(AND(L188>0,ROUND(M188-H188,2)<>0),"Refund amount differs","OK"))))))) -> OK | O188: =IF(N188="OK",0,IF(N188="Paid, no payment",H188,IF(N188="Payment on failed/cancelled",K188,IF(OR(N188="Duplicate charge",N188="Amount difference"),K188-H188,IF(N188="Refunded, no refund",H188,M188))))) -> 0
A189: ORD26000188 | B189: 46281 | C189: CUST68138 | D189: Pune | E189: Card | F189: 4,298.00 | G189: Paid | H189: =VALUE(SUBSTITUTE(F189,",","")) -> 4298 | I189: =IF(TRIM(D189)="","Unknown",TRIM(D189)) -> Pune | J189: =COUNTIFS(pg_transaction_cleaned!$O:$O,A189,pg_transaction_cleaned!$F:$F,"CAPTURE") -> 1 | K189: =SUMIFS(pg_transaction_cleaned!$H:$H,pg_transaction_cleaned!$O:$O,A189,pg_transaction_cleaned!$F:$F,"CAPTURE") -> 4298 | L189: =COUNTIFS(pg_transaction_cleaned!$O:$O,A189,pg_transaction_cleaned!$F:$F,"REFUND") -> 0 | M189: =SUMIFS(pg_transaction_cleaned!$H:$H,pg_transaction_cleaned!$O:$O,A189,pg_transaction_cleaned!$F:$F,"REFUND") -> 0 | N189: =IF(AND(G189="Paid",J189=0),"Paid, no payment",IF(AND(OR(G189="Failed",G189="Cancelled"),J189>0),"Payment on failed/cancelled",IF(J189>1,"Duplicate charge",IF(AND(J189=1,ROUND(K189-H189,2)<>0),"Amount difference",IF(AND(G189="Refunded",L189=0),"Refunded, no refund",IF(AND(G189<>"Refunded",L189>0),"Refund, order not Refunded",IF(AND(L189>0,ROUND(M189-H189,2)<>0),"Refund amount differs","OK"))))))) -> OK | O189: =IF(N189="OK",0,IF(N189="Paid, no payment",H189,IF(N189="Payment on failed/cancelled",K189,IF(OR(N189="Duplicate charge",N189="Amount difference"),K189-H189,IF(N189="Refunded, no refund",H189,M189))))) -> 0
A190: ORD26000189 | B190: 46294 | C190: CUST46046 | D190: Lucknow | E190: UPI | F190: 999.0 | G190: Paid | H190: =VALUE(SUBSTITUTE(F190,",","")) -> 999 | I190: =IF(TRIM(D190)="","Unknown",TRIM(D190)) -> Lucknow | J190: =COUNTIFS(pg_transaction_cleaned!$O:$O,A190,pg_transaction_cleaned!$F:$F,"CAPTURE") -> 1 | K190: =SUMIFS(pg_transaction_cleaned!$H:$H,pg_transaction_cleaned!$O:$O,A190,pg_transaction_cleaned!$F:$F,"CAPTURE") -> 999 | L190: =COUNTIFS(pg_transaction_cleaned!$O:$O,A190,pg_transaction_cleaned!$F:$F,"REFUND") -> 0 | M190: =SUMIFS(pg_transaction_cleaned!$H:$H,pg_transaction_cleaned!$O:$O,A190,pg_transaction_cleaned!$F:$F,"REFUND") -> 0 | N190: =IF(AND(G190="Paid",J190=0),"Paid, no payment",IF(AND(OR(G190="Failed",G190="Cancelled"),J190>0),"Payment on failed/cancelled",IF(J190>1,"Duplicate charge",IF(AND(J190=1,ROUND(K190-H190,2)<>0),"Amount difference",IF(AND(G190="Refunded",L190=0),"Refunded, no refund",IF(AND(G190<>"Refunded",L190>0),"Refund, order not Refunded",IF(AND(L190>0,ROUND(M190-H190,2)<>0),"Refund amount differs","OK"))))))) -> OK | O190: =IF(N190="OK",0,IF(N190="Paid, no payment",H190,IF(N190="Payment on failed/cancelled",K190,IF(OR(N190="Duplicate charge",N190="Amount difference"),K190-H190,IF(N190="Refunded, no refund",H190,M190))))) -> 0
A191: ORD26000190 | B191: 46286 | C191: CUST79541 | D191: Hyderabad | E191: Wallet | F191: 5298.0 | G191: Paid | H191: =VALUE(SUBSTITUTE(F191,",","")) -> 5298 | I191: =IF(TRIM(D191)="","Unknown",TRIM(D191)) -> Hyderabad | J191: =COUNTIFS(pg_transaction_cleaned!$O:$O,A191,pg_transaction_cleaned!$F:$F,"CAPTURE") -> 1 | K191: =SUMIFS(pg_transaction_cleaned!$H:$H,pg_transaction_cleaned!$O:$O,A191,pg_transaction_cleaned!$F:$F,"CAPTURE") -> 5298 | L191: =COUNTIFS(pg_transaction_cleaned!$O:$O,A191,pg_transaction_cleaned!$F:$F,"REFUND") -> 0 | M191: =SUMIFS(pg_transaction_cleaned!$H:$H,pg_transaction_cleaned!$O:$O,A191,pg_transaction_cleaned!$F:$F,"REFUND") -> 0 | N191: =IF(AND(G191="Paid",J191=0),"Paid, no payment",IF(AND(OR(G191="Failed",G191="Cancelled"),J191>0),"Payment on failed/cancelled",IF(J191>1,"Duplicate charge",IF(AND(J191=1,ROUND(K191-H191,2)<>0),"Amount difference",IF(AND(G191="Refunded",L191=0),"Refunded, no refund",IF(AND(G191<>"Refunded",L191>0),"Refund, order not Refunded",IF(AND(L191>0,ROUND(M191-H191,2)<>0),"Refund amount differs","OK"))))))) -> OK | O191: =IF(N191="OK",0,IF(N191="Paid, no payment",H191,IF(N191="Payment on failed/cancelled",K191,IF(OR(N191="Duplicate charge",N191="Amount difference"),K191-H191,IF(N191="Refunded, no refund",H191,M191))))) -> 0
A192: ORD26000191 | B192: 46280 | C192: CUST95814 | D192: Jaipur | E192: Card | F192: 3798.0 | G192: Paid | H192: =VALUE(SUBSTITUTE(F192,",","")) -> 3798 | I192: =IF(TRIM(D192)="","Unknown",TRIM(D192)) -> Jaipur | J192: =COUNTIFS(pg_transaction_cleaned!$O:$O,A192,pg_transaction_cleaned!$F:$F,"CAPTURE") -> 1 | K192: =SUMIFS(pg_transaction_cleaned!$H:$H,pg_transaction_cleaned!$O:$O,A192,pg_transaction_cleaned!$F:$F,"CAPTURE") -> 3798 | L192: =COUNTIFS(pg_transaction_cleaned!$O:$O,A192,pg_transaction_cleaned!$F:$F,"REFUND") -> 0 | M192: =SUMIFS(pg_transaction_cleaned!$H:$H,pg_transaction_cleaned!$O:$O,A192,pg_transaction_cleaned!$F:$F,"REFUND") -> 0 | N192: =IF(AND(G192="Paid",J192=0),"Paid, no payment",IF(AND(OR(G192="Failed",G192="Cancelled"),J192>0),"Payment on failed/cancelled",IF(J192>1,"Duplicate charge",IF(AND(J192=1,ROUND(K192-H192,2)<>0),"Amount difference",IF(AND(G192="Refunded",L192=0),"Refunded, no refund",IF(AND(G192<>"Refunded",L192>0),"Refund, order not Refunded",IF(AND(L192>0,ROUND(M192-H192,2)<>0),"Refund amount differs","OK"))))))) -> OK | O192: =IF(N192="OK",0,IF(N192="Paid, no payment",H192,IF(N192="Payment on failed/cancelled",K192,IF(OR(N192="Duplicate charge",N192="Amount difference"),K192-H192,IF(N192="Refunded, no refund",H192,M192))))) -> 0
A193: ORD26000192 | B193: 46289 | C193: CUST54424 | D193: Ahmedabad | E193: UPI | F193: 1299.0 | G193: Paid | H193: =VALUE(SUBSTITUTE(F193,",","")) -> 1299 | I193: =IF(TRIM(D193)="","Unknown",TRIM(D193)) -> Ahmedabad | J193: =COUNTIFS(pg_transaction_cleaned!$O:$O,A193,pg_transaction_cleaned!$F:$F,"CAPTURE") -> 1 | K193: =SUMIFS(pg_transaction_cleaned!$H:$H,pg_transaction_cleaned!$O:$O,A193,pg_transaction_cleaned!$F:$F,"CAPTURE") -> 1299 | L193: =COUNTIFS(pg_transaction_cleaned!$O:$O,A193,pg_transaction_cleaned!$F:$F,"REFUND") -> 0 | M193: =SUMIFS(pg_transaction_cleaned!$H:$H,pg_transaction_cleaned!$O:$O,A193,pg_transaction_cleaned!$F:$F,"REFUND") -> 0 | N193: =IF(AND(G193="Paid",J193=0),"Paid, no payment",IF(AND(OR(G193="Failed",G193="Cancelled"),J193>0),"Payment on failed/cancelled",IF(J193>1,"Duplicate charge",IF(AND(J193=1,ROUND(K193-H193,2)<>0),"Amount difference",IF(AND(G193="Refunded",L193=0),"Refunded, no refund",IF(AND(G193<>"Refunded",L193>0),"Refund, order not Refunded",IF(AND(L193>0,ROUND(M193-H193,2)<>0),"Refund amount differs","OK"))))))) -> OK | O193: =IF(N193="OK",0,IF(N193="Paid, no payment",H193,IF(N193="Payment on failed/cancelled",K193,IF(OR(N193="Duplicate charge",N193="Amount difference"),K193-H193,IF(N193="Refunded, no refund",H193,M193))))) -> 0
... A235: ORD26000234 | B235: 46282 | C235: CUST54140 | D235: Lucknow | E235: UPI | F235: 11498.0 | G235: Failed | H235: =VALUE(SUBSTITUTE(F235,",","")) -> 11498 | I235: =IF(TRIM(D235)="","Unknown",TRIM(D235)) -> Lucknow | J235: =COUNTIFS(pg_transaction_cleaned!$O:$O,A235,pg_transaction_cleaned!$F:$F,"CAPTURE") -> 0 | K235: =SUMIFS(pg_transaction_cleaned!$H:$H,pg_transaction_cleaned!$O:$O,A235,pg_transaction_cleaned!$F:$F,"CAPTURE") -> 0 | L235: =COUNTIFS(pg_transaction_cleaned!$O:$O,A235,pg_transaction_cleaned!$F:$F,"REFUND") -> 0 | M235: =SUMIFS(pg_transaction_cleaned!$H:$H,pg_transaction_cleaned!$O:$O,A235,pg_transaction_cleaned!$F:$F,"REFUND") -> 0 | N235: =IF(AND(G235="Paid",J235=0),"Paid, no payment",IF(AND(OR(G235="Failed",G235="Cancelled"),J235>0),"Payment on failed/cancelled",IF(J235>1,"Duplicate charge",IF(AND(J235=1,ROUND(K235-H235,2)<>0),"Amount difference",IF(AND(G235="Refunded",L235=0),"Refunded, no refund",IF(AND(G235<>"Refunded",L235>0),"Refund, order not Refunded",IF(AND(L235>0,ROUND(M235-H235,2)<>0),"Refund amount differs","OK"))))))) -> OK | O235: =IF(N235="OK",0,IF(N235="Paid, no payment",H235,IF(N235="Payment on failed/cancelled",K235,IF(OR(N235="Duplicate charge",N235="Amount difference"),K235-H235,IF(N235="Refunded, no refund",H235,M235))))) -> 0
A236: ORD26000235 | B236: 46270 | C236: CUST91885 | E236: NetBanking | F236: 1798.0 | G236: Paid | H236: =VALUE(SUBSTITUTE(F236,",","")) -> 1798 | I236: =IF(TRIM(D236)="","Unknown",TRIM(D236)) -> Unknown | J236: =COUNTIFS(pg_transaction_cleaned!$O:$O,A236,pg_transaction_cleaned!$F:$F,"CAPTURE") -> 1 | K236: =SUMIFS(pg_transaction_cleaned!$H:$H,pg_transaction_cleaned!$O:$O,A236,pg_transaction_cleaned!$F:$F,"CAPTURE") -> 1798 | L236: =COUNTIFS(pg_transaction_cleaned!$O:$O,A236,pg_transaction_cleaned!$F:$F,"REFUND") -> 0 | M236: =SUMIFS(pg_transaction_cleaned!$H:$H,pg_transaction_cleaned!$O:$O,A236,pg_transaction_cleaned!$F:$F,"REFUND") -> 0 | N236: =IF(AND(G236="Paid",J236=0),"Paid, no payment",IF(AND(OR(G236="Failed",G236="Cancelled"),J236>0),"Payment on failed/cancelled",IF(J236>1,"Duplicate charge",IF(AND(J236=1,ROUND(K236-H236,2)<>0),"Amount difference",IF(AND(G236="Refunded",L236=0),"Refunded, no refund",IF(AND(G236<>"Refunded",L236>0),"Refund, order not Refunded",IF(AND(L236>0,ROUND(M236-H236,2)<>0),"Refund amount differs","OK"))))))) -> OK | O236: =IF(N236="OK",0,IF(N236="Paid, no payment",H236,IF(N236="Payment on failed/cancelled",K236,IF(OR(N236="Duplicate charge",N236="Amount difference"),K236-H236,IF(N236="Refunded, no refund",H236,M236))))) -> 0
A237: ORD26000236 | B237: 46289 | C237: CUST68222 | D237: Lucknow | E237: Card | F237: 1598.0 | G237: Paid | H237: =VALUE(SUBSTITUTE(F237,",","")) -> 1598 | I237: =IF(TRIM(D237)="","Unknown",TRIM(D237)) -> Lucknow | J237: =COUNTIFS(pg_transaction_cleaned!$O:$O,A237,pg_transaction_cleaned!$F:$F,"CAPTURE") -> 1 | K237: =SUMIFS(pg_transaction_cleaned!$H:$H,pg_transaction_cleaned!$O:$O,A237,pg_transaction_cleaned!$F:$F,"CAPTURE") -> 1598 | L237: =COUNTIFS(pg_transaction_cleaned!$O:$O,A237,pg_transaction_cleaned!$F:$F,"REFUND") -> 0 | M237: =SUMIFS(pg_transaction_cleaned!$H:$H,pg_transaction_cleaned!$O:$O,A237,pg_transaction_cleaned!$F:$F,"REFUND") -> 0 | N237: =IF(AND(G237="Paid",J237=0),"Paid, no payment",IF(AND(OR(G237="Failed",G237="Cancelled"),J237>0),"Payment on failed/cancelled",IF(J237>1,"Duplicate charge",IF(AND(J237=1,ROUND(K237-H237,2)<>0),"Amount difference",IF(AND(G237="Refunded",L237=0),"Refunded, no refund",IF(AND(G237<>"Refunded",L237>0),"Refund, order not Refunded",IF(AND(L237>0,ROUND(M237-H237,2)<>0),"Refund amount differs","OK"))))))) -> OK | O237: =IF(N237="OK",0,IF(N237="Paid, no payment",H237,IF(N237="Payment on failed/cancelled",K237,IF(OR(N237="Duplicate charge",N237="Amount difference"),K237-H237,IF(N237="Refunded, no refund",H237,M237))))) -> 0
A238: ORD26000237 | B238: 46275 | C238: CUST71474 | D238: Bengaluru | E238: UPI | F238: 7097.0 | G238: Paid | H238: =VALUE(SUBSTITUTE(F238,",","")) -> 7097 | I238: =IF(TRIM(D238)="","Unknown",TRIM(D238)) -> Bengaluru | J238: =COUNTIFS(pg_transaction_cleaned!$O:$O,A238,pg_transaction_cleaned!$F:$F,"CAPTURE") -> 1 | K238: =SUMIFS(pg_transaction_cleaned!$H:$H,pg_transaction_cleaned!$O:$O,A238,pg_transaction_cleaned!$F:$F,"CAPTURE") -> 7097 | L238: =COUNTIFS(pg_transaction_cleaned!$O:$O,A238,pg_transaction_cleaned!$F:$F,"REFUND") -> 0 | M238: =SUMIFS(pg_transaction_cleaned!$H:$H,pg_transaction_cleaned!$O:$O,A238,pg_transaction_cleaned!$F:$F,"REFUND") -> 0 | N238: =IF(AND(G238="Paid",J238=0),"Paid, no payment",IF(AND(OR(G238="Failed",G238="Cancelled"),J238>0),"Payment on failed/cancelled",IF(J238>1,"Duplicate charge",IF(AND(J238=1,ROUND(K238-H238,2)<>0),"Amount difference",IF(AND(G238="Refunded",L238=0),"Refunded, no refund",IF(AND(G238<>"Refunded",L238>0),"Refund, order not Refunded",IF(AND(L238>0,ROUND(M238-H238,2)<>0),"Refund amount differs","OK"))))))) -> OK | O238: =IF(N238="OK",0,IF(N238="Paid, no payment",H238,IF(N238="Payment on failed/cancelled",K238,IF(OR(N238="Duplicate charge",N238="Amount difference"),K238-H238,IF(N238="Refunded, no refund",H238,M238))))) -> 0
A239: ORD26000238 | B239: 46277 | C239: CUST75916 | D239: Jaipur | E239: Card | F239: 5497.0 | G239: Paid | H239: =VALUE(SUBSTITUTE(F239,",","")) -> 5497 | I239: =IF(TRIM(D239)="","Unknown",TRIM(D239)) -> Jaipur | J239: =COUNTIFS(pg_transaction_cleaned!$O:$O,A239,pg_transaction_cleaned!$F:$F,"CAPTURE") -> 1 | K239: =SUMIFS(pg_transaction_cleaned!$H:$H,pg_transaction_cleaned!$O:$O,A239,pg_transaction_cleaned!$F:$F,"CAPTURE") -> 5497 | L239: =COUNTIFS(pg_transaction_cleaned!$O:$O,A239,pg_transaction_cleaned!$F:$F,"REFUND") -> 0 | M239: =SUMIFS(pg_transaction_cleaned!$H:$H,pg_transaction_cleaned!$O:$O,A239,pg_transaction_cleaned!$F:$F,"REFUND") -> 0 | N239: =IF(AND(G239="Paid",J239=0),"Paid, no payment",IF(AND(OR(G239="Failed",G239="Cancelled"),J239>0),"Payment on failed/cancelled",IF(J239>1,"Duplicate charge",IF(AND(J239=1,ROUND(K239-H239,2)<>0),"Amount difference",IF(AND(G239="Refunded",L239=0),"Refunded, no refund",IF(AND(G239<>"Refunded",L239>0),"Refund, order not Refunded",IF(AND(L239>0,ROUND(M239-H239,2)<>0),"Refund amount differs","OK"))))))) -> OK | O239: =IF(N239="OK",0,IF(N239="Paid, no payment",H239,IF(N239="Payment on failed/cancelled",K239,IF(OR(N239="Duplicate charge",N239="Amount difference"),K239-H239,IF(N239="Refunded, no refund",H239,M239))))) -> 0
...

Sheet pg_transaction_cleaned
A1: pg_txn_id | B1: original_payment_id | C1: merchant_order_ref | D1: merchant_order_ref_cleaned | E1: txn_date | F1: txn_type | G1: payment_method | H1: gross_amount | I1: mdr_fee | J1: gst_on_fee | K1: net_amount | L1: settlement_date | M1: settlement_batch_id | N1: dup_flag | O1: order_key | P1: settlement_period | Q1: order_found
A2: pay_420000065 | C2: ORD26000066 | D2: =UPPER(SUBSTITUTE(TRIM(C2),"-","")) -> ORD26000066 | E2: 46266 | F2: CAPTURE | G2: Wallet | H2: 6798 | I2: 163.15 | J2: 29.37 | K2: 6605.48 | L2: 46268 | M2: STL-20260903 | N2: =IF(COUNTIF($A$2:A2,A2)>1,"DUP","OK") -> OK | O2: =IF(F2="REFUND",INDEX($D:$D,MATCH(B2,$A:$A,0)),D2) -> ORD26000066 | P2: =IF(L2>DATE(2026,9,30),"Oct-Due","Sep") -> Sep | Q2: =IF(F2="CAPTURE",IF(COUNTIF(orders!$A:$A,O2)>0,"Yes","NO ORDER"),"") -> Yes
A3: pay_420000121 | C3: ORD-26000130 | D3: =UPPER(SUBSTITUTE(TRIM(C3),"-","")) -> ORD26000130 | E3: 46266 | F3: CAPTURE | G3: Card | H3: 11297 | I3: 180.75 | J3: 32.54 | K3: 11083.71 | L3: 46268 | M3: STL-20260903 | N3: =IF(COUNTIF($A$2:A3,A3)>1,"DUP","OK") -> OK | O3: =IF(F3="REFUND",INDEX($D:$D,MATCH(B3,$A:$A,0)),D3) -> ORD26000130 | P3: =IF(L3>DATE(2026,9,30),"Oct-Due","Sep") -> Sep | Q3: =IF(F3="CAPTURE",IF(COUNTIF(orders!$A:$A,O3)>0,"Yes","NO ORDER"),"") -> Yes
A4: pay_420000170 | C4: ORD26000184 | D4: =UPPER(SUBSTITUTE(TRIM(C4),"-","")) -> ORD26000184 | E4: 46266 | F4: CAPTURE | G4: Card | H4: 4999 | I4: 79.98 | J4: 14.4 | K4: 4904.62 | L4: 46268 | M4: STL-20260903 | N4: =IF(COUNTIF($A$2:A4,A4)>1,"DUP","OK") -> OK | O4: =IF(F4="REFUND",INDEX($D:$D,MATCH(B4,$A:$A,0)),D4) -> ORD26000184 | P4: =IF(L4>DATE(2026,9,30),"Oct-Due","Sep") -> Sep | Q4: =IF(F4="CAPTURE",IF(COUNTIF(orders!$A:$A,O4)>0,"Yes","NO ORDER"),"") -> Yes
A5: pay_420000229 | C5: ORD26000244 | D5: =UPPER(SUBSTITUTE(TRIM(C5),"-","")) -> ORD26000244 | E5: 46266 | F5: CAPTURE | G5: Card | H5: 349 | I5: 6.28 | J5: 1.13 | K5: 341.59 | L5: 46268 | M5: STL-20260903 | N5: =IF(COUNTIF($A$2:A5,A5)>1,"DUP","OK") -> OK | O5: =IF(F5="REFUND",INDEX($D:$D,MATCH(B5,$A:$A,0)),D5) -> ORD26000244 | P5: =IF(L5>DATE(2026,9,30),"Oct-Due","Sep") -> Sep | Q5: =IF(F5="CAPTURE",IF(COUNTIF(orders!$A:$A,O5)>0,"Yes","NO ORDER"),"") -> Yes
A6: pay_420000236 | C6: ORD26000252 | D6: =UPPER(SUBSTITUTE(TRIM(C6),"-","")) -> ORD26000252 | E6: 46266 | F6: CAPTURE | G6: UPI | H6: 9498 | I6: 28.49 | J6: 5.13 | K6: 9464.38 | L6: 46268 | M6: STL-20260903 | N6: =IF(COUNTIF($A$2:A6,A6)>1,"DUP","OK") -> OK | O6: =IF(F6="REFUND",INDEX($D:$D,MATCH(B6,$A:$A,0)),D6) -> ORD26000252 | P6: =IF(L6>DATE(2026,9,30),"Oct-Due","Sep") -> Sep | Q6: =IF(F6="CAPTURE",IF(COUNTIF(orders!$A:$A,O6)>0,"Yes","NO ORDER"),"") -> Yes
A7: pay_420000249 | C7: ORD26000266 | D7: =UPPER(SUBSTITUTE(TRIM(C7),"-","")) -> ORD26000266 | E7: 46266 | F7: CAPTURE | G7: Card | H7: 7999 | I7: 127.98 | J7: 23.04 | K7: 7847.98 | L7: 46268 | M7: STL-20260903 | N7: =IF(COUNTIF($A$2:A7,A7)>1,"DUP","OK") -> OK | O7: =IF(F7="REFUND",INDEX($D:$D,MATCH(B7,$A:$A,0)),D7) -> ORD26000266 | P7: =IF(L7>DATE(2026,9,30),"Oct-Due","Sep") -> Sep | Q7: =IF(F7="CAPTURE",IF(COUNTIF(orders!$A:$A,O7)>0,"Yes","NO ORDER"),"") -> Yes
A8: pay_420000316 | C8: ORD26000331 | D8: =UPPER(SUBSTITUTE(TRIM(C8),"-","")) -> ORD26000331 | E8: 46266 | F8: CAPTURE | G8: Card | H8: 1299 | I8: 23.38 | J8: 4.21 | K8: 1271.41 | L8: 46268 | M8: STL-20260903 | N8: =IF(COUNTIF($A$2:A8,A8)>1,"DUP","OK") -> OK | O8: =IF(F8="REFUND",INDEX($D:$D,MATCH(B8,$A:$A,0)),D8) -> ORD26000331 | P8: =IF(L8>DATE(2026,9,30),"Oct-Due","Sep") -> Sep | Q8: =IF(F8="CAPTURE",IF(COUNTIF(orders!$A:$A,O8)>0,"Yes","NO ORDER"),"") -> Yes
A9: pay_420000355 | C9: ORD26000373 | D9: =UPPER(SUBSTITUTE(TRIM(C9),"-","")) -> ORD26000373 | E9: 46266 | F9: CAPTURE | G9: UPI | H9: 1799 | I9: 0 | J9: 0 | K9: 1799 | L9: 46268 | M9: STL-20260903 | N9: =IF(COUNTIF($A$2:A9,A9)>1,"DUP","OK") -> OK | O9: =IF(F9="REFUND",INDEX($D:$D,MATCH(B9,$A:$A,0)),D9) -> ORD26000373 | P9: =IF(L9>DATE(2026,9,30),"Oct-Due","Sep") -> Sep | Q9: =IF(F9="CAPTURE",IF(COUNTIF(orders!$A:$A,O9)>0,"Yes","NO ORDER"),"") -> Yes
A10: pay_420000357 | C10: ORD26000375 | D10: =UPPER(SUBSTITUTE(TRIM(C10),"-","")) -> ORD26000375 | E10: 46266 | F10: CAPTURE | G10: UPI | H10: 4298 | I10: 12.89 | J10: 2.32 | K10: 4282.79 | L10: 46268 | M10: STL-20260903 | N10: =IF(COUNTIF($A$2:A10,A10)>1,"DUP","OK") -> OK | O10: =IF(F10="REFUND",INDEX($D:$D,MATCH(B10,$A:$A,0)),D10) -> ORD26000375 | P10: =IF(L10>DATE(2026,9,30),"Oct-Due","Sep") -> Sep | Q10: =IF(F10="CAPTURE",IF(COUNTIF(orders!$A:$A,O10)>0,"Yes","NO ORDER"),"") -> Yes
A11: pay_420000392 | C11: ORD26000410 | D11: =UPPER(SUBSTITUTE(TRIM(C11),"-","")) -> ORD26000410 | E11: 46266 | F11: CAPTURE | G11: Card | H11: 799 | I11: 14.38 | J11: 2.59 | K11: 782.03 | L11: 46268 | M11: STL-20260903 | N11: =IF(COUNTIF($A$2:A11,A11)>1,"DUP","OK") -> OK | O11: =IF(F11="REFUND",INDEX($D:$D,MATCH(B11,$A:$A,0)),D11) -> ORD26000410 | P11: =IF(L11>DATE(2026,9,30),"Oct-Due","Sep") -> Sep | Q11: =IF(F11="CAPTURE",IF(COUNTIF(orders!$A:$A,O11)>0,"Yes","NO ORDER"),"") -> Yes
A12: pay_420000449 | C12: ORD26000470 | D12: =UPPER(SUBSTITUTE(TRIM(C12),"-","")) -> ORD26000470 | E12: 46266 | F12: CAPTURE | G12: Wallet | H12: 4297 | I12: 73.05 | J12: 13.15 | K12: 4210.8 | L12: 46268 | M12: STL-20260903 | N12: =IF(COUNTIF($A$2:A12,A12)>1,"DUP","OK") -> OK | O12: =IF(F12="REFUND",INDEX($D:$D,MATCH(B12,$A:$A,0)),D12) -> ORD26000470 | P12: =IF(L12>DATE(2026,9,30),"Oct-Due","Sep") -> Sep | Q12: =IF(F12="CAPTURE",IF(COUNTIF(orders!$A:$A,O12)>0,"Yes","NO ORDER"),"") -> Yes
A13: pay_420000460 | C13: ORD26000483 | D13: =UPPER(SUBSTITUTE(TRIM(C13),"-","")) -> ORD26000483 | E13: 46266 | F13: CAPTURE | G13: Card | H13: 898 | I13: 16.16 | J13: 2.91 | K13: 878.93 | L13: 46268 | M13: STL-20260903 | N13: =IF(COUNTIF($A$2:A13,A13)>1,"DUP","OK") -> OK | O13: =IF(F13="REFUND",INDEX($D:$D,MATCH(B13,$A:$A,0)),D13) -> ORD26000483 | P13: =IF(L13>DATE(2026,9,30),"Oct-Due","Sep") -> Sep | Q13: =IF(F13="CAPTURE",IF(COUNTIF(orders!$A:$A,O13)>0,"Yes","NO ORDER"),"") -> Yes
... A329: pay_420005677 | C329: ORD26005942 | D329: =UPPER(SUBSTITUTE(TRIM(C329),"-","")) -> ORD26005942 | E329: 46267 | F329: CAPTURE | G329: Wallet | H329: 1499 | I329: 28.48 | J329: 5.13 | K329: 1465.39 | L329: 46269 | M329: STL-20260904 | N329: =IF(COUNTIF($A$2:A329,A329)>1,"DUP","OK") -> OK | O329: =IF(F329="REFUND",INDEX($D:$D,MATCH(B329,$A:$A,0)),D329) -> ORD26005942 | P329: =IF(L329>DATE(2026,9,30),"Oct-Due","Sep") -> Sep | Q329: =IF(F329="CAPTURE",IF(COUNTIF(orders!$A:$A,O329)>0,"Yes","NO ORDER"),"") -> Yes
A330: rfnd_BDDX8L3AAXM0 | B330: pay_420002554 | D330: =UPPER(SUBSTITUTE(TRIM(C330),"-","")) | E330: 46267 | F330: REFUND | G330: Wallet | H330: 1799 | I330: 0 | J330: 0 | K330: -1799 | L330: 46269 | M330: STL-20260904 | N330: =IF(COUNTIF($A$2:A330,A330)>1,"DUP","OK") -> OK | O330: =IF(F330="REFUND",INDEX($D:$D,MATCH(B330,$A:$A,0)),D330) -> ORD26002680 | P330: =IF(L330>DATE(2026,9,30),"Oct-Due","Sep") -> Sep | Q330: =IF(F330="CAPTURE",IF(COUNTIF(orders!$A:$A,O330)>0,"Yes","NO ORDER"),"")
A331: rfnd_W6UU5WJWSTPB | B331: pay_420004896 | D331: =UPPER(SUBSTITUTE(TRIM(C331),"-","")) | E331: 46267 | F331: REFUND | G331: NetBanking | H331: 599 | I331: 0 | J331: 0 | K331: -599 | L331: 46269 | M331: STL-20260904 | N331: =IF(COUNTIF($A$2:A331,A331)>1,"DUP","OK") -> OK | O331: =IF(F331="REFUND",INDEX($D:$D,MATCH(B331,$A:$A,0)),D331) -> ORD26005124 | P331: =IF(L331>DATE(2026,9,30),"Oct-Due","Sep") -> Sep | Q331: =IF(F331="CAPTURE",IF(COUNTIF(orders!$A:$A,O331)>0,"Yes","NO ORDER"),"")
A332: pay_420000041 | C332: ORD26000042 | D332: =UPPER(SUBSTITUTE(TRIM(C332),"-","")) -> ORD26000042 | E332: 46268 | F332: CAPTURE | G332: Card | H332: 349 | I332: 6.28 | J332: 1.13 | K332: 341.59 | L332: 46270 | M332: STL-20260905 | N332: =IF(COUNTIF($A$2:A332,A332)>1,"DUP","OK") -> OK | O332: =IF(F332="REFUND",INDEX($D:$D,MATCH(B332,$A:$A,0)),D332) -> ORD26000042 | P332: =IF(L332>DATE(2026,9,30),"Oct-Due","Sep") -> Sep | Q332: =IF(F332="CAPTURE",IF(COUNTIF(orders!$A:$A,O332)>0,"Yes","NO ORDER"),"") -> Yes
A333: pay_420000078 | C333: ORD26000082 | D333: =UPPER(SUBSTITUTE(TRIM(C333),"-","")) -> ORD26000082 | E333: 46268 | F333: CAPTURE | G333: Wallet | H333: 2197 | I333: 37.35 | J333: 6.72 | K333: 2152.93 | L333: 46270 | M333: STL-20260905 | N333: =IF(COUNTIF($A$2:A333,A333)>1,"DUP","OK") -> OK | O333: =IF(F333="REFUND",INDEX($D:$D,MATCH(B333,$A:$A,0)),D333) -> ORD26000082 | P333: =IF(L333>DATE(2026,9,30),"Oct-Due","Sep") -> Sep | Q333: =IF(F333="CAPTURE",IF(COUNTIF(orders!$A:$A,O333)>0,"Yes","NO ORDER"),"") -> Yes
A334: pay_420000101 | C334: ORD26000109 | D334: =UPPER(SUBSTITUTE(TRIM(C334),"-","")) -> ORD26000109 | E334: 46268 | F334: CAPTURE | G334: UPI | H334: 599 | I334: 0 | J334: 0 | K334: 599 | L334: 46270 | M334: STL-20260905 | N334: =IF(COUNTIF($A$2:A334,A334)>1,"DUP","OK") -> OK | O334: =IF(F334="REFUND",INDEX($D:$D,MATCH(B334,$A:$A,0)),D334) -> ORD26000109 | P334: =IF(L334>DATE(2026,9,30),"Oct-Due","Sep") -> Sep | Q334: =IF(F334="CAPTURE",IF(COUNTIF(orders!$A:$A,O334)>0,"Yes","NO ORDER"),"") -> Yes
A335: pay_420000111 | C335: ORD26000119 | D335: =UPPER(SUBSTITUTE(TRIM(C335),"-","")) -> ORD26000119 | E335: 46268 | F335: CAPTURE | G335: UPI | H335: 349 | I335: 0 | J335: 0 | K335: 349 | L335: 46270 | M335: STL-20260905 | N335: =IF(COUNTIF($A$2:A335,A335)>1,"DUP","OK") -> OK | O335: =IF(F335="REFUND",INDEX($D:$D,MATCH(B335,$A:$A,0)),D335) -> ORD26000119 | P335: =IF(L335>DATE(2026,9,30),"Oct-Due","Sep") -> Sep | Q335: =IF(F335="CAPTURE",IF(COUNTIF(orders!$A:$A,O335)>0,"Yes","NO ORDER"),"") -> Yes
A336: pay_420000115 | C336: ORD26000124 | D336: =UPPER(SUBSTITUTE(TRIM(C336),"-","")) -> ORD26000124 | E336: 46268 | F336: CAPTURE | G336: Card | H336: 6397 | I336: 102.35 | J336: 18.42 | K336: 6276.23 | L336: 46270 | M336: STL-20260905 | N336: =IF(COUNTIF($A$2:A336,A336)>1,"DUP","OK") -> OK | O336: =IF(F336="REFUND",INDEX($D:$D,MATCH(B336,$A:$A,0)),D336) -> ORD26000124 | P336: =IF(L336>DATE(2026,9,30),"Oct-Due","Sep") -> Sep | Q336: =IF(F336="CAPTURE",IF(COUNTIF(orders!$A:$A,O336)>0,"Yes","NO ORDER"),"") -> Yes
A337: pay_420000228 | C337: ORD26000243 | D337: =UPPER(SUBSTITUTE(TRIM(C337),"-","")) -> ORD26000243 | E337: 46268 | F337: CAPTURE | G337: Wallet | H337: 2798 | I337: 47.57 | J337: 8.56 | K337: 2741.87 | L337: 46270 | M337: STL-20260905 | N337: =IF(COUNTIF($A$2:A337,A337)>1,"DUP","OK") -> OK | O337: =IF(F337="REFUND",INDEX($D:$D,MATCH(B337,$A:$A,0)),D337) -> ORD26000243 | P337: =IF(L337>DATE(2026,9,30),"Oct-Due","Sep") -> Sep | Q337: =IF(F337="CAPTURE",IF(COUNTIF(orders!$A:$A,O337)>0,"Yes","NO ORDER"),"") -> Yes
A338: pay_420000250 | C338: ORD26000267 | D338: =UPPER(SUBSTITUTE(TRIM(C338),"-","")) -> ORD26000267 | E338: 46268 | F338: CAPTURE | G338: UPI | H338: 4999 | I338: 15 | J338: 2.7 | K338: 4981.3 | L338: 46270 | M338: STL-20260905 | N338: =IF(COUNTIF($A$2:A338,A338)>1,"DUP","OK") -> OK | O338: =IF(F338="REFUND",INDEX($D:$D,MATCH(B338,$A:$A,0)),D338) -> ORD26000267 | P338: =IF(L338>DATE(2026,9,30),"Oct-Due","Sep") -> Sep | Q338: =IF(F338="CAPTURE",IF(COUNTIF(orders!$A:$A,O338)>0,"Yes","NO ORDER"),"") -> Yes
A339: pay_420000268 | C339: ORD26000285 | D339: =UPPER(SUBSTITUTE(TRIM(C339),"-","")) -> ORD26000285 | E339: 46268 | F339: CAPTURE | G339: Card | H339: 349 | I339: 6.28 | J339: 1.13 | K339: 341.59 | L339: 46270 | M339: STL-20260905 | N339: =IF(COUNTIF($A$2:A339,A339)>1,"DUP","OK") -> OK | O339: =IF(F339="REFUND",INDEX($D:$D,MATCH(B339,$A:$A,0)),D339) -> ORD26000285 | P339: =IF(L339>DATE(2026,9,30),"Oct-Due","Sep") -> Sep | Q339: =IF(F339="CAPTURE",IF(COUNTIF(orders!$A:$A,O339)>0,"Yes","NO ORDER"),"") -> Yes
A340: pay_420000281 | C340: ord26000298 | D340: =UPPER(SUBSTITUTE(TRIM(C340),"-","")) -> ORD26000298 | E340: 46268 | F340: CAPTURE | G340: UPI | H340: 2398 | I340: 7.19 | J340: 1.29 | K340: 2389.52 | L340: 46270 | M340: STL-20260905 | N340: =IF(COUNTIF($A$2:A340,A340)>1,"DUP","OK") -> OK | O340: =IF(F340="REFUND",INDEX($D:$D,MATCH(B340,$A:$A,0)),D340) -> ORD26000298 | P340: =IF(L340>DATE(2026,9,30),"Oct-Due","Sep") -> Sep | Q340: =IF(F340="CAPTURE",IF(COUNTIF(orders!$A:$A,O340)>0,"Yes","NO ORDER"),"") -> Yes
A341: pay_420000315 | C341: ORD26000330 | D341: =UPPER(SUBSTITUTE(TRIM(C341),"-","")) -> ORD26000330 | E341: 46268 | F341: CAPTURE | G341: UPI | H341: 3348 | I341: 10.04 | J341: 1.81 | K341: 3336.15 | L341: 46270 | M341: STL-20260905 | N341: =IF(COUNTIF($A$2:A341,A341)>1,"DUP","OK") -> OK | O341: =IF(F341="REFUND",INDEX($D:$D,MATCH(B341,$A:$A,0)),D341) -> ORD26000330 | P341: =IF(L341>DATE(2026,9,30),"Oct-Due","Sep") -> Sep | Q341: =IF(F341="CAPTURE",IF(COUNTIF(orders!$A:$A,O341)>0,"Yes","NO ORDER"),"") -> Yes
A342: pay_420000430 | C342: ORD26000447 | D342: =UPPER(SUBSTITUTE(TRIM(C342),"-","")) -> ORD26000447 | E342: 46268 | F342: CAPTURE | G342: UPI | H342: 2999 | I342: 9 | J342: 1.62 | K342: 2988.38 | L342: 46270 | M342: STL-20260905 | N342: =IF(COUNTIF($A$2:A342,A342)>1,"DUP","OK") -> OK | O342: =IF(F342="REFUND",INDEX($D:$D,MATCH(B342,$A:$A,0)),D342) -> ORD26000447 | P342: =IF(L342>DATE(2026,9,30),"Oct-Due","Sep") -> Sep | Q342: =IF(F342="CAPTURE",IF(COUNTIF(orders!$A:$A,O342)>0,"Yes","NO ORDER"),"") -> Yes
A343: pay_420000437 | C343: ord26000455 | D343: =UPPER(SUBSTITUTE(TRIM(C343),"-","")) -> ORD26000455 | E343: 46268 | F343: CAPTURE | G343: UPI | H343: 2798 | I343: 8.39 | J343: 1.51 | K343: 2788.1 | L343: 46270 | M343: STL-20260905 | N343: =IF(COUNTIF($A$2:A343,A343)>1,"DUP","OK") -> OK | O343: =IF(F343="REFUND",INDEX($D:$D,MATCH(B343,$A:$A,0)),D343) -> ORD26000455 | P343: =IF(L343>DATE(2026,9,30),"Oct-Due","Sep") -> Sep | Q343: =IF(F343="CAPTURE",IF(COUNTIF(orders!$A:$A,O343)>0,"Yes","NO ORDER"),"") -> Yes
... A519: pay_420005699 | C519: ORD26005966 | D519: =UPPER(SUBSTITUTE(TRIM(C519),"-","")) -> ORD26005966 | E519: 46268 | F519: CAPTURE | G519: UPI | H519: 2798 | I519: 8.39 | J519: 1.51 | K519: 2788.1 | L519: 46270 | M519: STL-20260905 | N519: =IF(COUNTIF($A$2:A519,A519)>1,"DUP","OK") -> OK | O519: =IF(F519="REFUND",INDEX($D:$D,MATCH(B519,$A:$A,0)),D519) -> ORD26005966 | P519: =IF(L519>DATE(2026,9,30),"Oct-Due","Sep") -> Sep | Q519: =IF(F519="CAPTURE",IF(COUNTIF(orders!$A:$A,O519)>0,"Yes","NO ORDER"),"") -> Yes
A520: rfnd_1C41Q7T6GFAL | B520: pay_420001351 | D520: =UPPER(SUBSTITUTE(TRIM(C520),"-","")) | E520: 46268 | F520: REFUND | G520: Card | H520: 9297 | I520: 0 | J520: 0 | K520: -9297 | L520: 46270 | M520: STL-20260905 | N520: =IF(COUNTIF($A$2:A520,A520)>1,"DUP","OK") -> OK | O520: =IF(F520="REFUND",INDEX($D:$D,MATCH(B520,$A:$A,0)),D520) -> ORD26001416 | P520: =IF(L520>DATE(2026,9,30),"Oct-Due","Sep") -> Sep | Q520: =IF(F520="CAPTURE",IF(COUNTIF(orders!$A:$A,O520)>0,"Yes","NO ORDER"),"")
A521: rfnd_KJKJAE6PT0EL | B521: pay_420003553 | D521: =UPPER(SUBSTITUTE(TRIM(C521),"-","")) | E521: 46268 | F521: REFUND | G521: UPI | H521: 2499 | I521: 0 | J521: 0 | K521: -2499 | L521: 46270 | M521: STL-20260905 | N521: =IF(COUNTIF($A$2:A521,A521)>1,"DUP","OK") -> OK | O521: =IF(F521="REFUND",INDEX($D:$D,MATCH(B521,$A:$A,0)),D521) -> ORD26003723 | P521: =IF(L521>DATE(2026,9,30),"Oct-Due","Sep") -> Sep | Q521: =IF(F521="CAPTURE",IF(COUNTIF(orders!$A:$A,O521)>0,"Yes","NO ORDER"),"")
A522: pay_420000042 | C522: ORD26000043 | D522: =UPPER(SUBSTITUTE(TRIM(C522),"-","")) -> ORD26000043 | E522: 46269 | F522: CAPTURE | G522: Card | H522: 3098 | I522: 49.57 | J522: 8.92 | K522: 3039.51 | L522: 46271 | M522: STL-20260906 | N522: =IF(COUNTIF($A$2:A522,A522)>1,"DUP","OK") -> OK | O522: =IF(F522="REFUND",INDEX($D:$D,MATCH(B522,$A:$A,0)),D522) -> ORD26000043 | P522: =IF(L522>DATE(2026,9,30),"Oct-Due","Sep") -> Sep | Q522: =IF(F522="CAPTURE",IF(COUNTIF(orders!$A:$A,O522)>0,"Yes","NO ORDER"),"") -> Yes
A523: pay_420000048 | C523: ORD26000050 | D523: =UPPER(SUBSTITUTE(TRIM(C523),"-","")) -> ORD26000050 | E523: 46269 | F523: CAPTURE | G523: UPI | H523: 3499 | I523: 10.5 | J523: 1.89 | K523: 3486.61 | L523: 46271 | M523: STL-20260906 | N523: =IF(COUNTIF($A$2:A523,A523)>1,"DUP","OK") -> OK | O523: =IF(F523="REFUND",INDEX($D:$D,MATCH(B523,$A:$A,0)),D523) -> ORD26000050 | P523: =IF(L523>DATE(2026,9,30),"Oct-Due","Sep") -> Sep | Q523: =IF(F523="CAPTURE",IF(COUNTIF(orders!$A:$A,O523)>0,"Yes","NO ORDER"),"") -> Yes
A524: pay_420000091 | C524: ORD-26000097 | D524: =UPPER(SUBSTITUTE(TRIM(C524),"-","")) -> ORD26000097 | E524: 46269 | F524: CAPTURE | G524: Wallet | H524: 1098 | I524: 20.86 | J524: 3.75 | K524: 1073.39 | L524: 46271 | M524: STL-20260906 | N524: =IF(COUNTIF($A$2:A524,A524)>1,"DUP","OK") -> OK | O524: =IF(F524="REFUND",INDEX($D:$D,MATCH(B524,$A:$A,0)),D524) -> ORD26000097 | P524: =IF(L524>DATE(2026,9,30),"Oct-Due","Sep") -> Sep | Q524: =IF(F524="CAPTURE",IF(COUNTIF(orders!$A:$A,O524)>0,"Yes","NO ORDER"),"") -> Yes
A525: pay_420000104 | C525: ORD26000112 | D525: =UPPER(SUBSTITUTE(TRIM(C525),"-","")) -> ORD26000112 | E525: 46269 | F525: CAPTURE | G525: UPI | H525: 10297 | I525: 30.89 | J525: 5.56 | K525: 10260.55 | L525: 46271 | M525: STL-20260906 | N525: =IF(COUNTIF($A$2:A525,A525)>1,"DUP","OK") -> OK | O525: =IF(F525="REFUND",INDEX($D:$D,MATCH(B525,$A:$A,0)),D525) -> ORD26000112 | P525: =IF(L525>DATE(2026,9,30),"Oct-Due","Sep") -> Sep | Q525: =IF(F525="CAPTURE",IF(COUNTIF(orders!$A:$A,O525)>0,"Yes","NO ORDER"),"") -> Yes
A526: pay_420000108 | C526: ORD26000116 | D526: =UPPER(SUBSTITUTE(TRIM(C526),"-","")) -> ORD26000116 | E526: 46269 | F526: CAPTURE | G526: UPI | H526: 2499 | I526: 7.5 | J526: 1.35 | K526: 2490.15 | L526: 46271 | M526: STL-20260906 | N526: =IF(COUNTIF($A$2:A526,A526)>1,"DUP","OK") -> OK | O526: =IF(F526="REFUND",INDEX($D:$D,MATCH(B526,$A:$A,0)),D526) -> ORD26000116 | P526: =IF(L526>DATE(2026,9,30),"Oct-Due","Sep") -> Sep | Q526: =IF(F526="CAPTURE",IF(COUNTIF(orders!$A:$A,O526)>0,"Yes","NO ORDER"),"") -> Yes
A527: pay_420000110 | C527: ORD26000118 | D527: =UPPER(SUBSTITUTE(TRIM(C527),"-","")) -> ORD26000118 | E527: 46269 | F527: CAPTURE | G527: UPI | H527: 5998 | I527: 17.99 | J527: 3.24 | K527: 5976.77 | L527: 46271 | M527: STL-20260906 | N527: =IF(COUNTIF($A$2:A527,A527)>1,"DUP","OK") -> OK | O527: =IF(F527="REFUND",INDEX($D:$D,MATCH(B527,$A:$A,0)),D527) -> ORD26000118 | P527: =IF(L527>DATE(2026,9,30),"Oct-Due","Sep") -> Sep | Q527: =IF(F527="CAPTURE",IF(COUNTIF(orders!$A:$A,O527)>0,"Yes","NO ORDER"),"") -> Yes
A528: pay_420000150 | C528: ORD26000160 | D528: =UPPER(SUBSTITUTE(TRIM(C528),"-","")) -> ORD26000160 | E528: 46269 | F528: CAPTURE | G528: Card | H528: 1299 | I528: 23.38 | J528: 4.21 | K528: 1271.41 | L528: 46271 | M528: STL-20260906 | N528: =IF(COUNTIF($A$2:A528,A528)>1,"DUP","OK") -> OK | O528: =IF(F528="REFUND",INDEX($D:$D,MATCH(B528,$A:$A,0)),D528) -> ORD26000160 | P528: =IF(L528>DATE(2026,9,30),"Oct-Due","Sep") -> Sep | Q528: =IF(F528="CAPTURE",IF(COUNTIF(orders!$A:$A,O528)>0,"Yes","NO ORDER"),"") -> Yes
A529: pay_420000189 | C529: ORD26000202 | D529: =UPPER(SUBSTITUTE(TRIM(C529),"-","")) -> ORD26000202 | E529: 46269 | F529: CAPTURE | G529: UPI | H529: 3499 | I529: 10.5 | J529: 1.89 | K529: 3486.61 | L529: 46271 | M529: STL-20260906 | N529: =IF(COUNTIF($A$2:A529,A529)>1,"DUP","OK") -> OK | O529: =IF(F529="REFUND",INDEX($D:$D,MATCH(B529,$A:$A,0)),D529) -> ORD26000202 | P529: =IF(L529>DATE(2026,9,30),"Oct-Due","Sep") -> Sep | Q529: =IF(F529="CAPTURE",IF(COUNTIF(orders!$A:$A,O529)>0,"Yes","NO ORDER"),"") -> Yes
A530: pay_420000207 | C530: ORD26000221 | D530: =UPPER(SUBSTITUTE(TRIM(C530),"-","")) -> ORD26000221 | E530: 46269 | F530: CAPTURE | G530: UPI | H530: 1499 | I530: 0 | J530: 0 | K530: 1499 | L530: 46271 | M530: STL-20260906 | N530: =IF(COUNTIF($A$2:A530,A530)>1,"DUP","OK") -> OK | O530: =IF(F530="REFUND",INDEX($D:$D,MATCH(B530,$A:$A,0)),D530) -> ORD26000221 | P530: =IF(L530>DATE(2026,9,30),"Oct-Due","Sep") -> Sep | Q530: =IF(F530="CAPTURE",IF(COUNTIF(orders!$A:$A,O530)>0,"Yes","NO ORDER"),"") -> Yes
A531: pay_420000253 | C531: ORD26000270 | D531: =UPPER(SUBSTITUTE(TRIM(C531),"-","")) -> ORD26000270 | E531: 46269 | F531: CAPTURE | G531: UPI | H531: 3100 | I531: 9.3 | J531: 1.67 | K531: 3089.03 | L531: 46271 | M531: STL-20260906 | N531: =IF(COUNTIF($A$2:A531,A531)>1,"DUP","OK") -> OK | O531: =IF(F531="REFUND",INDEX($D:$D,MATCH(B531,$A:$A,0)),D531) -> ORD26000270 | P531: =IF(L531>DATE(2026,9,30),"Oct-Due","Sep") -> Sep | Q531: =IF(F531="CAPTURE",IF(COUNTIF(orders!$A:$A,O531)>0,"Yes","NO ORDER"),"") -> Yes
A532: pay_420000284 | C532: ORD26000300 | D532: =UPPER(SUBSTITUTE(TRIM(C532),"-","")) -> ORD26000300 | E532: 46269 | F532: CAPTURE | G532: Card | H532: 5998 | I532: 95.97 | J532: 17.27 | K532: 5884.76 | L532: 46271 | M532: STL-20260906 | N532: =IF(COUNTIF($A$2:A532,A532)>1,"DUP","OK") -> OK | O532: =IF(F532="REFUND",INDEX($D:$D,MATCH(B532,$A:$A,0)),D532) -> ORD26000300 | P532: =IF(L532>DATE(2026,9,30),"Oct-Due","Sep") -> Sep | Q532: =IF(F532="CAPTURE",IF(COUNTIF(orders!$A:$A,O532)>0,"Yes","NO ORDER"),"") -> Yes
A533: pay_420000304 | C533: ORD26000320 | D533: =UPPER(SUBSTITUTE(TRIM(C533),"-","")) -> ORD26000320 | E533: 46269 | F533: CAPTURE | G533: Card | H533: 4498 | I533: 71.97 | J533: 12.95 | K533: 4413.08 | L533: 46271 | M533: STL-20260906 | N533: =IF(COUNTIF($A$2:A533,A533)>1,"DUP","OK") -> OK | O533: =IF(F533="REFUND",INDEX($D:$D,MATCH(B533,$A:$A,0)),D533) -> ORD26000320 | P533: =IF(L533>DATE(2026,9,30),"Oct-Due","Sep") -> Sep | Q533: =IF(F533="CAPTURE",IF(COUNTIF(orders!$A:$A,O533)>0,"Yes","NO ORDER"),"") -> Yes
... A717: pay_420005731 | C717: ORD26005998 | D717: =UPPER(SUBSTITUTE(TRIM(C717),"-","")) -> ORD26005998 | E717: 46269 | F717: CAPTURE | G717: UPI | H717: 349 | I717: 0 | J717: 0 | K717: 349 | L717: 46271 | M717: STL-20260906 | N717: =IF(COUNTIF($A$2:A717,A717)>1,"DUP","OK") -> OK | O717: =IF(F717="REFUND",INDEX($D:$D,MATCH(B717,$A:$A,0)),D717) -> ORD26005998 | P717: =IF(L717>DATE(2026,9,30),"Oct-Due","Sep") -> Sep | Q717: =IF(F717="CAPTURE",IF(COUNTIF(orders!$A:$A,O717)>0,"Yes","NO ORDER"),"") -> Yes
A718: rfnd_1R7WDBXGYHDQ | B718: pay_420002852 | D718: =UPPER(SUBSTITUTE(TRIM(C718),"-","")) | E718: 46269 | F718: REFUND | G718: UPI | H718: 5998 | I718: 0 | J718: 0 | K718: -5998 | L718: 46271 | M718: STL-20260906 | N718: =IF(COUNTIF($A$2:A718,A718)>1,"DUP","OK") -> OK | O718: =IF(F718="REFUND",INDEX($D:$D,MATCH(B718,$A:$A,0)),D718) -> ORD26002995 | P718: =IF(L718>DATE(2026,9,30),"Oct-Due","Sep") -> Sep | Q718: =IF(F718="CAPTURE",IF(COUNTIF(orders!$A:$A,O718)>0,"Yes","NO ORDER"),"")
A719: rfnd_GKK57QSMZQR7 | B719: pay_420003990 | D719: =UPPER(SUBSTITUTE(TRIM(C719),"-","")) | E719: 46269 | F719: REFUND | G719: Card | H719: 7999 | I719: 0 | J719: 0 | K719: -7999 | L719: 46271 | M719: STL-20260906 | N719: =IF(COUNTIF($A$2:A719,A719)>1,"DUP","OK") -> OK | O719: =IF(F719="REFUND",INDEX($D:$D,MATCH(B719,$A:$A,0)),D719) -> ORD26004177 | P719: =IF(L719>DATE(2026,9,30),"Oct-Due","Sep") -> Sep | Q719: =IF(F719="CAPTURE",IF(COUNTIF(orders!$A:$A,O719)>0,"Yes","NO ORDER"),"")
A720: pay_420000116 | C720: ORD26000125 | D720: =UPPER(SUBSTITUTE(TRIM(C720),"-","")) -> ORD26000125 | E720: 46270 | F720: CAPTURE | G720: UPI | H720: 3598 | I720: 10.79 | J720: 1.94 | K720: 3585.27 | L720: 46272 | M720: STL-20260907 | N720: =IF(COUNTIF($A$2:A720,A720)>1,"DUP","OK") -> OK | O720: =IF(F720="REFUND",INDEX($D:$D,MATCH(B720,$A:$A,0)),D720) -> ORD26000125 | P720: =IF(L720>DATE(2026,9,30),"Oct-Due","Sep") -> Sep | Q720: =IF(F720="CAPTURE",IF(COUNTIF(orders!$A:$A,O720)>0,"Yes","NO ORDER"),"") -> Yes
A721: pay_420000220 | C721: ORD26000235 | D721: =UPPER(SUBSTITUTE(TRIM(C721),"-","")) -> ORD26000235 | E721: 46270 | F721: CAPTURE | G721: NetBanking | H721: 1798 | I721: 26.97 | J721: 4.85 | K721: 1766.18 | L721: 46272 | M721: STL-20260907 | N721: =IF(COUNTIF($A$2:A721,A721)>1,"DUP","OK") -> OK | O721: =IF(F721="REFUND",INDEX($D:$D,MATCH(B721,$A:$A,0)),D721) -> ORD26000235 | P721: =IF(L721>DATE(2026,9,30),"Oct-Due","Sep") -> Sep | Q721: =IF(F721="CAPTURE",IF(COUNTIF(orders!$A:$A,O721)>0,"Yes","NO ORDER"),"") -> Yes
A722: pay_420000266 | C722: ORD26000283 | D722: =UPPER(SUBSTITUTE(TRIM(C722),"-","")) -> ORD26000283 | E722: 46270 | F722: CAPTURE | G722: Card | H722: 5097 | I722: 81.55 | J722: 14.68 | K722: 5000.77 | L722: 46272 | M722: STL-20260907 | N722: =IF(COUNTIF($A$2:A722,A722)>1,"DUP","OK") -> OK | O722: =IF(F722="REFUND",INDEX($D:$D,MATCH(B722,$A:$A,0)),D722) -> ORD26000283 | P722: =IF(L722>DATE(2026,9,30),"Oct-Due","Sep") -> Sep | Q722: =IF(F722="CAPTURE",IF(COUNTIF(orders!$A:$A,O722)>0,"Yes","NO ORDER"),"") -> Yes
A723: pay_420000267 | C723: ORD26000284 | D723: =UPPER(SUBSTITUTE(TRIM(C723),"-","")) -> ORD26000284 | E723: 46270 | F723: CAPTURE | G723: Wallet | H723: 2999 | I723: 50.98 | J723: 9.18 | K723: 2938.84 | L723: 46272 | M723: STL-20260907 | N723: =IF(COUNTIF($A$2:A723,A723)>1,"DUP","OK") -> OK | O723: =IF(F723="REFUND",INDEX($D:$D,MATCH(B723,$A:$A,0)),D723) -> ORD26000284 | P723: =IF(L723>DATE(2026,9,30),"Oct-Due","Sep") -> Sep | Q723: =IF(F723="CAPTURE",IF(COUNTIF(orders!$A:$A,O723)>0,"Yes","NO ORDER"),"") -> Yes
A724: pay_420000320 | C724: ORD26000335 | D724: =UPPER(SUBSTITUTE(TRIM(C724),"-","")) -> ORD26000335 | E724: 46270 | F724: CAPTURE | G724: Card | H724: 5998 | I724: 95.97 | J724: 17.27 | K724: 5884.76 | L724: 46272 | M724: STL-20260907 | N724: =IF(COUNTIF($A$2:A724,A724)>1,"DUP","OK") -> OK | O724: =IF(F724="REFUND",INDEX($D:$D,MATCH(B724,$A:$A,0)),D724) -> ORD26000335 | P724: =IF(L724>DATE(2026,9,30),"Oct-Due","Sep") -> Sep | Q724: =IF(F724="CAPTURE",IF(COUNTIF(orders!$A:$A,O724)>0,"Yes","NO ORDER"),"") -> Yes
A725: pay_420000329 | C725: ORD26000345 | D725: =UPPER(SUBSTITUTE(TRIM(C725),"-","")) -> ORD26000345 | E725: 46270 | F725: CAPTURE | G725: UPI | H725: 9347 | I725: 28.04 | J725: 5.05 | K725: 9313.91 | L725: 46272 | M725: STL-20260907 | N725: =IF(COUNTIF($A$2:A725,A725)>1,"DUP","OK") -> OK | O725: =IF(F725="REFUND",INDEX($D:$D,MATCH(B725,$A:$A,0)),D725) -> ORD26000345 | P725: =IF(L725>DATE(2026,9,30),"Oct-Due","Sep") -> Sep | Q725: =IF(F725="CAPTURE",IF(COUNTIF(orders!$A:$A,O725)>0,"Yes","NO ORDER"),"") -> Yes
A726: pay_420000387 | C726: ORD26000405 | D726: =UPPER(SUBSTITUTE(TRIM(C726),"-","")) -> ORD26000405 | E726: 46270 | F726: CAPTURE | G726: Card | H726: 2197 | I726: 35.15 | J726: 6.33 | K726: 2155.52 | L726: 46272 | M726: STL-20260907 | N726: =IF(COUNTIF($A$2:A726,A726)>1,"DUP","OK") -> OK | O726: =IF(F726="REFUND",INDEX($D:$D,MATCH(B726,$A:$A,0)),D726) -> ORD26000405 | P726: =IF(L726>DATE(2026,9,30),"Oct-Due","Sep") -> Sep | Q726: =IF(F726="CAPTURE",IF(COUNTIF(orders!$A:$A,O726)>0,"Yes","NO ORDER"),"") -> Yes
A727: pay_420000389 | C727: ORD26000408 | D727: =UPPER(SUBSTITUTE(TRIM(C727),"-","")) -> ORD26000408 | E727: 46270 | F727: CAPTURE | G727: UPI | H727: 2999 | I727: 9 | J727: 1.62 | K727: 2988.38 | L727: 46272 | M727: STL-20260907 | N727: =IF(COUNTIF($A$2:A727,A727)>1,"DUP","OK") -> OK | O727: =IF(F727="REFUND",INDEX($D:$D,MATCH(B727,$A:$A,0)),D727) -> ORD26000408 | P727: =IF(L727>DATE(2026,9,30),"Oct-Due","Sep") -> Sep | Q727: =IF(F727="CAPTURE",IF(COUNTIF(orders!$A:$A,O727)>0,"Yes","NO ORDER"),"") -> Yes
A728: pay_420000486 | C728: ORD26000510 | D728: =UPPER(SUBSTITUTE(TRIM(C728),"-","")) -> ORD26000510 | E728: 46270 | F728: CAPTURE | G728: Wallet | H728: 8598 | I728: 146.17 | J728: 26.31 | K728: 8425.52 | L728: 46272 | M728: STL-20260907 | N728: =IF(COUNTIF($A$2:A728,A728)>1,"DUP","OK") -> OK | O728: =IF(F728="REFUND",INDEX($D:$D,MATCH(B728,$A:$A,0)),D728) -> ORD26000510 | P728: =IF(L728>DATE(2026,9,30),"Oct-Due","Sep") -> Sep | Q728: =IF(F728="CAPTURE",IF(COUNTIF(orders!$A:$A,O728)>0,"Yes","NO ORDER"),"") -> Yes
A729: pay_420000504 | C729: ORD26000526 | D729: =UPPER(SUBSTITUTE(TRIM(C729),"-","")) -> ORD26000526 | E729: 46270 | F729: CAPTURE | G729: UPI | H729: 999 | I729: 0 | J729: 0 | K729: 999 | L729: 46272 | M729: STL-20260907 | N729: =IF(COUNTIF($A$2:A729,A729)>1,"DUP","OK") -> OK | O729: =IF(F729="REFUND",INDEX($D:$D,MATCH(B729,$A:$A,0)),D729) -> ORD26000526 | P729: =IF(L729>DATE(2026,9,30),"Oct-Due","Sep") -> Sep | Q729: =IF(F729="CAPTURE",IF(COUNTIF(orders!$A:$A,O729)>0,"Yes","NO ORDER"),"") -> Yes
A730: pay_420000520 | C730: ORD26000545 | D730: =UPPER(SUBSTITUTE(TRIM(C730),"-","")) -> ORD26000545 | E730: 46270 | F730: CAPTURE | G730: Card | H730: 998 | I730: 17.96 | J730: 3.23 | K730: 976.81 | L730: 46272 | M730: STL-20260907 | N730: =IF(COUNTIF($A$2:A730,A730)>1,"DUP","OK") -> OK | O730: =IF(F730="REFUND",INDEX($D:$D,MATCH(B730,$A:$A,0)),D730) -> ORD26000545 | P730: =IF(L730>DATE(2026,9,30),"Oct-Due","Sep") -> Sep | Q730: =IF(F730="CAPTURE",IF(COUNTIF(orders!$A:$A,O730)>0,"Yes","NO ORDER"),"") -> Yes
A731: pay_420000578 | C731: ORD26000599 | D731: =UPPER(SUBSTITUTE(TRIM(C731),"-","")) -> ORD26000599 | E731: 46270 | F731: CAPTURE | G731: UPI | H731: 7999 | I731: 24 | J731: 4.32 | K731: 7970.68 | L731: 46272 | M731: STL-20260907 | N731: =IF(COUNTIF($A$2:A731,A731)>1,"DUP","OK") -> OK | O731: =IF(F731="REFUND",INDEX($D:$D,MATCH(B731,$A:$A,0)),D731) -> ORD26000599 | P731: =IF(L731>DATE(2026,9,30),"Oct-Due","Sep") -> Sep | Q731: =IF(F731="CAPTURE",IF(COUNTIF(orders!$A:$A,O731)>0,"Yes","NO ORDER"),"") -> Yes
... A900: pay_420005709 | C900: ORD26005977 | D900: =UPPER(SUBSTITUTE(TRIM(C900),"-","")) -> ORD26005977 | E900: 46270 | F900: CAPTURE | G900: UPI | H900: 2999 | I900: 9 | J900: 1.62 | K900: 2988.38 | L900: 46272 | M900: STL-20260907 | N900: =IF(COUNTIF($A$2:A900,A900)>1,"DUP","OK") -> OK | O900: =IF(F900="REFUND",INDEX($D:$D,MATCH(B900,$A:$A,0)),D900) -> ORD26005977 | P900: =IF(L900>DATE(2026,9,30),"Oct-Due","Sep") -> Sep | Q900: =IF(F900="CAPTURE",IF(COUNTIF(orders!$A:$A,O900)>0,"Yes","NO ORDER"),"") -> Yes
